Workbook

Sheet Feature_Controls
A1: Features | B1: View | C1: Manage | D1: Control | E1: Process | F1: Limitations | G1: Additional Limitations | H1: Column1
A2: Accounts | B2: Yes | C2: No | D2: No | E2: No | F2: Available in all packages | H2: =COUNTIF(Feature_Controls[[#This Row],[View]:[Process]],"Yes") -> 1
A3: Allocations (New Issues) | B3: No | C3: Yes | D3: No | E3: No | F3: cannot be assigned without orders | H3: =COUNTIF(Feature_Controls[[#This Row],[View]:[Process]],"Yes") -> 1
A4: Bulk Document Upload | B4: Yes | C4: No | D4: No | E4: No | F4: Available in all packages | H4: =COUNTIF(Feature_Controls[[#This Row],[View]:[Process]],"Yes") -> 1
A5: CRMA | B5: Yes | C5: No | D5: No | E5: No | F5: Available in all packages | H5: =COUNTIF(Feature_Controls[[#This Row],[View]:[Process]],"Yes") -> 1
A6: CRS-FATCA | B6: Yes | C6: Yes | D6: No | E6: No | G6: Manage is not possible without View | H6: =COUNTIF(Feature_Controls[[#This Row],[View]:[Process]],"Yes") -> 2
A7: Compass (Legacy) | B7: Yes | C7: No | D7: No | E7: No | F7: Available in all packages | H7: =COUNTIF(Feature_Controls[[#This Row],[View]:[Process]],"Yes") -> 1
A8: Data Export | B8: Yes | C8: No | D8: No | E8: No | F8: Available in all packages | H8: =COUNTIF(Feature_Controls[[#This Row],[View]:[Process]],"Yes") -> 1
A9: FundFacts/FundFacts History | B9: No | C9: Yes | D9: No | E9: No | F9: cannot be assigned without Trade Allocations | H9: =COUNTIF(Feature_Controls[[#This Row],[View]:[Process]],"Yes") -> 1
A10: Manage Equity Orders | B10: No | C10: Yes | D10: No | E10: No | F10: cannot be assigned without orders | H10: =COUNTIF(Feature_Controls[[#This Row],[View]:[Process]],"Yes") -> 1
A11: Manage Mutual Fund Orders | B11: No | C11: Yes | D11: No | E11: No | F11: cannot be assigned without orders | H11: =COUNTIF(Feature_Controls[[#This Row],[View]:[Process]],"Yes") -> 1
A12: Manage Options Orders | B12: No | C12: Yes | D12: No | E12: No | F12: cannot be assigned without orders | H12: =COUNTIF(Feature_Controls[[#This Row],[View]:[Process]],"Yes") -> 1
A13: MaxLite | B13: Yes | C13: No | D13: No | E13: No | F13: cannot be assigned without Trade Allocations | H13: =COUNTIF(Feature_Controls[[#This Row],[View]:[Process]],"Yes") -> 1
A14: MyPortfolio+ IA | B14: Yes | C14: No | D14: No | E14: No | F14: Available in all packages | H14: =COUNTIF(Feature_Controls[[#This Row],[View]:[Process]],"Yes") -> 1
A15: MyPortfolio+ User Admin | B15: No | C15: Yes | D15: No | E15: No | F15: Only available under client user management | H15: =COUNTIF(Feature_Controls[[#This Row],[View]:[Process]],"Yes") -> 1
A16: Onboarding: Approve Option Applications | B16: No | C16: No | D16: Yes | E16: No | F16: cannot be assigned without Paper Upload | H16: =COUNTIF(Feature_Controls[[#This Row],[View]:[Process]],"Yes") -> 1
A17: Onboarding: Form Applications | B17: Yes | C17: No | D17: No | E17: No | H17: =COUNTIF(Feature_Controls[[#This Row],[View]:[Process]],"Yes") -> 1
A18: Onboarding: Paper Upload | B18: Yes | C18: Yes | D18: Yes | E18: Yes | G18: Possible combinations are: View View + Manage View + Control View + Process | H18: =COUNTIF(Feature_Controls[[#This Row],[View]:[Process]],"Yes") -> 4
A19: Orders | B19: Yes | C19: No | D19: No | E19: No | H19: =COUNTIF(Feature_Controls[[#This Row],[View]:[Process]],"Yes") -> 1
A20: Orders: GIC | B20: No | C20: Yes | D20: No | E20: No | F20: cannot be assigned without orders | H20: =COUNTIF(Feature_Controls[[#This Row],[View]:[Process]],"Yes") -> 1
A21: Orders: MF Uploads | B21: No | C21: Yes | D21: No | E21: No | F21: cannot be assigned without orders | H21: =COUNTIF(Feature_Controls[[#This Row],[View]:[Process]],"Yes") -> 1
A22: Servicing | B22: Yes | C22: Yes | D22: No | E22: No | G22: Manage is not possible without View | H22: =COUNTIF(Feature_Controls[[#This Row],[View]:[Process]],"Yes") -> 2
A23: Servicing: Approvals | B23: No | C23: No | D23: Yes | E23: No | H23: =COUNTIF(Feature_Controls[[#This Row],[View]:[Process]],"Yes") -> 1
A24: Statements | B24: Yes | C24: No | D24: No | E24: No | F24: Available in all packages | H24: =COUNTIF(Feature_Controls[[#This Row],[View]:[Process]],"Yes") -> 1
A25: Tax Documents | B25: Yes | C25: No | D25: No | E25: No | F25: Available in all packages | H25: =COUNTIF(Feature_Controls[[#This Row],[View]:[Process]],"Yes") -> 1
A26: Tools | B26: Yes | C26: No | D26: No | E26: No | F26: Available in all packages | H26: =COUNTIF(Feature_Controls[[#This Row],[View]:[Process]],"Yes") -> 1
A27: Trade Allocations | B27: Yes | C27: Yes | D27: No | E27: No | G27: Manage is not possible without View | H27: =COUNTIF(Feature_Controls[[#This Row],[View]:[Process]],"Yes") -> 2
A28: Trade Allocations: Approvals | B28: No | C28: No | D28: Yes | E28: No | F28: cannot be assigned without Trade Allocations | H28: =COUNTIF(Feature_Controls[[#This Row],[View]:[Process]],"Yes") -> 1
A29: Trade Allocations: Processing | B29: No | C29: No | D29: No | E29: Yes | F29: cannot be assigned without Trade Allocations | H29: =COUNTIF(Feature_Controls[[#This Row],[View]:[Process]],"Yes") -> 1
A30: Trade Confirmations | B30: Yes | C30: No | D30: No | E30: No | F30: Available in all packages | H30: =COUNTIF(Feature_Controls[[#This Row],[View]:[Process]],"Yes") -> 1
A31: Unified Access Requests | B31: Yes | C31: Yes | D31: No | E31: Yes | F31: Only available under client user management | G31: Possible combinations are: View View + Manage View + Process | H31: =COUNTIF(Feature_Controls[[#This Row],[View]:[Process]],"Yes") -> 3
A32: View System Health Events | B32: Yes | C32: No | D32: No | E32: No | H32: =COUNTIF(Feature_Controls[[#This Row],[View]:[Process]],"Yes") -> 1
A33: Web Panagon | B33: Yes | C33: No | D33: No | E33: No | F33: Available in all packages | H33: =COUNTIF(Feature_Controls[[#This Row],[View]:[Process]],"Yes") -> 1

Sheet Rules Summary
A1: Rules Used to Generate the 50 Logical Requirements
A3: Purpose
A4: Identify logical capability-control combinations that may require a supporting preconfigured user package. Feature-level mapping will be assessed separately.
A6: Rule | B6: Application
A7: 1. View-only capabilities remain included | B7: The nine capabilities that only offer View remain visible and are fixed at View in each of the 48 standard combinations.
A8: 2. Four capabilities drive the standard combinations | B8: Client Lifecycle Management, Client Servicing, Order Management and Trade Operations are the capabilities whose controls vary.
A9: 3. None is not treated as a selectable control | B9: Each of the four variable capabilities has a selected control in every standard combination.
A10: 4. Client Servicing Process is excluded | B10: Client Servicing uses View, Manage and Control only. Process is not included in any scenario.
A11: 5. Other valid controls are retained | B11: Lifecycle uses View, Manage, Control and Process; Order Management uses View and Manage; Trade Operations uses View and Manage; Control is excluded.
A12: 6. Manage includes View | B12: Manage is recorded once as the selected control. A separate View plus Manage state is not generated.
A13: 7. User Access Management is exclusive | B13: User Access Management cannot coexist with another capability and is represented by two standalone requirements: View and Manage.
A14: 8. Features are outside this list | B14: This list covers capability-control patterns only. Eligible features will be mapped separately.
A17: Count calculation
A18: Standard combinations | B18: 4 × 3 × 2 × 2 = 48
A19: User Access Management standalone | B19: 2
A20: Total | B20: 50
A22: Important interpretation
A23: This list covers cases where all four main capabilities have a selected control. It does not separately list requests where one or more of the four main capabilities are left out. User Access Management is listed separately because it cannot be combined with any other capability.

Sheet 50 Requirements
A1: Requirement ID | B1: Application Links | C1: Application SSO | D1: Client Inquiry & Insights | E1: Client Lifecycle Management | F1: Client Servicing | G1: Data and Reporting | H1: Fee Management | I1: Investor Portal | J1: Managed Portfolios | K1: Order Management | L1: Reference Data | M1: Trade Operations | N1: Trading Tools | O1: User Access Management
A2: REQ-001 | B2: View | C2: View | D2: View | E2: View | F2: View | G2: View | H2: View | I2: View | J2: View | K2: View | L2: View | M2: View | N2: View | O2: Not applicable
A3: REQ-002 | B3: View | C3: View | D3: View | E3: View | F3: View | G3: View | H3: View | I3: View | J3: View | K3: View | L3: View | M3: Manage | N3: View | O3: Not applicable
A4: REQ-003 | B4: View | C4: View | D4: View | E4: View | F4: View | G4: View | H4: View | I4: View | J4: View | K4: Manage | L4: View | M4: View | N4: View | O4: Not applicable
A5: REQ-004 | B5: View | C5: View | D5: View | E5: View | F5: View | G5: View | H5: View | I5: View | J5: View | K5: Manage | L5: View | M5: Manage | N5: View | O5: Not applicable
A6: REQ-005 | B6: View | C6: View | D6: View | E6: View | F6: Manage | G6: View | H6: View | I6: View | J6: View | K6: View | L6: View | M6: View | N6: View | O6: Not applicable
A7: REQ-006 | B7: View | C7: View | D7: View | E7: View | F7: Manage | G7: View | H7: View | I7: View | J7: View | K7: View | L7: View | M7: Manage | N7: View | O7: Not applicable
A8: REQ-007 | B8: View | C8: View | D8: View | E8: View | F8: Manage | G8: View | H8: View | I8: View | J8: View | K8: Manage | L8: View | M8: View | N8: View | O8: Not applicable
A9: REQ-008 | B9: View | C9: View | D9: View | E9: View | F9: Manage | G9: View | H9: View | I9: View | J9: View | K9: Manage | L9: View | M9: Manage | N9: View | O9: Not applicable
A10: REQ-009 | B10: View | C10: View | D10: View | E10: View | F10: Control | G10: View | H10: View | I10: View | J10: View | K10: View | L10: View | M10: View | N10: View | O10: Not applicable
A11: REQ-010 | B11: View | C11: View | D11: View | E11: View | F11: Control | G11: View | H11: View | I11: View | J11: View | K11: View | L11: View | M11: Manage | N11: View | O11: Not applicable
A12: REQ-011 | B12: View | C12: View | D12: View | E12: View | F12: Control | G12: View | H12: View | I12: View | J12: View | K12: Manage | L12: View | M12: View | N12: View | O12: Not applicable
... A51: REQ-050 | B51: Not applicable | C51: Not applicable | D51: Not applicable | E51: Not applicable | F51: Not applicable | G51: Not applicable | H51: Not applicable | I51: Not applicable | J51: Not applicable | K51: Not applicable | L51: Not applicable | M51: Not applicable | N51: Not applicable | O51: Manage

Sheet Control Options
A1: Capability | B1: Options represented | C1: Treatment
A2: Application Links | B2: View | C2: Fixed at View in the 48 standard combinations
A3: Application SSO | B3: View | C3: Fixed at View in the 48 standard combinations
A4: Client Inquiry & Insights | B4: View | C4: Fixed at View in the 48 standard combinations
A5: Client Lifecycle Management | B5: View, Manage, Control, Process | C5: Varied in the 48 standard combinations
A6: Client Servicing | B6: View, Manage, Control | C6: Varied in the 48 standard combinations
A7: Data and Reporting | B7: View | C7: Fixed at View in the 48 standard combinations
A8: Fee Management | B8: View | C8: Fixed at View in the 48 standard combinations
A9: Investor Portal | B9: View | C9: Fixed at View in the 48 standard combinations
A10: Managed Portfolios | B10: View | C10: Fixed at View in the 48 standard combinations
A11: Order Management | B11: View, Manage | C11: Varied in the 48 standard combinations
A12: Reference Data | B12: View | C12: Fixed at View in the 48 standard combinations
... A15: User Access Management | B15: View, Manage | C15: Standalone and exclusive

Sheet Reference
A1: Product | B1: Control | D1: Feature control options
A2: Application Links | B2: View | D2: V
A3: Application SSO | B3: View | D3: V-O
A4: Client Inquiry & Insights | B4: View | D4: M
A5: Client Lifecycle Management | B5: View | D5: M-O
A6: Client Lifecycle Management | B6: Manage | D6: C
A7: Client Lifecycle Management | B7: Control | D7: C-O
A8: Client Lifecycle Management | B8: Process | D8: P
A9: Client Servicing | B9: View | D9: n/a
A10: Client Servicing | B10: Manage
A11: Client Servicing | B11: Control
A12: Client Servicing | B12: Process
A13: Data and Reporting | B13: View
A14: Fee Management | B14: View
A15: Investor Portal | B15: View
A16: Managed Portfolios | B16: View
A17: Order Management | B17: View
A18: Order Management | B18: Manage
A19: Reference Data | B19: View
A20: Trade Operations | B20: View
A21: Trade Operations | B21: Manage
... A25: User Access Management | B25: Manage
A30: Out of Scope - these are internal or apply to all users and don't need to be on UAR
A31: Product | B31: Control
A32: Application Status | B32: View
A33: Feature Management | B33: Manage
A34: Firm Configuration | B34: View
A35: Firm Configuration | B35: Manage
A36: User Communications | B36: View
A37: User Communications | B37: Manage
A38: User Content | B38: View
A39: User Settings | B39: View
A40: User Settings | B40: Manage

Sheet Full Map - OLD(98)
P1: Product | Q1: Client Inquiry & Insights | AG1: Investor Portal | AI1: Client Lifecycle Management | AT1: Client Servicing | BH1: Order Management | BQ1: Trade Operations | CH1: Trading Tools | CL1: Managed Portfolios | CM1: Data and Reporting | CQ1: Fee Management | CS1: Reference Data | CV1: User Access Management | DD1: Application Links | DG1: Application SSO
P2: Feature | Q2: Client & Account Summary | R2: Client Profile | S2: Client Profile | T2: Client Documents | U2: Account Profile | V2: Account Profile | W2: Account Holdings | X2: Account Activity | Y2: Account Profile | Z2: Account Profile | AA2: Account Documents | AB2: Account Documents | AC2: Account Documents | AD2: Account Documents | AE2: Account Documents | AF2: Client & Account Summary | AG2: Investor Portal Advisor View | AH2: Investor Portal Document Upload | AI2: Form-based Onboarding | AJ2: Paper Upload | AK2: CRS-FACTA Submissions | AL2: CRS-FACTA Submissions | AM2: Add Account | AN2: Client Profile Modifications | AO2: Client Profile Modifications | AP2: Estate Settlement | AQ2: Estate Settlement | AR2: Estate Settlement Resource | AS2: NBIN Document Resource Centre | AT2: Transfer Alerts | AU2: Transfer Statuses | AV2: Transfers Management | AW2: Transfers Management | AX2: Servicing | AY2: Servicing | AZ2: Systematic Plans | BA2: Systematic Plans | BB2: DRIP | BC2: Book Value Adjustments | BD2: Internal Transfers (Journals) | BE2: Tax Slip Events | BF2: Tax Slip Maintenance | BG2: Maturing Instruments | BH2: Core Orders Monitoring | BI2: Core Orders: Mutual Funds | BJ2: Core Orders: Equity | BK2: Core Orders: Options | BL2: Basket Orders | BM2: Basket Orders | BN2: GIC | BO2: New Issues | BP2: Equity Borrowing | BQ2: Trade Allocations | BR2: Trade Allocations | BS2: Trade Allocations | BT2: Trade Allocations | BU2: Trade Allocations | BV2: Trade Allocations | BW2: Option Expiry | BX2: Option Expiry | BY2: Options Commissions | BZ2: Options Email Delivery | CA2: Options Positions | CB2: Options Positions | CC2: View Re-Org Events | CD2: Re-Org Events | CE2: View Re-Org Events | CF2: Fund Facts | CG2: Fund Facts | CH2: NBF Research | CI2: NBF Research | CJ2: Evercore Research | CK2: Strucutred Products | CL2: Managed Portfolio Solutions | CM2: Credit Monitoring | CN2: Data Exports | CO2: Firm Reports | CP2: Firm Reports | CQ2: Management Fees Upload | CR2: Custody Fee Management | CS2: Historical FX Rates | CT2: Live Exchange Rates | CU2: Quotes | CV2: Client User Management | CW2: Global User Management | CX2: Global User Management | CY2: Global User Management | CZ2: Global User Management | DA2: Global User Management | DB2: Global User Management | DC2: Global User Management | DD2: Compass (Legacy) | DE2: Tools | DF2: NetRep | DG2: Creosus | DH2: D1G1T | DI2: Harmony
P3: Module | Q3: Accounts | R3: Client Accounts | S3: Client Profile | T3: Profile Documents | U3: Account Profile | V3: Accounts | W3: Positions | X3: Transactions | Y3: Accounts | Z3: Accounts | AA3: Statements | AB3: Tax Documents | AC3: Trade Confirmations | AD3: Securities Lending Reports | AE3: Estate Tax Slips | AF3: Activity Monitoring | AG3: My Portfolio+ IA | AH3: Bulk Document Upload | AI3: Form-Based Onboarding | AJ3: Paper Upload | AK3: CRS-FACTA Submissions | AL3: CRS-FACTA Submissions | AM3: Accounts | AN3: myRequest | AO3: TBC | AP3: Estate Settlement | AQ3: myRequest | AR3: Tools | AS3: Tools | AT3: Transfers Management | AU3: Transfers Management | AV3: Transfers Management | AW3: Transfers Management | AX3: Servicing | AY3: Servicing | AZ3: Systematic Plans (R2) | BA3: Systematic Plans | BB3: Tools | BC3: File Uploads | BD3: File Uploads | BE3: My Tax Slip Info | BF3: Tax Slip Maintenance & Notifications | BG3: Tools | BH3: Orders | BI3: Orders | BJ3: Orders | BK3: Orders | BL3: Basket Orders | BM3: File Uploads | BN3: GIC | BO3: Allocations | BP3: Tools | BQ3: MaxLite | BR3: Trade Allocations | BS3: Trade Allocations | BT3: Trade Allocation Approvals | BU3: Trade Allocation Processing | BV3: File Uploads | BW3: Option Expiry Events | BX3: Option Expiry Events (?) | BY3: Options Positions | BZ3: Options Positions | CA3: Options Positions | CB3: Options Management | CC3: Tools | CD3: File Uploads | CE3: Re-org Management | CF3: Fund Facts | CG3: Fund Facts | CH3: NBF Research | CI3: NBF Research | CJ3: Evercore Research | CK3: Trading Tools | CL3: Managed Portfolio Solutions | CM3: CRMA | CN3: Data Export | CO3: Firm Reporting | CP3: WebPanagon | CQ3: File Upload: Management Fees - Single/Batch | CR3: Fees | CS3: Tools | CT3: Tools | CU3: Tools | CV3: MyPortfolio+ User Admin | CW3: Users | CX3: Users | CY3: Users | CZ3: Users | DA3: Users | DB3: Manage Attestations | DC3: Manage Attestations | DD3: Compass (Legacy) | DE3: Application Links - E Trans (FIS) | DF3: Application Links - NetRep | DG3: Creosus | DH3: DIGIT | DI3: Harmony
P4: Module Resource | Q4: View Firm Client Accounts | R4: View Client Accounts | S4: View Client Profile | T4: Client Profile Documents | U4: View Account Profile | V4: Account Memos | W4: Positions | X4: Transactions | Y4: Account Fees | Z4: Fund Account Display | AA4: Statements | AB4: Tax Slips | AC4: Trade Confirmations | AD4: Securities Lending Reports | AE4: Estate Tax Slips | AF4: Activity Monitoring | AG4: Access My Portfolio+ IA | AH4: Access Bulk Document Upload | AI4: Form-based Onboarding | AJ4: Paper Upload | AK4: CRS-FATCA Submissions - View | AL4: CRS-FATCA Submissions - Manage | AM4: Add Account | AN4: MyRequest Banking & Address Updates | AO4: Client Profile Modifications | AP4: Estate Settlement | AQ4: Estate Settlement | AR4: Tools | AS4: NBIN Document Resource Centre | AT4: Transfer Alerts | AU4: Transfers statuses | AV4: Transfers | AW4: Transfers Management | AX4: Access Servicing | AY4: Access Servicing > Approvals | AZ4: Systematic Plans | BA4: Systematic Plans | BB4: Tools | BC4: File Upload: Book Value Updates | BD4: File Upload: Journal Processing | BE4: My Tax Slip Info | BF4: Tax Slip Maintenance & Notifications | BG4: Tools | BH4: Orders | BI4: Manage Mutual Fund Orders | BJ4: Manage Equity Orders | BK4: Manage Option Orders | BL4: Manage Basket Orders | BM4: Mutual Fund File Upload | BN4: Access GIC | BO4: Access New Issues | BP4: Tools | BQ4: Access Maxlite | BR4: View Trade Allocations | BS4: Manage Trade Allocations | BT4: Trade Allocation Approvals | BU4: Trade Allocation Processing | BV4: Trade Advice File Upload | BW4: Option Expiry Events | BX4: Option Expiry Events > Uploads | BY4: Tools - Options Commissions | BZ4: Tools - Options Email Delivery Log | CA4: Tools - Options Positions | CB4: Options Management TBC | CC4: Tools | CD4: Re-Org Events >. Uploads | CE4: Re-Org Events TBC | CF4: Access Send Fund Facts | CG4: Access Fund Facts History | CH4: NBF Research | CI4: NBF Research | CJ4: Evercore Research | CK4: Structured Products | CL4: Application Links - Managed Portfolio Solutions (MPS) | CM4: Access CRMA | CN4: Access Data Export | CO4: Access Firm Reporting | CP4: Access WebPanagon | CQ4: File Upload: Management Fees - Single/Batch | CR4: TBC | CS4: Tools | CT4: Tools - Live Exchange Rates | CU4: Delayed Quotes | CV4: Access MyPortfolio+ User Admin | CW4: Users | CX4: SSO Users | CY4: Users > Uploads | CZ4: Users > Exports | DA4: Tools - Manage Firm Users | DB4: Firm Attestations | DC4: Attestations | DD4: Compass (Legacy) | DE4: Application Links - E Trans (FIS) | DF4: Application Links - NetRep | DG4: Creosus | DH4: DIGIT | DI4: Harmony
A5: Requirement ID | B5: Application Links | C5: Application SSO | D5: Client Inquiry & Insights | E5: Client Lifecycle Management | F5: Client Servicing | G5: Data and Reporting | H5: Fee Management | I5: Investor Portal | J5: Managed Portfolios | K5: Order Management | L5: Reference Data | M5: Trade Operations | N5: Trading Tools | O5: User Access Management | P5: Role
A6: REQ-001 | B6: View | C6: View | D6: View | E6: View | F6: View | G6: View | H6: View | I6: View | J6: View | K6: View | L6: View | M6: View | N6: View | O6: Not applicable | P6: ViewOnlyConfidentialProfile_V1.17 | Q6: V | R6: V | S6: V | T6: V | U6: V | V6: V | W6: V | X6: V | Y6: V-O | Z6: V-O | AA6: V-O | AB6: V-O | AC6: V-O | AD6: V-O | AE6: V-O | AG6: V-O | AH6: V-O | AI6: V | AJ6: V | AK6: V-O | AL6: n/a | AM6: V | AN6: V | AO6: V | AQ6: V | AR6: V | AS6: V | AV6: V | AX6: V | AY6: n/a | AZ6: n/a | BB6: V | BC6: V-O | BD6: V-O | BE6: V | BF6: V | BH6: V | BP6: V | BQ6: V | BW6: V | BZ6: V | CA6: V | CB6: V | CC6: V | CE6: V | CH6: V-O | CJ6: V-O | CK6: V-O | CL6: V-O | CM6: V-O | CN6: V-O | CO6: V-O | CP6: V-O | CQ6: V-O | CS6: V | CT6: V | CU6: V | DD6: V-O | DE6: V-O | DF6: V-O | DG6: V-O | DH6: V-O | DI6: V-O
A7: REQ-002 | B7: View | C7: View | D7: View | E7: View | F7: View | G7: View | H7: View | I7: View | J7: View | K7: View | L7: View | M7: Manage | N7: View | O7: Not applicable | P7: No Role Available | Q7: V | R7: V | S7: V | T7: V | U7: V | V7: V | W7: V | X7: V | Y7: V-O | Z7: V-O | AA7: V-O | AB7: V-O | AC7: V-O | AD7: V-O | AE7: V-O | AG7: V-O | AH7: V-O | AI7: V | AJ7: V | AK7: V-O | AL7: n/a | AM7: V | AN7: V | AO7: V | AQ7: V | AR7: V | AS7: V | AV7: V | AX7: V | AY7: n/a | AZ7: n/a | BB7: V | BC7: V-O | BD7: V-O | BE7: V | BF7: V | BH7: V | BP7: V | BQ7: V | BR7: M | BS7: M | BW7: V | BX7: M | BY7: M | BZ7: V | CA7: V | CB7: M | CC7: V | CD7: M | CE7: V | CF7: M-O | CH7: V-O | CJ7: V-O | CK7: V-O | CL7: V-O | CM7: V-O | CN7: V-O | CO7: V-O | CP7: V-O | CQ7: V-O | CS7: V | CT7: V | CU7: V | DD7: V-O | DE7: V-O | DF7: V-O | DG7: V-O | DH7: V-O | DI7: V-O
A8: REQ-003 | B8: View | C8: View | D8: View | E8: View | F8: View | G8: View | H8: View | I8: View | J8: View | K8: View | L8: View | M8: Control | N8: View | O8: Not applicable | Q8: V | R8: V | S8: V | T8: V | U8: V | V8: V | W8: V | X8: V | Y8: V-O | Z8: V-O | AA8: V-O | AB8: V-O | AC8: V-O | AD8: V-O | AE8: V-O | AG8: V-O | AH8: V-O | AI8: V | AJ8: V | AK8: V-O | AL8: n/a | AM8: V | AN8: V | AO8: V | AQ8: V | AR8: V | AS8: V | AV8: V | AX8: V | AY8: n/a | AZ8: n/a | BB8: V | BC8: V-O | BD8: V-O | BE8: V | BF8: V | BH8: V | BP8: V | BQ8: V | BT8: C | BU8: C | BW8: V | BZ8: V | CA8: V | CC8: V | CE8: V | CH8: V-O | CJ8: V-O | CK8: V-O | CL8: V-O | CM8: V-O | CN8: V-O | CO8: V-O | CP8: V-O | CQ8: V-O | CS8: V | CT8: V | CU8: V | DD8: V-O | DE8: V-O | DF8: V-O | DG8: V-O | DH8: V-O | DI8: V-O
A9: REQ-004 | B9: View | C9: View | D9: View | E9: View | F9: View | G9: View | H9: View | I9: View | J9: View | K9: Manage | L9: View | M9: View | N9: View | O9: Not applicable | Q9: V | R9: V | S9: V | T9: V | U9: V | V9: V | W9: V | X9: V | Y9: V-O | Z9: V-O | AA9: V-O | AB9: V-O | AC9: V-O | AD9: V-O | AE9: V-O | AG9: V-O | AH9: V-O | AI9: V | AJ9: V | AK9: V-O | AL9: n/a | AM9: V | AN9: V | AO9: V | AQ9: V | AR9: V | AS9: V | AV9: V | AX9: V | AY9: n/a | AZ9: n/a | BB9: V | BC9: V-O | BD9: V-O | BE9: V | BF9: V | BH9: V | BI9: M-O | BJ9: M-O | BK9: M-O | BL9: M-O | BM9: M-O | BN9: M-O | BO9: M-O | BP9: V | BQ9: V | BW9: V | BZ9: V | CA9: V | CB9: V | CC9: V | CE9: V | CH9: V-O | CJ9: V-O | CK9: V-O | CL9: V-O | CM9: V-O | CN9: V-O | CO9: V-O | CP9: V-O | CQ9: V-O | CS9: V | CT9: V | CU9: V | DD9: V-O | DE9: V-O | DF9: V-O | DG9: V-O | DH9: V-O | DI9: V-O
A10: REQ-005 | B10: View | C10: View | D10: View | E10: View | F10: View | G10: View | H10: View | I10: View | J10: View | K10: Manage | L10: View | M10: Manage | N10: View | O10: Not applicable | Q10: V | R10: V | S10: V | T10: V | U10: V | V10: V | W10: V | X10: V | Y10: V-O | Z10: V-O | AA10: V-O | AB10: V-O | AC10: V-O | AD10: V-O | AE10: V-O | AG10: V-O | AH10: V-O | AI10: V | AJ10: V | AK10: V-O | AL10: n/a | AM10: V | AN10: V | AO10: V | AQ10: V | AR10: V | AS10: V | AV10: V | AX10: V | AY10: n/a | AZ10: n/a | BB10: V | BC10: V-O | BD10: V-O | BE10: V | BF10: V | BH10: V | BI10: M-O | BJ10: M-O | BK10: M-O | BL10: M-O | BM10: M-O | BN10: M-O | BO10: M-O | BP10: V | BQ10: V | BR10: M | BS10: M | BW10: V | BX10: M | BY10: M | BZ10: V | CA10: V | CB10: M | CC10: V | CD10: M | CE10: V | CF10: M-O | CH10: V-O | CJ10: V-O | CK10: V-O | CL10: V-O | CM10: V-O | CN10: V-O | CO10: V-O | CP10: V-O | CQ10: V-O | CS10: V | CT10: V | CU10: V | DD10: V-O | DE10: V-O | DF10: V-O | DG10: V-O | DH10: V-O | DI10: V-O
A11: REQ-006 | B11: View | C11: View | D11: View | E11: View | F11: View | G11: View | H11: View | I11: View | J11: View | K11: Manage | L11: View | M11: Control | N11: View | O11: Not applicable | Q11: V | R11: V | S11: V | T11: V | U11: V | V11: V | W11: V | X11: V | Y11: V-O | Z11: V-O | AA11: V-O | AB11: V-O | AC11: V-O | AD11: V-O | AE11: V-O | AG11: V-O | AH11: V-O | AI11: V | AJ11: V | AK11: V-O | AL11: n/a | AM11: V | AN11: V | AO11: V | AQ11: V | AR11: V | AS11: V | AV11: V | AX11: V | AY11: n/a | AZ11: n/a | BB11: V | BC11: V-O | BD11: V-O | BE11: V | BF11: V | BH11: V | BI11: M-O | BJ11: M-O | BK11: M-O | BL11: M-O | BM11: M-O | BN11: M-O | BO11: M-O | BP11: V | BQ11: V | BT11: C | BU11: C | BW11: V | BZ11: V | CA11: V | CC11: V | CE11: V | CH11: V-O | CJ11: V-O | CK11: V-O | CL11: V-O | CM11: V-O | CN11: V-O | CO11: V-O | CP11: V-O | CQ11: V-O | CS11: V | CT11: V | CU11: V | DD11: V-O | DE11: V-O | DF11: V-O | DG11: V-O | DH11: V-O | DI11: V-O
A12: REQ-007 | B12: View | C12: View | D12: View | E12: View | F12: Manage | G12: View | H12: View | I12: View | J12: View | K12: View | L12: View | M12: View | N12: View | O12: Not applicable | Q12: V | R12: V | S12: V | T12: V | U12: V | V12: V | W12: V | X12: V | Y12: V-O | Z12: V-O | AA12: V-O | AB12: V-O | AC12: V-O | AD12: V-O | AE12: V-O | AG12: V-O | AH12: V-O | AI12: V | AJ12: V | AK12: V-O | AL12: n/a | AM12: V | AN12: V | AO12: V | AQ12: V | AR12: V | AS12: V | AV12: M | AX12: M | AY12: n/a | AZ12: M | BB12: V | BC12: M-O | BD12: M-O | BE12: V | BF12: V | BH12: V | BP12: V | BQ12: V | BW12: V | BZ12: V | CA12: V | CB12: V | CC12: V | CE12: V | CH12: V-O | CJ12: V-O | CK12: V-O | CL12: V-O | CM12: V-O | CN12: V-O | CO12: V-O | CP12: V-O | CQ12: V-O | CS12: V | CT12: V | CU12: V | DD12: V-O | DE12: V-O | DF12: V-O | DG12: V-O | DH12: V-O | DI12: V-O
A13: REQ-008 | B13: View | C13: View | D13: View | E13: View | F13: Manage | G13: View | H13: View | I13: View | J13: View | K13: View | L13: View | M13: Manage | N13: View | O13: Not applicable | Q13: V | R13: V | S13: V | T13: V | U13: V | V13: V | W13: V | X13: V | Y13: V-O | Z13: V-O | AA13: V-O | AB13: V-O | AC13: V-O | AD13: V-O | AE13: V-O | AG13: V-O | AH13: V-O | AI13: V | AJ13: V | AK13: V-O | AL13: n/a | AM13: V | AN13: V | AO13: V | AQ13: V | AR13: V | AS13: V | AV13: M | AX13: M | AY13: n/a | AZ13: M | BB13: V | BC13: M-O | BD13: M-O | BE13: V | BF13: V | BH13: V | BP13: V | BQ13: V | BR13: M | BS13: M | BW13: V | BX13: M | BY13: M | BZ13: V | CA13: V | CB13: M | CC13: V | CD13: M | CE13: V | CF13: M-O | CH13: V-O | CJ13: V-O | CK13: V-O | CL13: V-O | CM13: V-O | CN13: V-O | CO13: V-O | CP13: V-O | CQ13: V-O | CS13: V | CT13: V | CU13: V | DD13: V-O | DE13: V-O | DF13: V-O | DG13: V-O | DH13: V-O | DI13: V-O
A14: REQ-009 | B14: View | C14: View | D14: View | E14: View | F14: Manage | G14: View | H14: View | I14: View | J14: View | K14: View | L14: View | M14: Control | N14: View | O14: Not applicable | Q14: V | R14: V | S14: V | T14: V | U14: V | V14: V | W14: V | X14: V | Y14: V-O | Z14: V-O | AA14: V-O | AB14: V-O | AC14: V-O | AD14: V-O | AE14: V-O | AG14: V-O | AH14: V-O | AI14: V | AJ14: V | AK14: V-O | AL14: n/a | AM14: V | AN14: V | AO14: V | AQ14: V | AR14: V | AS14: V | AV14: M | AX14: M | AY14: n/a | AZ14: M | BB14: V | BC14: M-O | BD14: M-O | BE14: V | BF14: V | BH14: V | BP14: V | BQ14: V | BT14: C | BU14: C | BW14: V | BZ14: V | CA14: V | CC14: V | CE14: V | CH14: V-O | CJ14: V-O | CK14: V-O | CL14: V-O | CM14: V-O | CN14: V-O | CO14: V-O | CP14: V-O | CQ14: V-O | CS14: V | CT14: V | CU14: V | DD14: V-O | DE14: V-O | DF14: V-O | DG14: V-O | DH14: V-O | DI14: V-O
A15: REQ-010 | B15: View | C15: View | D15: View | E15: View | F15: Manage | G15: View | H15: View | I15: View | J15: View | K15: Manage | L15: View | M15: View | N15: View | O15: Not applicable | Q15: V | R15: V | S15: V | T15: V | U15: V | V15: V | W15: V | X15: V | Y15: V-O | Z15: V-O | AA15: V-O | AB15: V-O | AC15: V-O | AD15: V-O | AE15: V-O | AG15: V-O | AH15: V-O | AI15: V | AJ15: V | AK15: V-O | AL15: n/a | AM15: V | AN15: V | AO15: V | AQ15: V | AR15: V | AS15: V | AV15: M | AX15: M | AY15: n/a | AZ15: M | BB15: V | BC15: M-O | BD15: M-O | BE15: V | BF15: V | BH15: V | BI15: M-O | BJ15: M-O | BK15: M-O | BL15: M-O | BM15: M-O | BN15: M-O | BO15: M-O | BP15: V | BQ15: V | BW15: V | BZ15: V | CA15: V | CB15: V | CC15: V | CE15: V | CH15: V-O | CJ15: V-O | CK15: V-O | CL15: V-O | CM15: V-O | CN15: V-O | CO15: V-O | CP15: V-O | CQ15: V-O | CS15: V | CT15: V | CU15: V | DD15: V-O | DE15: V-O | DF15: V-O | DG15: V-O | DH15: V-O | DI15: V-O
A16: REQ-011 | B16: View | C16: View | D16: View | E16: View | F16: Manage | G16: View | H16: View | I16: View | J16: View | K16: Manage | L16: View | M16: Manage | N16: View | O16: Not applicable | Q16: V | R16: V | S16: V | T16: V | U16: V | V16: V | W16: V | X16: V | Y16: V-O | Z16: V-O | AA16: V-O | AB16: V-O | AC16: V-O | AD16: V-O | AE16: V-O | AG16: V-O | AH16: V-O | AI16: V | AJ16: V | AK16: V-O | AL16: n/a | AM16: V | AN16: V | AO16: V | AQ16: V | AR16: V | AS16: V | AV16: M | AX16: M | AY16: n/a | AZ16: M | BB16: V | BC16: M-O | BD16: M-O | BE16: V | BF16: V | BH16: V | BI16: M-O | BJ16: M-O | BK16: M-O | BL16: M-O | BM16: M-O | BN16: M-O | BO16: M-O | BP16: V | BQ16: V | BR16: M | BS16: M | BW16: V | BX16: M | BY16: M | BZ16: V | CA16: V | CB16: M | CC16: V | CD16: M | CE16: V | CF16: M-O | CH16: V-O | CJ16: V-O | CK16: V-O | CL16: V-O | CM16: V-O | CN16: V-O | CO16: V-O | CP16: V-O | CQ16: V-O | CS16: V | CT16: V | CU16: V | DD16: V-O | DE16: V-O | DF16: V-O | DG16: V-O | DH16: V-O | DI16: V-O
A17: REQ-012 | B17: View | C17: View | D17: View | E17: View | F17: Manage | G17: View | H17: View | I17: View | J17: View | K17: Manage | L17: View | M17: Control | N17: View | O17: Not applicable | Q17: V | R17: V | S17: V | T17: V | U17: V | V17: V | W17: V | X17: V | Y17: V-O | Z17: V-O | AA17: V-O | AB17: V-O | AC17: V-O | AD17: V-O | AE17: V-O | AG17: V-O | AH17: V-O | AI17: V | AJ17: V | AK17: V-O | AL17: n/a | AM17: V | AN17: V | AO17: V | AQ17: V | AR17: V | AS17: V | AV17: M | AX17: M | AY17: n/a | AZ17: M | BB17: V | BC17: M-O | BD17: M-O | BE17: V | BF17: V | BH17: V | BI17: M-O | BJ17: M-O | BK17: M-O | BL17: M-O | BM17: M-O | BN17: M-O | BO17: M-O | BP17: V | BQ17: V | BT17: C | BU17: C | BW17: V | BZ17: V | CA17: V | CC17: V | CE17: V | CH17: V-O | CJ17: V-O | CK17: V-O | CL17: V-O | CM17: V-O | CN17: V-O | CO17: V-O | CP17: V-O | CQ17: V-O | CS17: V | CT17: V | CU17: V | DD17: V-O | DE17: V-O | DF17: V-O | DG17: V-O | DH17: V-O | DI17: V-O
A18: REQ-013 | B18: View | C18: View | D18: View | E18: View | F18: Control | G18: View | H18: View | I18: View | J18: View | K18: View | L18: View | M18: View | N18: View | O18: Not applicable | Q18: V | R18: V | S18: V | T18: V | U18: V | V18: V | W18: V | X18: V | Y18: V-O | Z18: V-O | AA18: V-O | AB18: V-O | AC18: V-O | AD18: V-O | AE18: V-O | AG18: V-O | AH18: V-O | AI18: V | AJ18: V | AK18: V-O | AL18: n/a | AM18: V | AN18: V | AO18: V | AQ18: V | AR18: V | AS18: V | AX18: M | AY18: C | BB18: V | BE18: V | BF18: V | BH18: V | BP18: V | BQ18: V | BW18: V | BZ18: V | CA18: V | CB18: V | CC18: V | CE18: V | CH18: V-O | CJ18: V-O | CK18: V-O | CL18: V-O | CM18: V-O | CN18: V-O | CO18: V-O | CP18: V-O | CQ18: V-O | CS18: V | CT18: V | CU18: V | DD18: V-O | DE18: V-O | DF18: V-O | DG18: V-O | DH18: V-O | DI18: V-O
A19: REQ-014 | B19: View | C19: View | D19: View | E19: View | F19: Control | G19: View | H19: View | I19: View | J19: View | K19: View | L19: View | M19: Manage | N19: View | O19: Not applicable | Q19: V | R19: V | S19: V | T19: V | U19: V | V19: V | W19: V | X19: V | Y19: V-O | Z19: V-O | AA19: V-O | AB19: V-O | AC19: V-O | AD19: V-O | AE19: V-O | AG19: V-O | AH19: V-O | AI19: V | AJ19: V | AK19: V-O | AL19: n/a | AM19: V | AN19: V | AO19: V | AQ19: V | AR19: V | AS19: V | AX19: M | AY19: C | BB19: V | BE19: V | BF19: V | BH19: V | BP19: V | BQ19: V | BR19: M | BS19: M | BW19: V | BX19: M | BY19: M | BZ19: V | CA19: V | CB19: M | CC19: V | CD19: M | CE19: V | CF19: M-O | CH19: V-O | CJ19: V-O | CK19: V-O | CL19: V-O | CM19: V-O | CN19: V-O | CO19: V-O | CP19: V-O | CQ19: V-O | CS19: V | CT19: V | CU19: V | DD19: V-O | DE19: V-O | DF19: V-O | DG19: V-O | DH19: V-O | DI19: V-O
A20: REQ-015 | B20: View | C20: View | D20: View | E20: View | F20: Control | G20: View | H20: View | I20: View | J20: View | K20: View | L20: View | M20: Control | N20: View | O20: Not applicable | Q20: V | R20: V | S20: V | T20: V | U20: V | V20: V | W20: V | X20: V | Y20: V-O | Z20: V-O | AA20: V-O | AB20: V-O | AC20: V-O | AD20: V-O | AE20: V-O | AG20: V-O | AH20: V-O | AI20: V | AJ20: V | AK20: V-O | AL20: n/a | AM20: V | AN20: V | AO20: V | AQ20: V | AR20: V | AS20: V | AX20: M | AY20: C | BB20: V | BE20: V | BF20: V | BH20: V | BP20: V | BQ20: V | BT20: C | BU20: C | BW20: V | BZ20: V | CA20: V | CC20: V | CE20: V | CH20: V-O | CJ20: V-O | CK20: V-O | CL20: V-O | CM20: V-O | CN20: V-O | CO20: V-O | CP20: V-O | CQ20: V-O | CS20: V | CT20: V | CU20: V | DD20: V-O | DE20: V-O | DF20: V-O | DG20: V-O | DH20: V-O | DI20: V-O
A21: REQ-016 | B21: View | C21: View | D21: View | E21: View | F21: Control | G21: View | H21: View | I21: View | J21: View | K21: Manage | L21: View | M21: View | N21: View | O21: Not applicable | Q21: V | R21: V | S21: V | T21: V | U21: V | V21: V | W21: V | X21: V | Y21: V-O | Z21: V-O | AA21: V-O | AB21: V-O | AC21: V-O | AD21: V-O | AE21: V-O | AG21: V-O | AH21: V-O | AI21: V | AJ21: V | AK21: V-O | AL21: n/a | AM21: V | AN21: V | AO21: V | AQ21: V | AR21: V | AS21: V | AX21: M | AY21: C | BB21: V | BE21: V | BF21: V | BH21: V | BI21: M-O | BJ21: M-O | BK21: M-O | BL21: M-O | BM21: M-O | BN21: M-O | BO21: M-O | BP21: V | BQ21: V | BW21: V | BZ21: V | CA21: V | CB21: V | CC21: V | CE21: V | CH21: V-O | CJ21: V-O | CK21: V-O | CL21: V-O | CM21: V-O | CN21: V-O | CO21: V-O | CP21: V-O | CQ21: V-O | CS21: V | CT21: V | CU21: V | DD21: V-O | DE21: V-O | DF21: V-O | DG21: V-O | DH21: V-O | DI21: V-O
A22: REQ-017 | B22: View | C22: View | D22: View | E22: View | F22: Control | G22: View | H22: View | I22: View | J22: View | K22: Manage | L22: View | M22: Manage | N22: View | O22: Not applicable | Q22: V | R22: V | S22: V | T22: V | U22: V | V22: V | W22: V | X22: V | Y22: V-O | Z22: V-O | AA22: V-O | AB22: V-O | AC22: V-O | AD22: V-O | AE22: V-O | AG22: V-O | AH22: V-O | AI22: V | AJ22: V | AK22: V-O | AL22: n/a | AM22: V | AN22: V | AO22: V | AQ22: V | AR22: V | AS22: V | AX22: M | AY22: C | BB22: V | BE22: V | BF22: V | BH22: V | BI22: M-O | BJ22: M-O | BK22: M-O | BL22: M-O | BM22: M-O | BN22: M-O | BO22: M-O | BP22: V | BQ22: V | BR22: M | BS22: M | BW22: V | BX22: M | BY22: M | BZ22: V | CA22: V | CB22: M | CC22: V | CD22: M | CE22: V | CF22: M-O | CH22: V-O | CJ22: V-O | CK22: V-O | CL22: V-O | CM22: V-O | CN22: V-O | CO22: V-O | CP22: V-O | CQ22: V-O | CS22: V | CT22: V | CU22: V | DD22: V-O | DE22: V-O | DF22: V-O | DG22: V-O | DH22: V-O | DI22: V-O
A23: REQ-018 | B23: View | C23: View | D23: View | E23: View | F23: Control | G23: View | H23: View | I23: View | J23: View | K23: Manage | L23: View | M23: Control | N23: View | O23: Not applicable | Q23: V | R23: V | S23: V | T23: V | U23: V | V23: V | W23: V | X23: V | Y23: V-O | Z23: V-O | AA23: V-O | AB23: V-O | AC23: V-O | AD23: V-O | AE23: V-O | AG23: V-O | AH23: V-O | AI23: V | AJ23: V | AK23: V-O | AL23: n/a | AM23: V | AN23: V | AO23: V | AQ23: V | AR23: V | AS23: V | AX23: M | AY23: C | BB23: V | BE23: V | BF23: V | BH23: V | BI23: M-O | BJ23: M-O | BK23: M-O | BL23: M-O | BM23: M-O | BN23: M-O | BO23: M-O | BP23: V | BQ23: V | BT23: C | BU23: C | BW23: V | BZ23: V | CA23: V | CC23: V | CE23: V | CH23: V-O | CJ23: V-O | CK23: V-O | CL23: V-O | CM23: V-O | CN23: V-O | CO23: V-O | CP23: V-O | CQ23: V-O | CS23: V | CT23: V | CU23: V | DD23: V-O | DE23: V-O | DF23: V-O | DG23: V-O | DH23: V-O | DI23: V-O
A24: REQ-019 | B24: View | C24: View | D24: View | E24: View | F24: Process | G24: View | H24: View | I24: View | J24: View | K24: View | L24: View | M24: View | N24: View | O24: Not applicable | Q24: V | R24: V | S24: V | T24: V | U24: V | V24: V | W24: V | X24: V | Y24: V-O | Z24: V-O | AA24: V-O | AB24: V-O | AC24: V-O | AD24: V-O | AE24: V-O | AG24: V-O | AH24: V-O | AI24: V | AJ24: V | AK24: V-O | AL24: n/a | AM24: V | AN24: V | AO24: V | AQ24: V | AR24: V | AS24: V | AX24: n/a | AY24: n/a | BB24: V | BE24: V | BF24: V | BH24: V | BP24: V | BQ24: V | BW24: V | BZ24: V | CA24: V | CB24: V | CC24: V | CE24: V | CH24: V-O | CJ24: V-O | CK24: V-O | CL24: V-O | CM24: V-O | CN24: V-O | CO24: V-O | CP24: V-O | CQ24: V-O | CS24: V | CT24: V | CU24: V | DD24: V-O | DE24: V-O | DF24: V-O | DG24: V-O | DH24: V-O | DI24: V-O
A25: REQ-020 | B25: View | C25: View | D25: View | E25: View | F25: Process | G25: View | H25: View | I25: View | J25: View | K25: View | L25: View | M25: Manage | N25: View | O25: Not applicable | Q25: V | R25: V | S25: V | T25: V | U25: V | V25: V | W25: V | X25: V | Y25: V-O | Z25: V-O | AA25: V-O | AB25: V-O | AC25: V-O | AD25: V-O | AE25: V-O | AG25: V-O | AH25: V-O | AI25: V | AJ25: V | AK25: V-O | AL25: n/a | AM25: V | AN25: V | AO25: V | AQ25: V | AR25: V | AS25: V | AX25: n/a | AY25: n/a | BB25: V | BE25: V | BF25: V | BH25: V | BP25: V | BQ25: V | BR25: M | BS25: M | BW25: V | BX25: M | BY25: M | BZ25: V | CA25: V | CB25: M | CC25: V | CD25: M | CE25: V | CF25: M-O | CH25: V-O | CJ25: V-O | CK25: V-O | CL25: V-O | CM25: V-O | CN25: V-O | CO25: V-O | CP25: V-O | CQ25: V-O | CS25: V | CT25: V | CU25: V | DD25: V-O | DE25: V-O | DF25: V-O | DG25: V-O | DH25: V-O | DI25: V-O
A26: REQ-021 | B26: View | C26: View | D26: View | E26: View | F26: Process | G26: View | H26: View | I26: View | J26: View | K26: View | L26: View | M26: Control | N26: View | O26: Not applicable | Q26: V | R26: V | S26: V | T26: V | U26: V | V26: V | W26: V | X26: V | Y26: V-O | Z26: V-O | AA26: V-O | AB26: V-O | AC26: V-O | AD26: V-O | AE26: V-O | AG26: V-O | AH26: V-O | AI26: V | AJ26: V | AK26: V-O | AL26: n/a | AM26: V | AN26: V | AO26: V | AQ26: V | AR26: V | AS26: V | AX26: n/a | AY26: n/a | BB26: V | BE26: V | BF26: V | BH26: V | BP26: V | BQ26: V | BT26: C | BU26: C | BW26: V | BZ26: V | CA26: V | CC26: V | CE26: V | CH26: V-O | CJ26: V-O | CK26: V-O | CL26: V-O | CM26: V-O | CN26: V-O | CO26: V-O | CP26: V-O | CQ26: V-O | CS26: V | CT26: V | CU26: V | DD26: V-O | DE26: V-O | DF26: V-O | DG26: V-O | DH26: V-O | DI26: V-O
A27: REQ-022 | B27: View | C27: View | D27: View | E27: View | F27: Process | G27: View | H27: View | I27: View | J27: View | K27: Manage | L27: View | M27: View | N27: View | O27: Not applicable | Q27: V | R27: V | S27: V | T27: V | U27: V | V27: V | W27: V | X27: V | Y27: V-O | Z27: V-O | AA27: V-O | AB27: V-O | AC27: V-O | AD27: V-O | AE27: V-O | AG27: V-O | AH27: V-O | AI27: V | AJ27: V | AK27: V-O | AL27: n/a | AM27: V | AN27: V | AO27: V | AQ27: V | AR27: V | AS27: V | AX27: n/a | AY27: n/a | BB27: V | BE27: V | BF27: V | BH27: V | BI27: M-O | BJ27: M-O | BK27: M-O | BL27: M-O | BM27: M-O | BN27: M-O | BO27: M-O | BP27: V | BQ27: V | BW27: V | BZ27: V | CA27: V | CB27: V | CC27: V | CE27: V | CH27: V-O | CJ27: V-O | CK27: V-O | CL27: V-O | CM27: V-O | CN27: V-O | CO27: V-O | CP27: V-O | CQ27: V-O | CS27: V | CT27: V | CU27: V | DD27: V-O | DE27: V-O | DF27: V-O | DG27: V-O | DH27: V-O | DI27: V-O
A28: REQ-023 | B28: View | C28: View | D28: View | E28: View | F28: Process | G28: View | H28: View | I28: View | J28: View | K28: Manage | L28: View | M28: Manage | N28: View | O28: Not applicable | Q28: V | R28: V | S28: V | T28: V | U28: V | V28: V | W28: V | X28: V | Y28: V-O | Z28: V-O | AA28: V-O | AB28: V-O | AC28: V-O | AD28: V-O | AE28: V-O | AG28: V-O | AH28: V-O | AI28: V | AJ28: V | AK28: V-O | AL28: n/a | AM28: V | AN28: V | AO28: V | AQ28: V | AR28: V | AS28: V | AX28: n/a | AY28: n/a | BB28: V | BE28: V | BF28: V | BH28: V | BI28: M-O | BJ28: M-O | BK28: M-O | BL28: M-O | BM28: M-O | BN28: M-O | BO28: M-O | BP28: V | BQ28: V | BR28: M | BS28: M | BW28: V | BX28: M | BY28: M | BZ28: V | CA28: V | CB28: M | CC28: V | CD28: M | CE28: V | CF28: M-O | CH28: V-O | CJ28: V-O | CK28: V-O | CL28: V-O | CM28: V-O | CN28: V-O | CO28: V-O | CP28: V-O | CQ28: V-O | CS28: V | CT28: V | CU28: V | DD28: V-O | DE28: V-O | DF28: V-O | DG28: V-O | DH28: V-O | DI28: V-O
A29: REQ-024 | B29: View | C29: View | D29: View | E29: View | F29: Process | G29: View | H29: View | I29: View | J29: View | K29: Manage | L29: View | M29: Control | N29: View | O29: Not applicable | Q29: V | R29: V | S29: V | T29: V | U29: V | V29: V | W29: V | X29: V | Y29: V-O | Z29: V-O | AA29: V-O | AB29: V-O | AC29: V-O | AD29: V-O | AE29: V-O | AG29: V-O | AH29: V-O | AI29: V | AJ29: V | AK29: V-O | AL29: n/a | AM29: V | AN29: V | AO29: V | AQ29: V | AR29: V | AS29: V | AX29: n/a | AY29: n/a | BB29: V | BE29: V | BF29: V | BH29: V | BI29: M-O | BJ29: M-O | BK29: M-O | BL29: M-O | BM29: M-O | BN29: M-O | BO29: M-O | BP29: V | BQ29: V | BT29: C | BU29: C | BW29: V | BZ29: V | CA29: V | CC29: V | CE29: V | CH29: V-O | CJ29: V-O | CK29: V-O | CL29: V-O | CM29: V-O | CN29: V-O | CO29: V-O | CP29: V-O | CQ29: V-O | CS29: V | CT29: V | CU29: V | DD29: V-O | DE29: V-O | DF29: V-O | DG29: V-O | DH29: V-O | DI29: V-O
A30: REQ-025 | B30: View | C30: View | D30: View | E30: Manage | F30: View | G30: View | H30: View | I30: View | J30: View | K30: View | L30: View | M30: View | N30: View | O30: Not applicable | Q30: V | R30: V | S30: V | T30: V | U30: V | V30: V | W30: V | X30: V | Y30: V-O | Z30: V-O | AA30: V-O | AB30: V-O | AC30: V-O | AD30: V-O | AE30: V-O | AG30: V-O | AH30: V-O | AI30: M | AJ30: M | AK30: V-O | AL30: M-O | AM30: M | AN30: M | AO30: M | AQ30: M | AR30: V | AS30: V | AV30: V | AX30: V | AY30: n/a | AZ30: n/a | BB30: V | BC30: V-O | BD30: V-O | BE30: V | BF30: V | BH30: V | BP30: V | BQ30: V | BW30: V | BZ30: V | CA30: V | CB30: V | CC30: V | CE30: V | CH30: V-O | CJ30: V-O | CK30: V-O | CL30: V-O | CM30: V-O | CN30: V-O | CO30: V-O | CP30: V-O | CQ30: V-O | CS30: V | CT30: V | CU30: V | DD30: V-O | DE30: V-O | DF30: V-O | DG30: V-O | DH30: V-O | DI30: V-O
A31: REQ-026 | B31: View | C31: View | D31: View | E31: Manage | F31: View | G31: View | H31: View | I31: View | J31: View | K31: View | L31: View | M31: Manage | N31: View | O31: Not applicable | Q31: V | R31: V | S31: V | T31: V | U31: V | V31: V | W31: V | X31: V | Y31: V-O | Z31: V-O | AA31: V-O | AB31: V-O | AC31: V-O | AD31: V-O | AE31: V-O | AG31: V-O | AH31: V-O | AI31: M | AJ31: M | AK31: V-O | AL31: M-O | AM31: M | AN31: M | AO31: M | AQ31: M | AR31: V | AS31: V | AV31: V | AX31: V | AY31: n/a | AZ31: n/a | BB31: V | BC31: V-O | BD31: V-O | BE31: V | BF31: V | BH31: V | BP31: V | BQ31: V | BR31: M | BS31: M | BW31: V | BX31: M | BY31: M | BZ31: V | CA31: V | CB31: M | CC31: V | CD31: M | CE31: V | CF31: M-O | CH31: V-O | CJ31: V-O | CK31: V-O | CL31: V-O | CM31: V-O | CN31: V-O | CO31: V-O | CP31: V-O | CQ31: V-O | CS31: V | CT31: V | CU31: V | DD31: V-O | DE31: V-O | DF31: V-O | DG31: V-O | DH31: V-O | DI31: V-O
A32: REQ-027 | B32: View | C32: View | D32: View | E32: Manage | F32: View | G32: View | H32: View | I32: View | J32: View | K32: View | L32: View | M32: Control | N32: View | O32: Not applicable | Q32: V | R32: V | S32: V | T32: V | U32: V | V32: V | W32: V | X32: V | Y32: V-O | Z32: V-O | AA32: V-O | AB32: V-O | AC32: V-O | AD32: V-O | AE32: V-O | AG32: V-O | AH32: V-O | AI32: M | AJ32: M | AK32: V-O | AL32: M-O | AM32: M | AN32: M | AO32: M | AQ32: M | AR32: V | AS32: V | AV32: V | AX32: V | AY32: n/a | AZ32: n/a | BB32: V | BC32: V-O | BD32: V-O | BE32: V | BF32: V | BH32: V | BP32: V | BQ32: V | BT32: C | BU32: C | BW32: V | BZ32: V | CA32: V | CC32: V | CE32: V | CH32: V-O | CJ32: V-O | CK32: V-O | CL32: V-O | CM32: V-O | CN32: V-O | CO32: V-O | CP32: V-O | CQ32: V-O | CS32: V | CT32: V | CU32: V | DD32: V-O | DE32: V-O | DF32: V-O | DG32: V-O | DH32: V-O | DI32: V-O
A33: REQ-028 | B33: View | C33: View | D33: View | E33: Manage | F33: View | G33: View | H33: View | I33: View | J33: View | K33: Manage | L33: View | M33: View | N33: View | O33: Not applicable | Q33: V | R33: V | S33: V | T33: V | U33: V | V33: V | W33: V | X33: V | Y33: V-O | Z33: V-O | AA33: V-O | AB33: V-O | AC33: V-O | AD33: V-O | AE33: V-O | AG33: V-O | AH33: V-O | AI33: M | AJ33: M | AK33: V-O | AL33: M-O | AM33: M | AN33: M | AO33: M | AQ33: M | AR33: V | AS33: V | AV33: V | AX33: V | AY33: n/a | AZ33: n/a | BB33: V | BC33: V-O | BD33: V-O | BE33: V | BF33: V | BH33: V | BI33: M-O | BJ33: M-O | BK33: M-O | BL33: M-O | BM33: M-O | BN33: M-O | BO33: M-O | BP33: V | BQ33: V | BW33: V | BZ33: V | CA33: V | CB33: V | CC33: V | CE33: V | CH33: V-O | CJ33: V-O | CK33: V-O | CL33: V-O | CM33: V-O | CN33: V-O | CO33: V-O | CP33: V-O | CQ33: V-O | CS33: V | CT33: V | CU33: V | DD33: V-O | DE33: V-O | DF33: V-O | DG33: V-O | DH33: V-O | DI33: V-O
A34: REQ-029 | B34: View | C34: View | D34: View | E34: Manage | F34: View | G34: View | H34: View | I34: View | J34: View | K34: Manage | L34: View | M34: Manage | N34: View | O34: Not applicable | Q34: V | R34: V | S34: V | T34: V | U34: V | V34: V | W34: V | X34: V | Y34: V-O | Z34: V-O | AA34: V-O | AB34: V-O | AC34: V-O | AD34: V-O | AE34: V-O | AG34: V-O | AH34: V-O | AI34: M | AJ34: M | AK34: V-O | AL34: M-O | AM34: M | AN34: M | AO34: M | AQ34: M | AR34: V | AS34: V | AV34: V | AX34: V | AY34: n/a | AZ34: n/a | BB34: V | BC34: V-O | BD34: V-O | BE34: V | BF34: V | BH34: V | BI34: M-O | BJ34: M-O | BK34: M-O | BL34: M-O | BM34: M-O | BN34: M-O | BO34: M-O | BP34: V | BQ34: V | BR34: M | BS34: M | BW34: V | BX34: M | BY34: M | BZ34: V | CA34: V | CB34: M | CC34: V | CD34: M | CE34: V | CF34: M-O | CH34: V-O | CJ34: V-O | CK34: V-O | CL34: V-O | CM34: V-O | CN34: V-O | CO34: V-O | CP34: V-O | CQ34: V-O | CS34: V | CT34: V | CU34: V | DD34: V-O | DE34: V-O | DF34: V-O | DG34: V-O | DH34: V-O | DI34: V-O
A35: REQ-030 | B35: View | C35: View | D35: View | E35: Manage | F35: View | G35: View | H35: View | I35: View | J35: View | K35: Manage | L35: View | M35: Control | N35: View | O35: Not applicable | Q35: V | R35: V | S35: V | T35: V | U35: V | V35: V | W35: V | X35: V | Y35: V-O | Z35: V-O | AA35: V-O | AB35: V-O | AC35: V-O | AD35: V-O | AE35: V-O | AG35: V-O | AH35: V-O | AI35: M | AJ35: M | AK35: V-O | AL35: M-O | AM35: M | AN35: M | AO35: M | AQ35: M | AR35: V | AS35: V | AV35: V | AX35: V | AY35: n/a | AZ35: n/a | BB35: V | BC35: V-O | BD35: V-O | BE35: V | BF35: V | BH35: V | BI35: M-O | BJ35: M-O | BK35: M-O | BL35: M-O | BM35: M-O | BN35: M-O | BO35: M-O | BP35: V | BQ35: V | BT35: C | BU35: C | BW35: V | BZ35: V | CA35: V | CC35: V | CE35: V | CH35: V-O | CJ35: V-O | CK35: V-O | CL35: V-O | CM35: V-O | CN35: V-O | CO35: V-O | CP35: V-O | CQ35: V-O | CS35: V | CT35: V | CU35: V | DD35: V-O | DE35: V-O | DF35: V-O | DG35: V-O | DH35: V-O | DI35: V-O
A36: REQ-031 | B36: View | C36: View | D36: View | E36: Manage | F36: Manage | G36: View | H36: View | I36: View | J36: View | K36: View | L36: View | M36: View | N36: View | O36: Not applicable | Q36: V | R36: V | S36: V | T36: V | U36: V | V36: V | W36: V | X36: V | Y36: V-O | Z36: V-O | AA36: V-O | AB36: V-O | AC36: V-O | AD36: V-O | AE36: V-O | AG36: V-O | AH36: V-O | AI36: M | AJ36: M | AK36: V-O | AL36: M-O | AM36: M | AN36: M | AO36: M | AQ36: M | AR36: V | AS36: V | AV36: M | AX36: M | AY36: n/a | AZ36: M | BB36: V | BC36: M-O | BD36: M-O | BE36: V | BF36: V | BH36: V | BP36: V | BQ36: V | BW36: V | BZ36: V | CA36: V | CB36: V | CC36: V | CE36: V | CH36: V-O | CJ36: V-O | CK36: V-O | CL36: V-O | CM36: V-O | CN36: V-O | CO36: V-O | CP36: V-O | CQ36: V-O | CS36: V | CT36: V | CU36: V | DD36: V-O | DE36: V-O | DF36: V-O | DG36: V-O | DH36: V-O | DI36: V-O
A37: REQ-032 | B37: View | C37: View | D37: View | E37: Manage | F37: Manage | G37: View | H37: View | I37: View | J37: View | K37: View | L37: View | M37: Manage | N37: View | O37: Not applicable | Q37: V | R37: V | S37: V | T37: V | U37: V | V37: V | W37: V | X37: V | Y37: V-O | Z37: V-O | AA37: V-O | AB37: V-O | AC37: V-O | AD37: V-O | AE37: V-O | AG37: V-O | AH37: V-O | AI37: M | AJ37: M | AK37: V-O | AL37: M-O | AM37: M | AN37: M | AO37: M | AQ37: M | AR37: V | AS37: V | AV37: M | AX37: M | AY37: n/a | AZ37: M | BB37: V | BC37: M-O | BD37: M-O | BE37: V | BF37: V | BH37: V | BP37: V | BQ37: V | BR37: M | BS37: M | BW37: V | BX37: M | BY37: M | BZ37: V | CA37: V | CB37: M | CC37: V | CD37: M | CE37: V | CF37: M-O | CH37: V-O | CJ37: V-O | CK37: V-O | CL37: V-O | CM37: V-O | CN37: V-O | CO37: V-O | CP37: V-O | CQ37: V-O | CS37: V | CT37: V | CU37: V | DD37: V-O | DE37: V-O | DF37: V-O | DG37: V-O | DH37: V-O | DI37: V-O
A38: REQ-033 | B38: View | C38: View | D38: View | E38: Manage | F38: Manage | G38: View | H38: View | I38: View | J38: View | K38: View | L38: View | M38: Control | N38: View | O38: Not applicable | Q38: V | R38: V | S38: V | T38: V | U38: V | V38: V | W38: V | X38: V | Y38: V-O | Z38: V-O | AA38: V-O | AB38: V-O | AC38: V-O | AD38: V-O | AE38: V-O | AG38: V-O | AH38: V-O | AI38: M | AJ38: M | AK38: V-O | AL38: M-O | AM38: M | AN38: M | AO38: M | AQ38: M | AR38: V | AS38: V | AV38: M | AX38: M | AY38: n/a | AZ38: M | BB38: V | BC38: M-O | BD38: M-O | BE38: V | BF38: V | BH38: V | BP38: V | BQ38: V | BT38: C | BU38: C | BW38: V | BZ38: V | CA38: V | CC38: V | CE38: V | CH38: V-O | CJ38: V-O | CK38: V-O | CL38: V-O | CM38: V-O | CN38: V-O | CO38: V-O | CP38: V-O | CQ38: V-O | CS38: V | CT38: V | CU38: V | DD38: V-O | DE38: V-O | DF38: V-O | DG38: V-O | DH38: V-O | DI38: V-O
A39: REQ-034 | B39: View | C39: View | D39: View | E39: Manage | F39: Manage | G39: View | H39: View | I39: View | J39: View | K39: Manage | L39: View | M39: View | N39: View | O39: Not applicable | Q39: V | R39: V | S39: V | T39: V | U39: V | V39: V | W39: V | X39: V | Y39: V-O | Z39: V-O | AA39: V-O | AB39: V-O | AC39: V-O | AD39: V-O | AE39: V-O | AG39: V-O | AH39: V-O | AI39: M | AJ39: M | AK39: V-O | AL39: M-O | AM39: M | AN39: M | AO39: M | AQ39: M | AR39: V | AS39: V | AV39: M | AX39: M | AY39: n/a | AZ39: M | BB39: V | BC39: M-O | BD39: M-O | BE39: V | BF39: V | BH39: V | BI39: M-O | BJ39: M-O | BK39: M-O | BL39: M-O | BM39: M-O | BN39: M-O | BO39: M-O | BP39: V | BQ39: V | BW39: V | BZ39: V | CA39: V | CB39: V | CC39: V | CE39: V | CH39: V-O | CJ39: V-O | CK39: V-O | CL39: V-O | CM39: V-O | CN39: V-O | CO39: V-O | CP39: V-O | CQ39: V-O | CS39: V | CT39: V | CU39: V | DD39: V-O | DE39: V-O | DF39: V-O | DG39: V-O | DH39: V-O | DI39: V-O
A40: REQ-035 | B40: View | C40: View | D40: View | E40: Manage | F40: Manage | G40: View | H40: View | I40: View | J40: View | K40: Manage | L40: View | M40: Manage | N40: View | O40: Not applicable | Q40: V | R40: V | S40: V | T40: V | U40: V | V40: V | W40: V | X40: V | Y40: V-O | Z40: V-O | AA40: V-O | AB40: V-O | AC40: V-O | AD40: V-O | AE40: V-O | AG40: V-O | AH40: V-O | AI40: M | AJ40: M | AK40: V-O | AL40: M-O | AM40: M | AN40: M | AO40: M | AQ40: M | AR40: V | AS40: V | AV40: M | AX40: M | AY40: n/a | AZ40: M | BB40: V | BC40: M-O | BD40: M-O | BE40: V | BF40: V | BH40: V | BI40: M-O | BJ40: M-O | BK40: M-O | BL40: M-O | BM40: M-O | BN40: M-O | BO40: M-O | BP40: V | BQ40: V | BR40: M | BS40: M | BW40: V | BX40: M | BY40: M | BZ40: V | CA40: V | CB40: M | CC40: V | CD40: M | CE40: V | CF40: M-O | CH40: V-O | CJ40: V-O | CK40: V-O | CL40: V-O | CM40: V-O | CN40: V-O | CO40: V-O | CP40: V-O | CQ40: V-O | CS40: V | CT40: V | CU40: V | DD40: V-O | DE40: V-O | DF40: V-O | DG40: V-O | DH40: V-O | DI40: V-O
A41: REQ-036 | B41: View | C41: View | D41: View | E41: Manage | F41: Manage | G41: View | H41: View | I41: View | J41: View | K41: Manage | L41: View | M41: Control | N41: View | O41: Not applicable | Q41: V | R41: V | S41: V | T41: V | U41: V | V41: V | W41: V | X41: V | Y41: V-O | Z41: V-O | AA41: V-O | AB41: V-O | AC41: V-O | AD41: V-O | AE41: V-O | AG41: V-O | AH41: V-O | AI41: M | AJ41: M | AK41: V-O | AL41: M-O | AM41: M | AN41: M | AO41: M | AQ41: M | AR41: V | AS41: V | AV41: M | AX41: M | AY41: n/a | AZ41: M | BB41: V | BC41: M-O | BD41: M-O | BE41: V | BF41: V | BH41: V | BI41: M-O | BJ41: M-O | BK41: M-O | BL41: M-O | BM41: M-O | BN41: M-O | BO41: M-O | BP41: V | BQ41: V | BT41: C | BU41: C | BW41: V | BZ41: V | CA41: V | CC41: V | CE41: V | CH41: V-O | CJ41: V-O | CK41: V-O | CL41: V-O | CM41: V-O | CN41: V-O | CO41: V-O | CP41: V-O | CQ41: V-O | CS41: V | CT41: V | CU41: V | DD41: V-O | DE41: V-O | DF41: V-O | DG41: V-O | DH41: V-O | DI41: V-O
A42: REQ-037 | B42: View | C42: View | D42: View | E42: Manage | F42: Control | G42: View | H42: View | I42: View | J42: View | K42: View | L42: View | M42: View | N42: View | O42: Not applicable | Q42: V | R42: V | S42: V | T42: V | U42: V | V42: V | W42: V | X42: V | Y42: V-O | Z42: V-O | AA42: V-O | AB42: V-O | AC42: V-O | AD42: V-O | AE42: V-O | AG42: V-O | AH42: V-O | AI42: M | AJ42: M | AK42: V-O | AL42: M-O | AM42: M | AN42: M | AO42: M | AQ42: M | AR42: V | AS42: V | AX42: M | AY42: C | BB42: V | BE42: V | BF42: V | BH42: V | BP42: V | BQ42: V | BW42: V | BZ42: V | CA42: V | CB42: V | CC42: V | CE42: V | CH42: V-O | CJ42: V-O | CK42: V-O | CL42: V-O | CM42: V-O | CN42: V-O | CO42: V-O | CP42: V-O | CQ42: V-O | CS42: V | CT42: V | CU42: V | DD42: V-O | DE42: V-O | DF42: V-O | DG42: V-O | DH42: V-O | DI42: V-O
A43: REQ-038 | B43: View | C43: View | D43: View | E43: Manage | F43: Control | G43: View | H43: View | I43: View | J43: View | K43: View | L43: View | M43: Manage | N43: View | O43: Not applicable | Q43: V | R43: V | S43: V | T43: V | U43: V | V43: V | W43: V | X43: V | Y43: V-O | Z43: V-O | AA43: V-O | AB43: V-O | AC43: V-O | AD43: V-O | AE43: V-O | AG43: V-O | AH43: V-O | AI43: M | AJ43: M | AK43: V-O | AL43: M-O | AM43: M | AN43: M | AO43: M | AQ43: M | AR43: V | AS43: V | AX43: M | AY43: C | BB43: V | BE43: V | BF43: V | BH43: V | BP43: V | BQ43: V | BR43: M | BS43: M | BW43: V | BX43: M | BY43: M | BZ43: V | CA43: V | CB43: M | CC43: V | CD43: M | CE43: V | CF43: M-O | CH43: V-O | CJ43: V-O | CK43: V-O | CL43: V-O | CM43: V-O | CN43: V-O | CO43: V-O | CP43: V-O | CQ43: V-O | CS43: V | CT43: V | CU43: V | DD43: V-O | DE43: V-O | DF43: V-O | DG43: V-O | DH43: V-O | DI43: V-O
A44: REQ-039 | B44: View | C44: View | D44: View | E44: Manage | F44: Control | G44: View | H44: View | I44: View | J44: View | K44: View | L44: View | M44: Control | N44: View | O44: Not applicable | Q44: V | R44: V | S44: V | T44: V | U44: V | V44: V | W44: V | X44: V | Y44: V-O | Z44: V-O | AA44: V-O | AB44: V-O | AC44: V-O | AD44: V-O | AE44: V-O | AG44: V-O | AH44: V-O | AI44: M | AJ44: M | AK44: V-O | AL44: M-O | AM44: M | AN44: M | AO44: M | AQ44: M | AR44: V | AS44: V | AX44: M | AY44: C | BB44: V | BE44: V | BF44: V | BH44: V | BP44: V | BQ44: V | BT44: C | BU44: C | BW44: V | BZ44: V | CA44: V | CC44: V | CE44: V | CH44: V-O | CJ44: V-O | CK44: V-O | CL44: V-O | CM44: V-O | CN44: V-O | CO44: V-O | CP44: V-O | CQ44: V-O | CS44: V | CT44: V | CU44: V | DD44: V-O | DE44: V-O | DF44: V-O | DG44: V-O | DH44: V-O | DI44: V-O
A45: REQ-040 | B45: View | C45: View | D45: View | E45: Manage | F45: Control | G45: View | H45: View | I45: View | J45: View | K45: Manage | L45: View | M45: View | N45: View | O45: Not applicable | Q45: V | R45: V | S45: V | T45: V | U45: V | V45: V | W45: V | X45: V | Y45: V-O | Z45: V-O | AA45: V-O | AB45: V-O | AC45: V-O | AD45: V-O | AE45: V-O | AG45: V-O | AH45: V-O | AI45: M | AJ45: M | AK45: V-O | AL45: M-O | AM45: M | AN45: M | AO45: M | AQ45: M | AR45: V | AS45: V | AX45: M | AY45: C | BB45: V | BE45: V | BF45: V | BH45: V | BI45: M-O | BJ45: M-O | BK45: M-O | BL45: M-O | BM45: M-O | BN45: M-O | BO45: M-O | BP45: V | BQ45: V | BW45: V | BZ45: V | CA45: V | CB45: V | CC45: V | CE45: V | CH45: V-O | CJ45: V-O | CK45: V-O | CL45: V-O | CM45: V-O | CN45: V-O | CO45: V-O | CP45: V-O | CQ45: V-O | CS45: V | CT45: V | CU45: V | DD45: V-O | DE45: V-O | DF45: V-O | DG45: V-O | DH45: V-O | DI45: V-O
A46: REQ-041 | B46: View | C46: View | D46: View | E46: Manage | F46: Control | G46: View | H46: View | I46: View | J46: View | K46: Manage | L46: View | M46: Manage | N46: View | O46: Not applicable | Q46: V | R46: V | S46: V | T46: V | U46: V | V46: V | W46: V | X46: V | Y46: V-O | Z46: V-O | AA46: V-O | AB46: V-O | AC46: V-O | AD46: V-O | AE46: V-O | AG46: V-O | AH46: V-O | AI46: M | AJ46: M | AK46: V-O | AL46: M-O | AM46: M | AN46: M | AO46: M | AQ46: M | AR46: V | AS46: V | AX46: M | AY46: C | BB46: V | BE46: V | BF46: V | BH46: V | BI46: M-O | BJ46: M-O | BK46: M-O | BL46: M-O | BM46: M-O | BN46: M-O | BO46: M-O | BP46: V | BQ46: V | BR46: M | BS46: M | BW46: V | BX46: M | BY46: M | BZ46: V | CA46: V | CB46: M | CC46: V | CD46: M | CE46: V | CF46: M-O | CH46: V-O | CJ46: V-O | CK46: V-O | CL46: V-O | CM46: V-O | CN46: V-O | CO46: V-O | CP46: V-O | CQ46: V-O | CS46: V | CT46: V | CU46: V | DD46: V-O | DE46: V-O | DF46: V-O | DG46: V-O | DH46: V-O | DI46: V-O
A47: REQ-042 | B47: View | C47: View | D47: View | E47: Manage | F47: Control | G47: View | H47: View | I47: View | J47: View | K47: Manage | L47: View | M47: Control | N47: View | O47: Not applicable | Q47: V | R47: V | S47: V | T47: V | U47: V | V47: V | W47: V | X47: V | Y47: V-O | Z47: V-O | AA47: V-O | AB47: V-O | AC47: V-O | AD47: V-O | AE47: V-O | AG47: V-O | AH47: V-O | AI47: M | AJ47: M | AK47: V-O | AL47: M-O | AM47: M | AN47: M | AO47: M | AQ47: M | AR47: V | AS47: V | AX47: M | AY47: C | BB47: V | BE47: V | BF47: V | BH47: V | BI47: M-O | BJ47: M-O | BK47: M-O | BL47: M-O | BM47: M-O | BN47: M-O | BO47: M-O | BP47: V | BQ47: V | BT47: C | BU47: C | BW47: V | BZ47: V | CA47: V | CC47: V | CE47: V | CH47: V-O | CJ47: V-O | CK47: V-O | CL47: V-O | CM47: V-O | CN47: V-O | CO47: V-O | CP47: V-O | CQ47: V-O | CS47: V | CT47: V | CU47: V | DD47: V-O | DE47: V-O | DF47: V-O | DG47: V-O | DH47: V-O | DI47: V-O
A48: REQ-043 | B48: View | C48: View | D48: View | E48: Manage | F48: Process | G48: View | H48: View | I48: View | J48: View | K48: View | L48: View | M48: View | N48: View | O48: Not applicable | Q48: V | R48: V | S48: V | T48: V | U48: V | V48: V | W48: V | X48: V | Y48: V-O | Z48: V-O | AA48: V-O | AB48: V-O | AC48: V-O | AD48: V-O | AE48: V-O | AG48: V-O | AH48: V-O | AI48: M | AJ48: M | AK48: V-O | AL48: M-O | AM48: M | AN48: M | AO48: M | AQ48: M | AR48: V | AS48: V | AX48: n/a | AY48: n/a | BB48: V | BE48: V | BF48: V | BH48: V | BP48: V | BQ48: V | BW48: V | BZ48: V | CA48: V | CB48: V | CC48: V | CE48: V | CH48: V-O | CJ48: V-O | CK48: V-O | CL48: V-O | CM48: V-O | CN48: V-O | CO48: V-O | CP48: V-O | CQ48: V-O | CS48: V | CT48: V | CU48: V | DD48: V-O | DE48: V-O | DF48: V-O | DG48: V-O | DH48: V-O | DI48: V-O
A49: REQ-044 | B49: View | C49: View | D49: View | E49: Manage | F49: Process | G49: View | H49: View | I49: View | J49: View | K49: View | L49: View | M49: Manage | N49: View | O49: Not applicable | Q49: V | R49: V | S49: V | T49: V | U49: V | V49: V | W49: V | X49: V | Y49: V-O | Z49: V-O | AA49: V-O | AB49: V-O | AC49: V-O | AD49: V-O | AE49: V-O | AG49: V-O | AH49: V-O | AI49: M | AJ49: M | AK49: V-O | AL49: M-O | AM49: M | AN49: M | AO49: M | AQ49: M | AR49: V | AS49: V | AX49: n/a | AY49: n/a | BB49: V | BE49: V | BF49: V | BH49: V | BP49: V | BQ49: V | BR49: M | BS49: M | BW49: V | BX49: M | BY49: M | BZ49: V | CA49: V | CB49: M | CC49: V | CD49: M | CE49: V | CF49: M-O | CH49: V-O | CJ49: V-O | CK49: V-O | CL49: V-O | CM49: V-O | CN49: V-O | CO49: V-O | CP49: V-O | CQ49: V-O | CS49: V | CT49: V | CU49: V | DD49: V-O | DE49: V-O | DF49: V-O | DG49: V-O | DH49: V-O | DI49: V-O
A50: REQ-045 | B50: View | C50: View | D50: View | E50: Manage | F50: Process | G50: View | H50: View | I50: View | J50: View | K50: View | L50: View | M50: Control | N50: View | O50: Not applicable | Q50: V | R50: V | S50: V | T50: V | U50: V | V50: V | W50: V | X50: V | Y50: V-O | Z50: V-O | AA50: V-O | AB50: V-O | AC50: V-O | AD50: V-O | AE50: V-O | AG50: V-O | AH50: V-O | AI50: M | AJ50: M | AK50: V-O | AL50: M-O | AM50: M | AN50: M | AO50: M | AQ50: M | AR50: V | AS50: V | AX50: n/a | AY50: n/a | BB50: V | BE50: V | BF50: V | BH50: V | BP50: V | BQ50: V | BT50: C | BU50: C | BW50: V | BZ50: V | CA50: V | CC50: V | CE50: V | CH50: V-O | CJ50: V-O | CK50: V-O | CL50: V-O | CM50: V-O | CN50: V-O | CO50: V-O | CP50: V-O | CQ50: V-O | CS50: V | CT50: V | CU50: V | DD50: V-O | DE50: V-O | DF50: V-O | DG50: V-O | DH50: V-O | DI50: V-O
A51: REQ-046 | B51: View | C51: View | D51: View | E51: Manage | F51: Process | G51: View | H51: View | I51: View | J51: View | K51: Manage | L51: View | M51: View | N51: View | O51: Not applicable | Q51: V | R51: V | S51: V | T51: V | U51: V | V51: V | W51: V | X51: V | Y51: V-O | Z51: V-O | AA51: V-O | AB51: V-O | AC51: V-O | AD51: V-O | AE51: V-O | AG51: V-O | AH51: V-O | AI51: M | AJ51: M | AK51: V-O | AL51: M-O | AM51: M | AN51: M | AO51: M | AQ51: M | AR51: V | AS51: V | AX51: n/a | AY51: n/a | BB51: V | BE51: V | BF51: V | BH51: V | BI51: M-O | BJ51: M-O | BK51: M-O | BL51: M-O | BM51: M-O | BN51: M-O | BO51: M-O | BP51: V | BQ51: V | BW51: V | BZ51: V | CA51: V | CB51: V | CC51: V | CE51: V | CH51: V-O | CJ51: V-O | CK51: V-O | CL51: V-O | CM51: V-O | CN51: V-O | CO51: V-O | CP51: V-O | CQ51: V-O | CS51: V | CT51: V | CU51: V | DD51: V-O | DE51: V-O | DF51: V-O | DG51: V-O | DH51: V-O | DI51: V-O
A52: REQ-047 | B52: View | C52: View | D52: View | E52: Manage | F52: Process | G52: View | H52: View | I52: View | J52: View | K52: Manage | L52: View | M52: Manage | N52: View | O52: Not applicable | Q52: V | R52: V | S52: V | T52: V | U52: V | V52: V | W52: V | X52: V | Y52: V-O | Z52: V-O | AA52: V-O | AB52: V-O | AC52: V-O | AD52: V-O | AE52: V-O | AG52: V-O | AH52: V-O | AI52: M | AJ52: M | AK52: V-O | AL52: M-O | AM52: M | AN52: M | AO52: M | AQ52: M | AR52: V | AS52: V | AX52: n/a | AY52: n/a | BB52: V | BE52: V | BF52: V | BH52: V | BI52: M-O | BJ52: M-O | BK52: M-O | BL52: M-O | BM52: M-O | BN52: M-O | BO52: M-O | BP52: V | BQ52: V | BR52: M | BS52: M | BW52: V | BX52: M | BY52: M | BZ52: V | CA52: V | CB52: M | CC52: V | CD52: M | CE52: V | CF52: M-O | CH52: V-O | CJ52: V-O | CK52: V-O | CL52: V-O | CM52: V-O | CN52: V-O | CO52: V-O | CP52: V-O | CQ52: V-O | CS52: V | CT52: V | CU52: V | DD52: V-O | DE52: V-O | DF52: V-O | DG52: V-O | DH52: V-O | DI52: V-O
A53: REQ-048 | B53: View | C53: View | D53: View | E53: Manage | F53: Process | G53: View | H53: View | I53: View | J53: View | K53: Manage | L53: View | M53: Control | N53: View | O53: Not applicable | Q53: V | R53: V | S53: V | T53: V | U53: V | V53: V | W53: V | X53: V | Y53: V-O | Z53: V-O | AA53: V-O | AB53: V-O | AC53: V-O | AD53: V-O | AE53: V-O | AG53: V-O | AH53: V-O | AI53: M | AJ53: M | AK53: V-O | AL53: M-O | AM53: M | AN53: M | AO53: M | AQ53: M | AR53: V | AS53: V | AX53: n/a | AY53: n/a | BB53: V | BE53: V | BF53: V | BH53: V | BI53: M-O | BJ53: M-O | BK53: M-O | BL53: M-O | BM53: M-O | BN53: M-O | BO53: M-O | BP53: V | BQ53: V | BT53: C | BU53: C | BW53: V | BZ53: V | CA53: V | CC53: V | CE53: V | CH53: V-O | CJ53: V-O | CK53: V-O | CL53: V-O | CM53: V-O | CN53: V-O | CO53: V-O | CP53: V-O | CQ53: V-O | CS53: V | CT53: V | CU53: V | DD53: V-O | DE53: V-O | DF53: V-O | DG53: V-O | DH53: V-O | DI53: V-O
A54: REQ-049 | B54: View | C54: View | D54: View | E54: Control | F54: View | G54: View | H54: View | I54: View | J54: View | K54: View | L54: View | M54: View | N54: View | O54: Not applicable | Q54: V | R54: V | S54: V | T54: V | U54: V | V54: V | W54: V | X54: V | Y54: V-O | Z54: V-O | AA54: V-O | AB54: V-O | AC54: V-O | AD54: V-O | AE54: V-O | AG54: V-O | AH54: V-O | AI54: C-O | AJ54: C-O | AK54: V-O | AR54: V | AS54: V | AV54: V | AX54: V | AY54: n/a | AZ54: n/a | BB54: V | BC54: V-O | BD54: V-O | BE54: V | BF54: V | BH54: V | BP54: V | BQ54: V | BW54: V | BZ54: V | CA54: V | CB54: V | CC54: V | CE54: V | CH54: V-O | CJ54: V-O | CK54: V-O | CL54: V-O | CM54: V-O | CN54: V-O | CO54: V-O | CP54: V-O | CQ54: V-O | CS54: V | CT54: V | CU54: V | DD54: V-O | DE54: V-O | DF54: V-O | DG54: V-O | DH54: V-O | DI54: V-O
A55: REQ-050 | B55: View | C55: View | D55: View | E55: Control | F55: View | G55: View | H55: View | I55: View | J55: View | K55: View | L55: View | M55: Manage | N55: View | O55: Not applicable | Q55: V | R55: V | S55: V | T55: V | U55: V | V55: V | W55: V | X55: V | Y55: V-O | Z55: V-O | AA55: V-O | AB55: V-O | AC55: V-O | AD55: V-O | AE55: V-O | AG55: V-O | AH55: V-O | AI55: C-O | AJ55: C-O | AK55: V-O | AR55: V | AS55: V | AV55: V | AX55: V | AY55: n/a | AZ55: n/a | BB55: V | BC55: V-O | BD55: V-O | BE55: V | BF55: V | BH55: V | BP55: V | BQ55: V | BR55: M | BS55: M | BW55: V | BX55: M | BY55: M | BZ55: V | CA55: V | CB55: M | CC55: V | CD55: M | CE55: V | CF55: M-O | CH55: V-O | CJ55: V-O | CK55: V-O | CL55: V-O | CM55: V-O | CN55: V-O | CO55: V-O | CP55: V-O | CQ55: V-O | CS55: V | CT55: V | CU55: V | DD55: V-O | DE55: V-O | DF55: V-O | DG55: V-O | DH55: V-O | DI55: V-O
A56: REQ-051 | B56: View | C56: View | D56: View | E56: Control | F56: View | G56: View | H56: View | I56: View | J56: View | K56: View | L56: View | M56: Control | N56: View | O56: Not applicable | Q56: V | R56: V | S56: V | T56: V | U56: V | V56: V | W56: V | X56: V | Y56: V-O | Z56: V-O | AA56: V-O | AB56: V-O | AC56: V-O | AD56: V-O | AE56: V-O | AG56: V-O | AH56: V-O | AI56: C-O | AJ56: C-O | AK56: V-O | AR56: V | AS56: V | AV56: V | AX56: V | AY56: n/a | AZ56: n/a | BB56: V | BC56: V-O | BD56: V-O | BE56: V | BF56: V | BH56: V | BP56: V | BQ56: V | BT56: C | BU56: C | BW56: V | BZ56: V | CA56: V | CC56: V | CE56: V | CH56: V-O | CJ56: V-O | CK56: V-O | CL56: V-O | CM56: V-O | CN56: V-O | CO56: V-O | CP56: V-O | CQ56: V-O | CS56: V | CT56: V | CU56: V | DD56: V-O | DE56: V-O | DF56: V-O | DG56: V-O | DH56: V-O | DI56: V-O
A57: REQ-052 | B57: View | C57: View | D57: View | E57: Control | F57: View | G57: View | H57: View | I57: View | J57: View | K57: Manage | L57: View | M57: View | N57: View | O57: Not applicable | Q57: V | R57: V | S57: V | T57: V | U57: V | V57: V | W57: V | X57: V | Y57: V-O | Z57: V-O | AA57: V-O | AB57: V-O | AC57: V-O | AD57: V-O | AE57: V-O | AG57: V-O | AH57: V-O | AI57: C-O | AJ57: C-O | AK57: V-O | AR57: V | AS57: V | AV57: V | AX57: V | AY57: n/a | AZ57: n/a | BB57: V | BC57: V-O | BD57: V-O | BE57: V | BF57: V | BH57: V | BI57: M-O | BJ57: M-O | BK57: M-O | BL57: M-O | BM57: M-O | BN57: M-O | BO57: M-O | BP57: V | BQ57: V | BW57: V | BZ57: V | CA57: V | CB57: V | CC57: V | CE57: V | CH57: V-O | CJ57: V-O | CK57: V-O | CL57: V-O | CM57: V-O | CN57: V-O | CO57: V-O | CP57: V-O | CQ57: V-O | CS57: V | CT57: V | CU57: V | DD57: V-O | DE57: V-O | DF57: V-O | DG57: V-O | DH57: V-O | DI57: V-O
A58: REQ-053 | B58: View | C58: View | D58: View | E58: Control | F58: View | G58: View | H58: View | I58: View | J58: View | K58: Manage | L58: View | M58: Manage | N58: View | O58: Not applicable | Q58: V | R58: V | S58: V | T58: V | U58: V | V58: V | W58: V | X58: V | Y58: V-O | Z58: V-O | AA58: V-O | AB58: V-O | AC58: V-O | AD58: V-O | AE58: V-O | AG58: V-O | AH58: V-O | AI58: C-O | AJ58: C-O | AK58: V-O | AR58: V | AS58: V | AV58: V | AX58: V | AY58: n/a | AZ58: n/a | BB58: V | BC58: V-O | BD58: V-O | BE58: V | BF58: V | BH58: V | BI58: M-O | BJ58: M-O | BK58: M-O | BL58: M-O | BM58: M-O | BN58: M-O | BO58: M-O | BP58: V | BQ58: V | BR58: M | BS58: M | BW58: V | BX58: M | BY58: M | BZ58: V | CA58: V | CB58: M | CC58: V | CD58: M | CE58: V | CF58: M-O | CH58: V-O | CJ58: V-O | CK58: V-O | CL58: V-O | CM58: V-O | CN58: V-O | CO58: V-O | CP58: V-O | CQ58: V-O | CS58: V | CT58: V | CU58: V | DD58: V-O | DE58: V-O | DF58: V-O | DG58: V-O | DH58: V-O | DI58: V-O
A59: REQ-054 | B59: View | C59: View | D59: View | E59: Control | F59: View | G59: View | H59: View | I59: View | J59: View | K59: Manage | L59: View | M59: Control | N59: View | O59: Not applicable | Q59: V | R59: V | S59: V | T59: V | U59: V | V59: V | W59: V | X59: V | Y59: V-O | Z59: V-O | AA59: V-O | AB59: V-O | AC59: V-O | AD59: V-O | AE59: V-O | AG59: V-O | AH59: V-O | AI59: C-O | AJ59: C-O | AK59: V-O | AR59: V | AS59: V | AV59: V | AX59: V | AY59: n/a | AZ59: n/a | BB59: V | BC59: V-O | BD59: V-O | BE59: V | BF59: V | BH59: V | BI59: M-O | BJ59: M-O | BK59: M-O | BL59: M-O | BM59: M-O | BN59: M-O | BO59: M-O | BP59: V | BQ59: V | BT59: C | BU59: C | BW59: V | BZ59: V | CA59: V | CC59: V | CE59: V | CH59: V-O | CJ59: V-O | CK59: V-O | CL59: V-O | CM59: V-O | CN59: V-O | CO59: V-O | CP59: V-O | CQ59: V-O | CS59: V | CT59: V | CU59: V | DD59: V-O | DE59: V-O | DF59: V-O | DG59: V-O | DH59: V-O | DI59: V-O
A60: REQ-055 | B60: View | C60: View | D60: View | E60: Control | F60: Manage | G60: View | H60: View | I60: View | J60: View | K60: View | L60: View | M60: View | N60: View | O60: Not applicable | Q60: V | R60: V | S60: V | T60: V | U60: V | V60: V | W60: V | X60: V | Y60: V-O | Z60: V-O | AA60: V-O | AB60: V-O | AC60: V-O | AD60: V-O | AE60: V-O | AG60: V-O | AH60: V-O | AI60: C-O | AJ60: C-O | AK60: V-O | AR60: V | AS60: V | AV60: M | AX60: M | AY60: n/a | AZ60: M | BB60: V | BC60: M-O | BD60: M-O | BE60: V | BF60: V | BH60: V | BP60: V | BQ60: V | BW60: V | BZ60: V | CA60: V | CB60: V | CC60: V | CE60: V | CH60: V-O | CJ60: V-O | CK60: V-O | CL60: V-O | CM60: V-O | CN60: V-O | CO60: V-O | CP60: V-O | CQ60: V-O | CS60: V | CT60: V | CU60: V | DD60: V-O | DE60: V-O | DF60: V-O | DG60: V-O | DH60: V-O | DI60: V-O
A61: REQ-056 | B61: View | C61: View | D61: View | E61: Control | F61: Manage | G61: View | H61: View | I61: View | J61: View | K61: View | L61: View | M61: Manage | N61: View | O61: Not applicable | Q61: V | R61: V | S61: V | T61: V | U61: V | V61: V | W61: V | X61: V | Y61: V-O | Z61: V-O | AA61: V-O | AB61: V-O | AC61: V-O | AD61: V-O | AE61: V-O | AG61: V-O | AH61: V-O | AI61: C-O | AJ61: C-O | AK61: V-O | AR61: V | AS61: V | AV61: M | AX61: M | AY61: n/a | AZ61: M | BB61: V | BC61: M-O | BD61: M-O | BE61: V | BF61: V | BH61: V | BP61: V | BQ61: V | BR61: M | BS61: M | BW61: V | BX61: M | BY61: M | BZ61: V | CA61: V | CB61: M | CC61: V | CD61: M | CE61: V | CF61: M-O | CH61: V-O | CJ61: V-O | CK61: V-O | CL61: V-O | CM61: V-O | CN61: V-O | CO61: V-O | CP61: V-O | CQ61: V-O | CS61: V | CT61: V | CU61: V | DD61: V-O | DE61: V-O | DF61: V-O | DG61: V-O | DH61: V-O | DI61: V-O
A62: REQ-057 | B62: View | C62: View | D62: View | E62: Control | F62: Manage | G62: View | H62: View | I62: View | J62: View | K62: View | L62: View | M62: Control | N62: View | O62: Not applicable | Q62: V | R62: V | S62: V | T62: V | U62: V | V62: V | W62: V | X62: V | Y62: V-O | Z62: V-O | AA62: V-O | AB62: V-O | AC62: V-O | AD62: V-O | AE62: V-O | AG62: V-O | AH62: V-O | AI62: C-O | AJ62: C-O | AK62: V-O | AR62: V | AS62: V | AV62: M | AX62: M | AY62: n/a | AZ62: M | BB62: V | BC62: M-O | BD62: M-O | BE62: V | BF62: V | BH62: V | BP62: V | BQ62: V | BT62: C | BU62: C | BW62: V | BZ62: V | CA62: V | CC62: V | CE62: V | CH62: V-O | CJ62: V-O | CK62: V-O | CL62: V-O | CM62: V-O | CN62: V-O | CO62: V-O | CP62: V-O | CQ62: V-O | CS62: V | CT62: V | CU62: V | DD62: V-O | DE62: V-O | DF62: V-O | DG62: V-O | DH62: V-O | DI62: V-O
A63: REQ-058 | B63: View | C63: View | D63: View | E63: Control | F63: Manage | G63: View | H63: View | I63: View | J63: View | K63: Manage | L63: View | M63: View | N63: View | O63: Not applicable | Q63: V | R63: V | S63: V | T63: V | U63: V | V63: V | W63: V | X63: V | Y63: V-O | Z63: V-O | AA63: V-O | AB63: V-O | AC63: V-O | AD63: V-O | AE63: V-O | AG63: V-O | AH63: V-O | AI63: C-O | AJ63: C-O | AK63: V-O | AR63: V | AS63: V | AV63: M | AX63: M | AY63: n/a | AZ63: M | BB63: V | BC63: M-O | BD63: M-O | BE63: V | BF63: V | BH63: V | BI63: M-O | BJ63: M-O | BK63: M-O | BL63: M-O | BM63: M-O | BN63: M-O | BO63: M-O | BP63: V | BQ63: V | BW63: V | BZ63: V | CA63: V | CB63: V | CC63: V | CE63: V | CH63: V-O | CJ63: V-O | CK63: V-O | CL63: V-O | CM63: V-O | CN63: V-O | CO63: V-O | CP63: V-O | CQ63: V-O | CS63: V | CT63: V | CU63: V | DD63: V-O | DE63: V-O | DF63: V-O | DG63: V-O | DH63: V-O | DI63: V-O
A64: REQ-059 | B64: View | C64: View | D64: View | E64: Control | F64: Manage | G64: View | H64: View | I64: View | J64: View | K64: Manage | L64: View | M64: Manage | N64: View | O64: Not applicable | Q64: V | R64: V | S64: V | T64: V | U64: V | V64: V | W64: V | X64: V | Y64: V-O | Z64: V-O | AA64: V-O | AB64: V-O | AC64: V-O | AD64: V-O | AE64: V-O | AG64: V-O | AH64: V-O | AI64: C-O | AJ64: C-O | AK64: V-O | AR64: V | AS64: V | AV64: M | AX64: M | AY64: n/a | AZ64: M | BB64: V | BC64: M-O | BD64: M-O | BE64: V | BF64: V | BH64: V | BI64: M-O | BJ64: M-O | BK64: M-O | BL64: M-O | BM64: M-O | BN64: M-O | BO64: M-O | BP64: V | BQ64: V | BR64: M | BS64: M | BW64: V | BX64: M | BY64: M | BZ64: V | CA64: V | CB64: M | CC64: V | CD64: M | CE64: V | CF64: M-O | CH64: V-O | CJ64: V-O | CK64: V-O | CL64: V-O | CM64: V-O | CN64: V-O | CO64: V-O | CP64: V-O | CQ64: V-O | CS64: V | CT64: V | CU64: V | DD64: V-O | DE64: V-O | DF64: V-O | DG64: V-O | DH64: V-O | DI64: V-O
A65: REQ-060 | B65: View | C65: View | D65: View | E65: Control | F65: Manage | G65: View | H65: View | I65: View | J65: View | K65: Manage | L65: View | M65: Control | N65: View | O65: Not applicable | Q65: V | R65: V | S65: V | T65: V | U65: V | V65: V | W65: V | X65: V | Y65: V-O | Z65: V-O | AA65: V-O | AB65: V-O | AC65: V-O | AD65: V-O | AE65: V-O | AG65: V-O | AH65: V-O | AI65: C-O | AJ65: C-O | AK65: V-O | AR65: V | AS65: V | AV65: M | AX65: M | AY65: n/a | AZ65: M | BB65: V | BC65: M-O | BD65: M-O | BE65: V | BF65: V | BH65: V | BI65: M-O | BJ65: M-O | BK65: M-O | BL65: M-O | BM65: M-O | BN65: M-O | BO65: M-O | BP65: V | BQ65: V | BT65: C | BU65: C | BW65: V | BZ65: V | CA65: V | CC65: V | CE65: V | CH65: V-O | CJ65: V-O | CK65: V-O | CL65: V-O | CM65: V-O | CN65: V-O | CO65: V-O | CP65: V-O | CQ65: V-O | CS65: V | CT65: V | CU65: V | DD65: V-O | DE65: V-O | DF65: V-O | DG65: V-O | DH65: V-O | DI65: V-O
A66: REQ-061 | B66: View | C66: View | D66: View | E66: Control | F66: Control | G66: View | H66: View | I66: View | J66: View | K66: View | L66: View | M66: View | N66: View | O66: Not applicable | Q66: V | R66: V | S66: V | T66: V | U66: V | V66: V | W66: V | X66: V | Y66: V-O | Z66: V-O | AA66: V-O | AB66: V-O | AC66: V-O | AD66: V-O | AE66: V-O | AG66: V-O | AH66: V-O | AI66: C-O | AJ66: C-O | AK66: V-O | AR66: V | AS66: V | AX66: M | AY66: C | BB66: V | BE66: V | BF66: V | BH66: V | BP66: V | BQ66: V | BW66: V | BZ66: V | CA66: V | CB66: V | CC66: V | CE66: V | CH66: V-O | CJ66: V-O | CK66: V-O | CL66: V-O | CM66: V-O | CN66: V-O | CO66: V-O | CP66: V-O | CQ66: V-O | CS66: V | CT66: V | CU66: V | DD66: V-O | DE66: V-O | DF66: V-O | DG66: V-O | DH66: V-O | DI66: V-O
A67: REQ-062 | B67: View | C67: View | D67: View | E67: Control | F67: Control | G67: View | H67: View | I67: View | J67: View | K67: View | L67: View | M67: Manage | N67: View | O67: Not applicable | Q67: V | R67: V | S67: V | T67: V | U67: V | V67: V | W67: V | X67: V | Y67: V-O | Z67: V-O | AA67: V-O | AB67: V-O | AC67: V-O | AD67: V-O | AE67: V-O | AG67: V-O | AH67: V-O | AI67: C-O | AJ67: C-O | AK67: V-O | AR67: V | AS67: V | AX67: M | AY67: C | BB67: V | BE67: V | BF67: V | BH67: V | BP67: V | BQ67: V | BR67: M | BS67: M | BW67: V | BX67: M | BY67: M | BZ67: V | CA67: V | CB67: M | CC67: V | CD67: M | CE67: V | CF67: M-O | CH67: V-O | CJ67: V-O | CK67: V-O | CL67: V-O | CM67: V-O | CN67: V-O | CO67: V-O | CP67: V-O | CQ67: V-O | CS67: V | CT67: V | CU67: V | DD67: V-O | DE67: V-O | DF67: V-O | DG67: V-O | DH67: V-O | DI67: V-O
A68: REQ-063 | B68: View | C68: View | D68: View | E68: Control | F68: Control | G68: View | H68: View | I68: View | J68: View | K68: View | L68: View | M68: Control | N68: View | O68: Not applicable | Q68: V | R68: V | S68: V | T68: V | U68: V | V68: V | W68: V | X68: V | Y68: V-O | Z68: V-O | AA68: V-O | AB68: V-O | AC68: V-O | AD68: V-O | AE68: V-O | AG68: V-O | AH68: V-O | AI68: C-O | AJ68: C-O | AK68: V-O | AR68: V | AS68: V | AX68: M | AY68: C | BB68: V | BE68: V | BF68: V | BH68: V | BP68: V | BQ68: V | BT68: C | BU68: C | BW68: V | BZ68: V | CA68: V | CC68: V | CE68: V | CH68: V-O | CJ68: V-O | CK68: V-O | CL68: V-O | CM68: V-O | CN68: V-O | CO68: V-O | CP68: V-O | CQ68: V-O | CS68: V | CT68: V | CU68: V | DD68: V-O | DE68: V-O | DF68: V-O | DG68: V-O | DH68: V-O | DI68: V-O
A69: REQ-064 | B69: View | C69: View | D69: View | E69: Control | F69: Control | G69: View | H69: View | I69: View | J69: View | K69: Manage | L69: View | M69: View | N69: View | O69: Not applicable | Q69: V | R69: V | S69: V | T69: V | U69: V | V69: V | W69: V | X69: V | Y69: V-O | Z69: V-O | AA69: V-O | AB69: V-O | AC69: V-O | AD69: V-O | AE69: V-O | AG69: V-O | AH69: V-O | AI69: C-O | AJ69: C-O | AK69: V-O | AR69: V | AS69: V | AX69: M | AY69: C | BB69: V | BE69: V | BF69: V | BH69: V | BI69: M-O | BJ69: M-O | BK69: M-O | BL69: M-O | BM69: M-O | BN69: M-O | BO69: M-O | BP69: V | BQ69: V | BW69: V | BZ69: V | CA69: V | CB69: V | CC69: V | CE69: V | CH69: V-O | CJ69: V-O | CK69: V-O | CL69: V-O | CM69: V-O | CN69: V-O | CO69: V-O | CP69: V-O | CQ69: V-O | CS69: V | CT69: V | CU69: V | DD69: V-O | DE69: V-O | DF69: V-O | DG69: V-O | DH69: V-O | DI69: V-O
A70: REQ-065 | B70: View | C70: View | D70: View | E70: Control | F70: Control | G70: View | H70: View | I70: View | J70: View | K70: Manage | L70: View | M70: Manage | N70: View | O70: Not applicable | Q70: V | R70: V | S70: V | T70: V | U70: V | V70: V | W70: V | X70: V | Y70: V-O | Z70: V-O | AA70: V-O | AB70: V-O | AC70: V-O | AD70: V-O | AE70: V-O | AG70: V-O | AH70: V-O | AI70: C-O | AJ70: C-O | AK70: V-O | AR70: V | AS70: V | AX70: M | AY70: C | BB70: V | BE70: V | BF70: V | BH70: V | BI70: M-O | BJ70: M-O | BK70: M-O | BL70: M-O | BM70: M-O | BN70: M-O | BO70: M-O | BP70: V | BQ70: V | BR70: M | BS70: M | BW70: V | BX70: M | BY70: M | BZ70: V | CA70: V | CB70: M | CC70: V | CD70: M | CE70: V | CF70: M-O | CH70: V-O | CJ70: V-O | CK70: V-O | CL70: V-O | CM70: V-O | CN70: V-O | CO70: V-O | CP70: V-O | CQ70: V-O | CS70: V | CT70: V | CU70: V | DD70: V-O | DE70: V-O | DF70: V-O | DG70: V-O | DH70: V-O | DI70: V-O
A71: REQ-066 | B71: View | C71: View | D71: View | E71: Control | F71: Control | G71: View | H71: View | I71: View | J71: View | K71: Manage | L71: View | M71: Control | N71: View | O71: Not applicable | Q71: V | R71: V | S71: V | T71: V | U71: V | V71: V | W71: V | X71: V | Y71: V-O | Z71: V-O | AA71: V-O | AB71: V-O | AC71: V-O | AD71: V-O | AE71: V-O | AG71: V-O | AH71: V-O | AI71: C-O | AJ71: C-O | AK71: V-O | AR71: V | AS71: V | AX71: M | AY71: C | BB71: V | BE71: V | BF71: V | BH71: V | BI71: M-O | BJ71: M-O | BK71: M-O | BL71: M-O | BM71: M-O | BN71: M-O | BO71: M-O | BP71: V | BQ71: V | BT71: C | BU71: C | BW71: V | BZ71: V | CA71: V | CC71: V | CE71: V | CH71: V-O | CJ71: V-O | CK71: V-O | CL71: V-O | CM71: V-O | CN71: V-O | CO71: V-O | CP71: V-O | CQ71: V-O | CS71: V | CT71: V | CU71: V | DD71: V-O | DE71: V-O | DF71: V-O | DG71: V-O | DH71: V-O | DI71: V-O
A72: REQ-067 | B72: View | C72: View | D72: View | E72: Control | F72: Process | G72: View | H72: View | I72: View | J72: View | K72: View | L72: View | M72: View | N72: View | O72: Not applicable | Q72: V | R72: V | S72: V | T72: V | U72: V | V72: V | W72: V | X72: V | Y72: V-O | Z72: V-O | AA72: V-O | AB72: V-O | AC72: V-O | AD72: V-O | AE72: V-O | AG72: V-O | AH72: V-O | AI72: C-O | AJ72: C-O | AK72: V-O | AR72: V | AS72: V | AX72: n/a | AY72: n/a | BB72: V | BE72: V | BF72: V | BH72: V | BP72: V | BQ72: V | BW72: V | BZ72: V | CA72: V | CB72: V | CC72: V | CE72: V | CH72: V-O | CJ72: V-O | CK72: V-O | CL72: V-O | CM72: V-O | CN72: V-O | CO72: V-O | CP72: V-O | CQ72: V-O | CS72: V | CT72: V | CU72: V | DD72: V-O | DE72: V-O | DF72: V-O | DG72: V-O | DH72: V-O | DI72: V-O
A73: REQ-068 | B73: View | C73: View | D73: View | E73: Control | F73: Process | G73: View | H73: View | I73: View | J73: View | K73: View | L73: View | M73: Manage | N73: View | O73: Not applicable | Q73: V | R73: V | S73: V | T73: V | U73: V | V73: V | W73: V | X73: V | Y73: V-O | Z73: V-O | AA73: V-O | AB73: V-O | AC73: V-O | AD73: V-O | AE73: V-O | AG73: V-O | AH73: V-O | AI73: C-O | AJ73: C-O | AK73: V-O | AR73: V | AS73: V | AX73: n/a | AY73: n/a | BB73: V | BE73: V | BF73: V | BH73: V | BP73: V | BQ73: V | BR73: M | BS73: M | BW73: V | BX73: M | BY73: M | BZ73: V | CA73: V | CB73: M | CC73: V | CD73: M | CE73: V | CF73: M-O | CH73: V-O | CJ73: V-O | CK73: V-O | CL73: V-O | CM73: V-O | CN73: V-O | CO73: V-O | CP73: V-O | CQ73: V-O | CS73: V | CT73: V | CU73: V | DD73: V-O | DE73: V-O | DF73: V-O | DG73: V-O | DH73: V-O | DI73: V-O
A74: REQ-069 | B74: View | C74: View | D74: View | E74: Control | F74: Process | G74: View | H74: View | I74: View | J74: View | K74: View | L74: View | M74: Control | N74: View | O74: Not applicable | Q74: V | R74: V | S74: V | T74: V | U74: V | V74: V | W74: V | X74: V | Y74: V-O | Z74: V-O | AA74: V-O | AB74: V-O | AC74: V-O | AD74: V-O | AE74: V-O | AG74: V-O | AH74: V-O | AI74: C-O | AJ74: C-O | AK74: V-O | AR74: V | AS74: V | AX74: n/a | AY74: n/a | BB74: V | BE74: V | BF74: V | BH74: V | BP74: V | BQ74: V | BT74: C | BU74: C | BW74: V | BZ74: V | CA74: V | CC74: V | CE74: V | CH74: V-O | CJ74: V-O | CK74: V-O | CL74: V-O | CM74: V-O | CN74: V-O | CO74: V-O | CP74: V-O | CQ74: V-O | CS74: V | CT74: V | CU74: V | DD74: V-O | DE74: V-O | DF74: V-O | DG74: V-O | DH74: V-O | DI74: V-O
A75: REQ-070 | B75: View | C75: View | D75: View | E75: Control | F75: Process | G75: View | H75: View | I75: View | J75: View | K75: Manage | L75: View | M75: View | N75: View | O75: Not applicable | Q75: V | R75: V | S75: V | T75: V | U75: V | V75: V | W75: V | X75: V | Y75: V-O | Z75: V-O | AA75: V-O | AB75: V-O | AC75: V-O | AD75: V-O | AE75: V-O | AG75: V-O | AH75: V-O | AI75: C-O | AJ75: C-O | AK75: V-O | AR75: V | AS75: V | AX75: n/a | AY75: n/a | BB75: V | BE75: V | BF75: V | BH75: V | BI75: M-O | BJ75: M-O | BK75: M-O | BL75: M-O | BM75: M-O | BN75: M-O | BO75: M-O | BP75: V | BQ75: V | BW75: V | BZ75: V | CA75: V | CB75: V | CC75: V | CE75: V | CH75: V-O | CJ75: V-O | CK75: V-O | CL75: V-O | CM75: V-O | CN75: V-O | CO75: V-O | CP75: V-O | CQ75: V-O | CS75: V | CT75: V | CU75: V | DD75: V-O | DE75: V-O | DF75: V-O | DG75: V-O | DH75: V-O | DI75: V-O
A76: REQ-071 | B76: View | C76: View | D76: View | E76: Control | F76: Process | G76: View | H76: View | I76: View | J76: View | K76: Manage | L76: View | M76: Manage | N76: View | O76: Not applicable | Q76: V | R76: V | S76: V | T76: V | U76: V | V76: V | W76: V | X76: V | Y76: V-O | Z76: V-O | AA76: V-O | AB76: V-O | AC76: V-O | AD76: V-O | AE76: V-O | AG76: V-O | AH76: V-O | AI76: C-O | AJ76: C-O | AK76: V-O | AR76: V | AS76: V | AX76: n/a | AY76: n/a | BB76: V | BE76: V | BF76: V | BH76: V | BI76: M-O | BJ76: M-O | BK76: M-O | BL76: M-O | BM76: M-O | BN76: M-O | BO76: M-O | BP76: V | BQ76: V | BR76: M | BS76: M | BW76: V | BX76: M | BY76: M | BZ76: V | CA76: V | CB76: M | CC76: V | CD76: M | CE76: V | CF76: M-O | CH76: V-O | CJ76: V-O | CK76: V-O | CL76: V-O | CM76: V-O | CN76: V-O | CO76: V-O | CP76: V-O | CQ76: V-O | CS76: V | CT76: V | CU76: V | DD76: V-O | DE76: V-O | DF76: V-O | DG76: V-O | DH76: V-O | DI76: V-O
A77: REQ-072 | B77: View | C77: View | D77: View | E77: Control | F77: Process | G77: View | H77: View | I77: View | J77: View | K77: Manage | L77: View | M77: Control | N77: View | O77: Not applicable | Q77: V | R77: V | S77: V | T77: V | U77: V | V77: V | W77: V | X77: V | Y77: V-O | Z77: V-O | AA77: V-O | AB77: V-O | AC77: V-O | AD77: V-O | AE77: V-O | AG77: V-O | AH77: V-O | AI77: C-O | AJ77: C-O | AK77: V-O | AR77: V | AS77: V | AX77: n/a | AY77: n/a | BB77: V | BE77: V | BF77: V | BH77: V | BI77: M-O | BJ77: M-O | BK77: M-O | BL77: M-O | BM77: M-O | BN77: M-O | BO77: M-O | BP77: V | BQ77: V | BT77: C | BU77: C | BW77: V | BZ77: V | CA77: V | CC77: V | CE77: V | CH77: V-O | CJ77: V-O | CK77: V-O | CL77: V-O | CM77: V-O | CN77: V-O | CO77: V-O | CP77: V-O | CQ77: V-O | CS77: V | CT77: V | CU77: V | DD77: V-O | DE77: V-O | DF77: V-O | DG77: V-O | DH77: V-O | DI77: V-O
A78: REQ-073 | B78: View | C78: View | D78: View | E78: Process | F78: View | G78: View | H78: View | I78: View | J78: View | K78: View | L78: View | M78: View | N78: View | O78: Not applicable | Q78: V | R78: V | S78: V | T78: V | U78: V | V78: V | W78: V | X78: V | Y78: V-O | Z78: V-O | AA78: V-O | AB78: V-O | AC78: V-O | AD78: V-O | AE78: V-O | AG78: V-O | AH78: V-O | AI78: P | AJ78: P | AK78: V-O | AR78: V | AS78: V | AV78: V | AX78: V | AY78: n/a | AZ78: n/a | BB78: V | BC78: V-O | BD78: V-O | BE78: V | BF78: V | BH78: V | BP78: V | BQ78: V | BW78: V | BZ78: V | CA78: V | CB78: V | CC78: V | CE78: V | CH78: V-O | CJ78: V-O | CK78: V-O | CL78: V-O | CM78: V-O | CN78: V-O | CO78: V-O | CP78: V-O | CQ78: V-O | CS78: V | CT78: V | CU78: V | DD78: V-O | DE78: V-O | DF78: V-O | DG78: V-O | DH78: V-O | DI78: V-O
A79: REQ-074 | B79: View | C79: View | D79: View | E79: Process | F79: View | G79: View | H79: View | I79: View | J79: View | K79: View | L79: View | M79: Manage | N79: View | O79: Not applicable | Q79: V | R79: V | S79: V | T79: V | U79: V | V79: V | W79: V | X79: V | Y79: V-O | Z79: V-O | AA79: V-O | AB79: V-O | AC79: V-O | AD79: V-O | AE79: V-O | AG79: V-O | AH79: V-O | AI79: P | AJ79: P | AK79: V-O | AR79: V | AS79: V | AV79: V | AX79: V | AY79: n/a | AZ79: n/a | BB79: V | BC79: V-O | BD79: V-O | BE79: V | BF79: V | BH79: V | BP79: V | BQ79: V | BR79: M | BS79: M | BW79: V | BX79: M | BY79: M | BZ79: V | CA79: V | CB79: M | CC79: V | CD79: M | CE79: V | CF79: M-O | CH79: V-O | CJ79: V-O | CK79: V-O | CL79: V-O | CM79: V-O | CN79: V-O | CO79: V-O | CP79: V-O | CQ79: V-O | CS79: V | CT79: V | CU79: V | DD79: V-O | DE79: V-O | DF79: V-O | DG79: V-O | DH79: V-O | DI79: V-O
A80: REQ-075 | B80: View | C80: View | D80: View | E80: Process | F80: View | G80: View | H80: View | I80: View | J80: View | K80: View | L80: View | M80: Control | N80: View | O80: Not applicable | Q80: V | R80: V | S80: V | T80: V | U80: V | V80: V | W80: V | X80: V | Y80: V-O | Z80: V-O | AA80: V-O | AB80: V-O | AC80: V-O | AD80: V-O | AE80: V-O | AG80: V-O | AH80: V-O | AI80: P | AJ80: P | AK80: V-O | AR80: V | AS80: V | AV80: V | AX80: V | AY80: n/a | AZ80: n/a | BB80: V | BC80: V-O | BD80: V-O | BE80: V | BF80: V | BH80: V | BP80: V | BQ80: V | BT80: C | BU80: C | BW80: V | BZ80: V | CA80: V | CC80: V | CE80: V | CH80: V-O | CJ80: V-O | CK80: V-O | CL80: V-O | CM80: V-O | CN80: V-O | CO80: V-O | CP80: V-O | CQ80: V-O | CS80: V | CT80: V | CU80: V | DD80: V-O | DE80: V-O | DF80: V-O | DG80: V-O | DH80: V-O | DI80: V-O
A81: REQ-076 | B81: View | C81: View | D81: View | E81: Process | F81: View | G81: View | H81: View | I81: View | J81: View | K81: Manage | L81: View | M81: View | N81: View | O81: Not applicable | Q81: V | R81: V | S81: V | T81: V | U81: V | V81: V | W81: V | X81: V | Y81: V-O | Z81: V-O | AA81: V-O | AB81: V-O | AC81: V-O | AD81: V-O | AE81: V-O | AG81: V-O | AH81: V-O | AI81: P | AJ81: P | AK81: V-O | AR81: V | AS81: V | AV81: V | AX81: V | AY81: n/a | AZ81: n/a | BB81: V | BC81: V-O | BD81: V-O | BE81: V | BF81: V | BH81: V | BI81: M-O | BJ81: M-O | BK81: M-O | BL81: M-O | BM81: M-O | BN81: M-O | BO81: M-O | BP81: V | BQ81: V | BW81: V | BZ81: V | CA81: V | CB81: V | CC81: V | CE81: V | CH81: V-O | CJ81: V-O | CK81: V-O | CL81: V-O | CM81: V-O | CN81: V-O | CO81: V-O | CP81: V-O | CQ81: V-O | CS81: V | CT81: V | CU81: V | DD81: V-O | DE81: V-O | DF81: V-O | DG81: V-O | DH81: V-O | DI81: V-O
A82: REQ-077 | B82: View | C82: View | D82: View | E82: Process | F82: View | G82: View | H82: View | I82: View | J82: View | K82: Manage | L82: View | M82: Manage | N82: View | O82: Not applicable | Q82: V | R82: V | S82: V | T82: V | U82: V | V82: V | W82: V | X82: V | Y82: V-O | Z82: V-O | AA82: V-O | AB82: V-O | AC82: V-O | AD82: V-O | AE82: V-O | AG82: V-O | AH82: V-O | AI82: P | AJ82: P | AK82: V-O | AR82: V | AS82: V | AV82: V | AX82: V | AY82: n/a | AZ82: n/a | BB82: V | BC82: V-O | BD82: V-O | BE82: V | BF82: V | BH82: V | BI82: M-O | BJ82: M-O | BK82: M-O | BL82: M-O | BM82: M-O | BN82: M-O | BO82: M-O | BP82: V | BQ82: V | BR82: M | BS82: M | BW82: V | BX82: M | BY82: M | BZ82: V | CA82: V | CB82: M | CC82: V | CD82: M | CE82: V | CF82: M-O | CH82: V-O | CJ82: V-O | CK82: V-O | CL82: V-O | CM82: V-O | CN82: V-O | CO82: V-O | CP82: V-O | CQ82: V-O | CS82: V | CT82: V | CU82: V | DD82: V-O | DE82: V-O | DF82: V-O | DG82: V-O | DH82: V-O | DI82: V-O
A83: REQ-078 | B83: View | C83: View | D83: View | E83: Process | F83: View | G83: View | H83: View | I83: View | J83: View | K83: Manage | L83: View | M83: Control | N83: View | O83: Not applicable | Q83: V | R83: V | S83: V | T83: V | U83: V | V83: V | W83: V | X83: V | Y83: V-O | Z83: V-O | AA83: V-O | AB83: V-O | AC83: V-O | AD83: V-O | AE83: V-O | AG83: V-O | AH83: V-O | AI83: P | AJ83: P | AK83: V-O | AR83: V | AS83: V | AV83: V | AX83: V | AY83: n/a | AZ83: n/a | BB83: V | BC83: V-O | BD83: V-O | BE83: V | BF83: V | BH83: V | BI83: M-O | BJ83: M-O | BK83: M-O | BL83: M-O | BM83: M-O | BN83: M-O | BO83: M-O | BP83: V | BQ83: V | BT83: C | BU83: C | BW83: V | BZ83: V | CA83: V | CC83: V | CE83: V | CH83: V-O | CJ83: V-O | CK83: V-O | CL83: V-O | CM83: V-O | CN83: V-O | CO83: V-O | CP83: V-O | CQ83: V-O | CS83: V | CT83: V | CU83: V | DD83: V-O | DE83: V-O | DF83: V-O | DG83: V-O | DH83: V-O | DI83: V-O
A84: REQ-079 | B84: View | C84: View | D84: View | E84: Process | F84: Manage | G84: View | H84: View | I84: View | J84: View | K84: View | L84: View | M84: View | N84: View | O84: Not applicable | Q84: V | R84: V | S84: V | T84: V | U84: V | V84: V | W84: V | X84: V | Y84: V-O | Z84: V-O | AA84: V-O | AB84: V-O | AC84: V-O | AD84: V-O | AE84: V-O | AG84: V-O | AH84: V-O | AI84: P | AJ84: P | AK84: V-O | AR84: V | AS84: V | AV84: M | AX84: M | AY84: n/a | AZ84: M | BB84: V | BC84: M-O | BD84: M-O | BE84: V | BF84: V | BH84: V | BP84: V | BQ84: V | BW84: V | BZ84: V | CA84: V | CB84: V | CC84: V | CE84: V | CH84: V-O | CJ84: V-O | CK84: V-O | CL84: V-O | CM84: V-O | CN84: V-O | CO84: V-O | CP84: V-O | CQ84: V-O | CS84: V | CT84: V | CU84: V | DD84: V-O | DE84: V-O | DF84: V-O | DG84: V-O | DH84: V-O | DI84: V-O
A85: REQ-080 | B85: View | C85: View | D85: View | E85: Process | F85: Manage | G85: View | H85: View | I85: View | J85: View | K85: View | L85: View | M85: Manage | N85: View | O85: Not applicable | Q85: V | R85: V | S85: V | T85: V | U85: V | V85: V | W85: V | X85: V | Y85: V-O | Z85: V-O | AA85: V-O | AB85: V-O | AC85: V-O | AD85: V-O | AE85: V-O | AG85: V-O | AH85: V-O | AI85: P | AJ85: P | AK85: V-O | AR85: V | AS85: V | AV85: M | AX85: M | AY85: n/a | AZ85: M | BB85: V | BC85: M-O | BD85: M-O | BE85: V | BF85: V | BH85: V | BP85: V | BQ85: V | BR85: M | BS85: M | BW85: V | BX85: M | BY85: M | BZ85: V | CA85: V | CB85: M | CC85: V | CD85: M | CE85: V | CF85: M-O | CH85: V-O | CJ85: V-O | CK85: V-O | CL85: V-O | CM85: V-O | CN85: V-O | CO85: V-O | CP85: V-O | CQ85: V-O | CS85: V | CT85: V | CU85: V | DD85: V-O | DE85: V-O | DF85: V-O | DG85: V-O | DH85: V-O | DI85: V-O
A86: REQ-081 | B86: View | C86: View | D86: View | E86: Process | F86: Manage | G86: View | H86: View | I86: View | J86: View | K86: View | L86: View | M86: Control | N86: View | O86: Not applicable | Q86: V | R86: V | S86: V | T86: V | U86: V | V86: V | W86: V | X86: V | Y86: V-O | Z86: V-O | AA86: V-O | AB86: V-O | AC86: V-O | AD86: V-O | AE86: V-O | AG86: V-O | AH86: V-O | AI86: P | AJ86: P | AK86: V-O | AR86: V | AS86: V | AV86: M | AX86: M | AY86: n/a | AZ86: M | BB86: V | BC86: M-O | BD86: M-O | BE86: V | BF86: V | BH86: V | BP86: V | BQ86: V | BT86: C | BU86: C | BW86: V | BZ86: V | CA86: V | CC86: V | CE86: V | CH86: V-O | CJ86: V-O | CK86: V-O | CL86: V-O | CM86: V-O | CN86: V-O | CO86: V-O | CP86: V-O | CQ86: V-O | CS86: V | CT86: V | CU86: V | DD86: V-O | DE86: V-O | DF86: V-O | DG86: V-O | DH86: V-O | DI86: V-O
A87: REQ-082 | B87: View | C87: View | D87: View | E87: Process | F87: Manage | G87: View | H87: View | I87: View | J87: View | K87: Manage | L87: View | M87: View | N87: View | O87: Not applicable | Q87: V | R87: V | S87: V | T87: V | U87: V | V87: V | W87: V | X87: V | Y87: V-O | Z87: V-O | AA87: V-O | AB87: V-O | AC87: V-O | AD87: V-O | AE87: V-O | AG87: V-O | AH87: V-O | AI87: P | AJ87: P | AK87: V-O | AR87: V | AS87: V | AV87: M | AX87: M | AY87: n/a | AZ87: M | BB87: V | BC87: M-O | BD87: M-O | BE87: V | BF87: V | BH87: V | BI87: M-O | BJ87: M-O | BK87: M-O | BL87: M-O | BM87: M-O | BN87: M-O | BO87: M-O | BP87: V | BQ87: V | BW87: V | BZ87: V | CA87: V | CB87: V | CC87: V | CE87: V | CH87: V-O | CJ87: V-O | CK87: V-O | CL87: V-O | CM87: V-O | CN87: V-O | CO87: V-O | CP87: V-O | CQ87: V-O | CS87: V | CT87: V | CU87: V | DD87: V-O | DE87: V-O | DF87: V-O | DG87: V-O | DH87: V-O | DI87: V-O
A88: REQ-083 | B88: View | C88: View | D88: View | E88: Process | F88: Manage | G88: View | H88: View | I88: View | J88: View | K88: Manage | L88: View | M88: Manage | N88: View | O88: Not applicable | Q88: V | R88: V | S88: V | T88: V | U88: V | V88: V | W88: V | X88: V | Y88: V-O | Z88: V-O | AA88: V-O | AB88: V-O | AC88: V-O | AD88: V-O | AE88: V-O | AG88: V-O | AH88: V-O | AI88: P | AJ88: P | AK88: V-O | AR88: V | AS88: V | AV88: M | AX88: M | AY88: n/a | AZ88: M | BB88: V | BC88: M-O | BD88: M-O | BE88: V | BF88: V | BH88: V | BI88: M-O | BJ88: M-O | BK88: M-O | BL88: M-O | BM88: M-O | BN88: M-O | BO88: M-O | BP88: V | BQ88: V | BR88: M | BS88: M | BW88: V | BX88: M | BY88: M | BZ88: V | CA88: V | CB88: M | CC88: V | CD88: M | CE88: V | CF88: M-O | CH88: V-O | CJ88: V-O | CK88: V-O | CL88: V-O | CM88: V-O | CN88: V-O | CO88: V-O | CP88: V-O | CQ88: V-O | CS88: V | CT88: V | CU88: V | DD88: V-O | DE88: V-O | DF88: V-O | DG88: V-O | DH88: V-O | DI88: V-O
A89: REQ-084 | B89: View | C89: View | D89: View | E89: Process | F89: Manage | G89: View | H89: View | I89: View | J89: View | K89: Manage | L89: View | M89: Control | N89: View | O89: Not applicable | Q89: V | R89: V | S89: V | T89: V | U89: V | V89: V | W89: V | X89: V | Y89: V-O | Z89: V-O | AA89: V-O | AB89: V-O | AC89: V-O | AD89: V-O | AE89: V-O | AG89: V-O | AH89: V-O | AI89: P | AJ89: P | AK89: V-O | AR89: V | AS89: V | AV89: M | AX89: M | AY89: n/a | AZ89: M | BB89: V | BC89: M-O | BD89: M-O | BE89: V | BF89: V | BH89: V | BI89: M-O | BJ89: M-O | BK89: M-O | BL89: M-O | BM89: M-O | BN89: M-O | BO89: M-O | BP89: V | BQ89: V | BT89: C | BU89: C | BW89: V | BZ89: V | CA89: V | CC89: V | CE89: V | CH89: V-O | CJ89: V-O | CK89: V-O | CL89: V-O | CM89: V-O | CN89: V-O | CO89: V-O | CP89: V-O | CQ89: V-O | CS89: V | CT89: V | CU89: V | DD89: V-O | DE89: V-O | DF89: V-O | DG89: V-O | DH89: V-O | DI89: V-O
A90: REQ-085 | B90: View | C90: View | D90: View | E90: Process | F90: Control | G90: View | H90: View | I90: View | J90: View | K90: View | L90: View | M90: View | N90: View | O90: Not applicable | Q90: V | R90: V | S90: V | T90: V | U90: V | V90: V | W90: V | X90: V | Y90: V-O | Z90: V-O | AA90: V-O | AB90: V-O | AC90: V-O | AD90: V-O | AE90: V-O | AG90: V-O | AH90: V-O | AI90: P | AJ90: P | AK90: V-O | AR90: V | AS90: V | AX90: M | AY90: C | BB90: V | BE90: V | BF90: V | BH90: V | BP90: V | BQ90: V | BW90: V | BZ90: V | CA90: V | CB90: V | CC90: V | CE90: V | CH90: V-O | CJ90: V-O | CK90: V-O | CL90: V-O | CM90: V-O | CN90: V-O | CO90: V-O | CP90: V-O | CQ90: V-O | CS90: V | CT90: V | CU90: V | DD90: V-O | DE90: V-O | DF90: V-O | DG90: V-O | DH90: V-O | DI90: V-O
A91: REQ-086 | B91: View | C91: View | D91: View | E91: Process | F91: Control | G91: View | H91: View | I91: View | J91: View | K91: View | L91: View | M91: Manage | N91: View | O91: Not applicable | Q91: V | R91: V | S91: V | T91: V | U91: V | V91: V | W91: V | X91: V | Y91: V-O | Z91: V-O | AA91: V-O | AB91: V-O | AC91: V-O | AD91: V-O | AE91: V-O | AG91: V-O | AH91: V-O | AI91: P | AJ91: P | AK91: V-O | AR91: V | AS91: V | AX91: M | AY91: C | BB91: V | BE91: V | BF91: V | BH91: V | BP91: V | BQ91: V | BR91: M | BS91: M | BW91: V | BX91: M | BY91: M | BZ91: V | CA91: V | CB91: M | CC91: V | CD91: M | CE91: V | CF91: M-O | CH91: V-O | CJ91: V-O | CK91: V-O | CL91: V-O | CM91: V-O | CN91: V-O | CO91: V-O | CP91: V-O | CQ91: V-O | CS91: V | CT91: V | CU91: V | DD91: V-O | DE91: V-O | DF91: V-O | DG91: V-O | DH91: V-O | DI91: V-O
A92: REQ-087 | B92: View | C92: View | D92: View | E92: Process | F92: Control | G92: View | H92: View | I92: View | J92: View | K92: View | L92: View | M92: Control | N92: View | O92: Not applicable | Q92: V | R92: V | S92: V | T92: V | U92: V | V92: V | W92: V | X92: V | Y92: V-O | Z92: V-O | AA92: V-O | AB92: V-O | AC92: V-O | AD92: V-O | AE92: V-O | AG92: V-O | AH92: V-O | AI92: P | AJ92: P | AK92: V-O | AR92: V | AS92: V | AX92: M | AY92: C | BB92: V | BE92: V | BF92: V | BH92: V | BP92: V | BQ92: V | BT92: C | BU92: C | BW92: V | BZ92: V | CA92: V | CC92: V | CE92: V | CH92: V-O | CJ92: V-O | CK92: V-O | CL92: V-O | CM92: V-O | CN92: V-O | CO92: V-O | CP92: V-O | CQ92: V-O | CS92: V | CT92: V | CU92: V | DD92: V-O | DE92: V-O | DF92: V-O | DG92: V-O | DH92: V-O | DI92: V-O
A93: REQ-088 | B93: View | C93: View | D93: View | E93: Process | F93: Control | G93: View | H93: View | I93: View | J93: View | K93: Manage | L93: View | M93: View | N93: View | O93: Not applicable | Q93: V | R93: V | S93: V | T93: V | U93: V | V93: V | W93: V | X93: V | Y93: V-O | Z93: V-O | AA93: V-O | AB93: V-O | AC93: V-O | AD93: V-O | AE93: V-O | AG93: V-O | AH93: V-O | AI93: P | AJ93: P | AK93: V-O | AR93: V | AS93: V | AX93: M | AY93: C | BB93: V | BE93: V | BF93: V | BH93: V | BI93: M-O | BJ93: M-O | BK93: M-O | BL93: M-O | BM93: M-O | BN93: M-O | BO93: M-O | BP93: V | BQ93: V | BW93: V | BZ93: V | CA93: V | CB93: V | CC93: V | CE93: V | CH93: V-O | CJ93: V-O | CK93: V-O | CL93: V-O | CM93: V-O | CN93: V-O | CO93: V-O | CP93: V-O | CQ93: V-O | CS93: V | CT93: V | CU93: V | DD93: V-O | DE93: V-O | DF93: V-O | DG93: V-O | DH93: V-O | DI93: V-O
A94: REQ-089 | B94: View | C94: View | D94: View | E94: Process | F94: Control | G94: View | H94: View | I94: View | J94: View | K94: Manage | L94: View | M94: Manage | N94: View | O94: Not applicable | Q94: V | R94: V | S94: V | T94: V | U94: V | V94: V | W94: V | X94: V | Y94: V-O | Z94: V-O | AA94: V-O | AB94: V-O | AC94: V-O | AD94: V-O | AE94: V-O | AG94: V-O | AH94: V-O | AI94: P | AJ94: P | AK94: V-O | AR94: V | AS94: V | AX94: M | AY94: C | BB94: V | BE94: V | BF94: V | BH94: V | BI94: M-O | BJ94: M-O | BK94: M-O | BL94: M-O | BM94: M-O | BN94: M-O | BO94: M-O | BP94: V | BQ94: V | BR94: M | BS94: M | BW94: V | BX94: M | BY94: M | BZ94: V | CA94: V | CB94: M | CC94: V | CD94: M | CE94: V | CF94: M-O | CH94: V-O | CJ94: V-O | CK94: V-O | CL94: V-O | CM94: V-O | CN94: V-O | CO94: V-O | CP94: V-O | CQ94: V-O | CS94: V | CT94: V | CU94: V | DD94: V-O | DE94: V-O | DF94: V-O | DG94: V-O | DH94: V-O | DI94: V-O
A95: REQ-090 | B95: View | C95: View | D95: View | E95: Process | F95: Control | G95: View | H95: View | I95: View | J95: View | K95: Manage | L95: View | M95: Control | N95: View | O95: Not applicable | Q95: V | R95: V | S95: V | T95: V | U95: V | V95: V | W95: V | X95: V | Y95: V-O | Z95: V-O | AA95: V-O | AB95: V-O | AC95: V-O | AD95: V-O | AE95: V-O | AG95: V-O | AH95: V-O | AI95: P | AJ95: P | AK95: V-O | AR95: V | AS95: V | AX95: M | AY95: C | BB95: V | BE95: V | BF95: V | BH95: V | BI95: M-O | BJ95: M-O | BK95: M-O | BL95: M-O | BM95: M-O | BN95: M-O | BO95: M-O | BP95: V | BQ95: V | BT95: C | BU95: C | BW95: V | BZ95: V | CA95: V | CC95: V | CE95: V | CH95: V-O | CJ95: V-O | CK95: V-O | CL95: V-O | CM95: V-O | CN95: V-O | CO95: V-O | CP95: V-O | CQ95: V-O | CS95: V | CT95: V | CU95: V | DD95: V-O | DE95: V-O | DF95: V-O | DG95: V-O | DH95: V-O | DI95: V-O
A96: REQ-091 | B96: View | C96: View | D96: View | E96: Process | F96: Process | G96: View | H96: View | I96: View | J96: View | K96: View | L96: View | M96: View | N96: View | O96: Not applicable | Q96: V | R96: V | S96: V | T96: V | U96: V | V96: V | W96: V | X96: V | Y96: V-O | Z96: V-O | AA96: V-O | AB96: V-O | AC96: V-O | AD96: V-O | AE96: V-O | AG96: V-O | AH96: V-O | AI96: P | AJ96: P | AK96: V-O | AR96: V | AS96: V | AX96: n/a | AY96: n/a | BB96: V | BE96: V | BF96: V | BH96: V | BP96: V | BQ96: V | BW96: V | BZ96: V | CA96: V | CB96: V | CC96: V | CE96: V | CH96: V-O | CJ96: V-O | CK96: V-O | CL96: V-O | CM96: V-O | CN96: V-O | CO96: V-O | CP96: V-O | CQ96: V-O | CS96: V | CT96: V | CU96: V | DD96: V-O | DE96: V-O | DF96: V-O | DG96: V-O | DH96: V-O | DI96: V-O
A97: REQ-092 | B97: View | C97: View | D97: View | E97: Process | F97: Process | G97: View | H97: View | I97: View | J97: View | K97: View | L97: View | M97: Manage | N97: View | O97: Not applicable | Q97: V | R97: V | S97: V | T97: V | U97: V | V97: V | W97: V | X97: V | Y97: V-O | Z97: V-O | AA97: V-O | AB97: V-O | AC97: V-O | AD97: V-O | AE97: V-O | AG97: V-O | AH97: V-O | AI97: P | AJ97: P | AK97: V-O | AR97: V | AS97: V | AX97: n/a | AY97: n/a | BB97: V | BE97: V | BF97: V | BH97: V | BP97: V | BQ97: V | BR97: M | BS97: M | BW97: V | BX97: M | BY97: M | BZ97: V | CA97: V | CB97: M | CC97: V | CD97: M | CE97: V | CF97: M-O | CH97: V-O | CJ97: V-O | CK97: V-O | CL97: V-O | CM97: V-O | CN97: V-O | CO97: V-O | CP97: V-O | CQ97: V-O | CS97: V | CT97: V | CU97: V | DD97: V-O | DE97: V-O | DF97: V-O | DG97: V-O | DH97: V-O | DI97: V-O
A98: REQ-093 | B98: View | C98: View | D98: View | E98: Process | F98: Process | G98: View | H98: View | I98: View | J98: View | K98: View | L98: View | M98: Control | N98: View | O98: Not applicable | Q98: V | R98: V | S98: V | T98: V | U98: V | V98: V | W98: V | X98: V | Y98: V-O | Z98: V-O | AA98: V-O | AB98: V-O | AC98: V-O | AD98: V-O | AE98: V-O | AG98: V-O | AH98: V-O | AI98: P | AJ98: P | AK98: V-O | AR98: V | AS98: V | AX98: n/a | AY98: n/a | BB98: V | BE98: V | BF98: V | BH98: V | BP98: V | BQ98: V | BT98: C | BU98: C | BW98: V | BZ98: V | CA98: V | CC98: V | CE98: V | CH98: V-O | CJ98: V-O | CK98: V-O | CL98: V-O | CM98: V-O | CN98: V-O | CO98: V-O | CP98: V-O | CQ98: V-O | CS98: V | CT98: V | CU98: V | DD98: V-O | DE98: V-O | DF98: V-O | DG98: V-O | DH98: V-O | DI98: V-O
A99: REQ-094 | B99: View | C99: View | D99: View | E99: Process | F99: Process | G99: View | H99: View | I99: View | J99: View | K99: Manage | L99: View | M99: View | N99: View | O99: Not applicable | Q99: V | R99: V | S99: V | T99: V | U99: V | V99: V | W99: V | X99: V | Y99: V-O | Z99: V-O | AA99: V-O | AB99: V-O | AC99: V-O | AD99: V-O | AE99: V-O | AG99: V-O | AH99: V-O | AI99: P | AJ99: P | AK99: V-O | AR99: V | AS99: V | AX99: n/a | AY99: n/a | BB99: V | BE99: V | BF99: V | BH99: V | BI99: M-O | BJ99: M-O | BK99: M-O | BL99: M-O | BM99: M-O | BN99: M-O | BO99: M-O | BP99: V | BQ99: V | BW99: V | BZ99: V | CA99: V | CB99: V | CC99: V | CE99: V | CH99: V-O | CJ99: V-O | CK99: V-O | CL99: V-O | CM99: V-O | CN99: V-O | CO99: V-O | CP99: V-O | CQ99: V-O | CS99: V | CT99: V | CU99: V | DD99: V-O | DE99: V-O | DF99: V-O | DG99: V-O | DH99: V-O | DI99: V-O
A100: REQ-095 | B100: View | C100: View | D100: View | E100: Process | F100: Process | G100: View | H100: View | I100: View | J100: View | K100: Manage | L100: View | M100: Manage | N100: View | O100: Not applicable | Q100: V | R100: V | S100: V | T100: V | U100: V | V100: V | W100: V | X100: V | Y100: V-O | Z100: V-O | AA100: V-O | AB100: V-O | AC100: V-O | AD100: V-O | AE100: V-O | AG100: V-O | AH100: V-O | AI100: P | AJ100: P | AK100: V-O | AR100: V | AS100: V | AX100: n/a | AY100: n/a | BB100: V | BE100: V | BF100: V | BH100: V | BI100: M-O | BJ100: M-O | BK100: M-O | BL100: M-O | BM100: M-O | BN100: M-O | BO100: M-O | BP100: V | BQ100: V | BR100: M | BS100: M | BW100: V | BX100: M | BY100: M | BZ100: V | CA100: V | CB100: M | CC100: V | CD100: M | CE100: V | CF100: M-O | CH100: V-O | CJ100: V-O | CK100: V-O | CL100: V-O | CM100: V-O | CN100: V-O | CO100: V-O | CP100: V-O | CQ100: V-O | CS100: V | CT100: V | CU100: V | DD100: V-O | DE100: V-O | DF100: V-O | DG100: V-O | DH100: V-O | DI100: V-O
...

Sheet 20260807 SZ App Integration
A1: Production User Packages
A2: Display Name | D2: Admin Accounts And Profiles | E2: Admin Accounts, Profiles And Servicing | F2: Admin All | G2: Admin Orders | H2: Admin Servicing Requests | I2: Config Platform | J2: Manage Accounts And Profiles | K2: Manage All | L2: Manage Accounts, Profiles, Servicing and Trades Manage All But Not Orders | M2: Manage Firms And Users | N2: Manage Orders | O2: Manage Servicing and Trades | P2: Manage Servicing Requests | Q2: Process Accounts And Profiles | R2: Process Trades | S2: View Only Confidential Profile | T2: Manage Servicing and Orders | U2: Manage Transactions | V2: Manage Orders and Trades | W2: Global Admin | X2: Manage Users | Y2: Manage Users Passwords | Z2: Manage All but not Trades | AA2: Admin All but not Trades | AB2: Admin Orders and Trades | AC2: Full Admin Trades | AD2: Client User Management (new Package; name TBD)
A3: Package Name (current) | D3: AdminAccountsAndProfiles_V1.17 | E3: AdminAllButNotTrade_V1.17 | F3: AdminAll_V1.17 | G3: AdminOrders_V1.17 | H3: AdminServiceRequests_V1.17 | I3: ConfigurePlatformV1.17 | J3: ManageAccountsAndProfiles_V1.17 | K3: ManageAll_V1.17 | L3: ManageAllButNotTrade_v1.16 | M3: ManageFirmAndUser_V1.17 | N3: ManageOrders_V1.17 | O3: ManageServicingandTrades | P3: ManageServiceRequests_V1.17 | Q3: ProcessAccounts_V1.17 | R3: ManagePostTrade_V1.17 | S3: ViewOnlyConfidentialProfile_V1.17 | T3: ManageServicingAndOrders | U3: ManageTransactions_V1.17 | V3: ManageOrdersAndTrades | W3: GlobalAdmin | X3: TBD | Y3: TBD | Z3: TBD | AA3: TBD | AB3: TBD | AC3: TBD | AD3: TBD
A5: Capability Mapping | C5: ACCOUNTS | D5: Open & Modify Accounts | E5: Open & Modify Accounts | F5: Open & Modify Accounts | G5: Open & Modify Accounts | H5: Open & Modify Accounts | I5: Open & Modify Accounts | J5: Open & Modify Accounts | K5: Open & Modify Accounts | L5: Open & Modify Accounts | M5: Open & Modify Accounts | N5: Open & Modify Accounts | O5: Open & Modify Accounts | P5: Open & Modify Accounts | Q5: Open & Modify Accounts | R5: Open & Modify Accounts | S5: Open & Modify Accounts | T5: Open & Modify Accounts | U5: Open & Modify Accounts | V5: Open & Modify Accounts | W5: Open & Modify Accounts | X5: Open & Modify Accounts | Y5: Open & Modify Accounts | Z5: Open & Modify Accounts | AA5: Open & Modify Accounts | AB5: Open & Modify Accounts | AC5: Open & Modify Accounts | AD5: Open & Modify Accounts
C6: SERVICING | D6: Asset Servicing | E6: Asset Servicing | F6: Asset Servicing | G6: Asset Servicing | H6: Asset Servicing | I6: Asset Servicing | J6: Asset Servicing | K6: Asset Servicing | L6: Asset Servicing | M6: Asset Servicing | N6: Asset Servicing | O6: Asset Servicing | P6: Asset Servicing | Q6: Asset Servicing | R6: Asset Servicing | S6: Asset Servicing | T6: Asset Servicing | U6: Asset Servicing | V6: Asset Servicing | W6: Asset Servicing | X6: Asset Servicing | Y6: Asset Servicing | Z6: Asset Servicing | AA6: Asset Servicing | AB6: Asset Servicing | AC6: Asset Servicing | AD6: Asset Servicing
C8: ORDERS | D8: Orders | E8: Orders | F8: Orders | G8: Orders | H8: Orders | I8: Orders | J8: Orders | K8: Orders | L8: Orders | M8: Orders | N8: Orders | O8: Orders | P8: Orders | Q8: Orders | R8: Orders | S8: Orders | T8: Orders | U8: Orders | V8: Orders | W8: Orders | X8: Orders | Y8: Orders | Z8: Orders | AA8: Orders | AB8: Orders | AC8: Orders | AD8: Orders
C9: TRADES | D9: Trades | E9: Trades | F9: Trades | G9: Trades | H9: Trades | I9: Trades | J9: Trades | K9: Trades | L9: Trades | M9: Trades | N9: Trades | O9: Trades | P9: Trades | Q9: Trades | R9: Trades | S9: Trades | T9: Trades | U9: Trades | V9: Trades | W9: Trades | X9: Trades | Y9: Trades | Z9: Trades | AA9: Trades | AB9: Trades | AC9: Trades | AD9: Trades
C11: PLATFORM | D11: Firm Management | E11: Firm Management | F11: Firm Management | G11: Firm Management | H11: Firm Management | I11: Firm Management | J11: Firm Management | K11: Firm Management | L11: Firm Management | M11: Firm Management | N11: Firm Management | O11: Firm Management | P11: Firm Management | Q11: Firm Management | R11: Firm Management | S11: Firm Management | T11: Firm Management | U11: Firm Management | V11: Firm Management | W11: Firm Management | X11: Firm Management | Y11: Firm Management | Z11: Firm Management | AA11: Firm Management | AB11: Firm Management | AC11: Firm Management | AD11: Firm Management
D12: User Management | E12: User Management | F12: User Management | G12: User Management | H12: User Management | I12: User Management | J12: User Management | K12: User Management | L12: User Management | M12: User Management | N12: User Management | O12: User Management | P12: User Management | Q12: User Management | R12: User Management | S12: User Management | T12: User Management | U12: User Management | V12: User Management | W12: User Management | X12: User Management | Y12: User Management | Z12: User Management | AA12: User Management | AB12: User Management | AC12: User Management | AD12: User Management
D13: Configuration | E13: Configuration | F13: Configuration | G13: Configuration | H13: Configuration | I13: Configuration | J13: Configuration | K13: Configuration | L13: Configuration | M13: Configuration | N13: Configuration | O13: Configuration | P13: Configuration | Q13: Configuration | R13: Configuration | S13: Configuration | T13: Configuration | U13: Configuration | V13: Configuration | W13: Configuration | X13: Configuration | Y13: Configuration | Z13: Configuration | AA13: Configuration | AB13: Configuration | AC13: Configuration | AD13: Configuration
A15: Capability Controls | C15: View | D15: 1 | E15: 1 | F15: 1 | G15: 1 | H15: 1 | I15: 1 | J15: 1 | K15: 1 | L15: 1 | M15: 1 | N15: 1 | O15: 1 | P15: 1 | Q15: 1 | R15: 1 | S15: 1 | T15: 1 | U15: 1 | V15: 1 | W15: 1 | X15: 1 | Y15: 1 | Z15: 1 | AA15: 1 | AB15: 1 | AC15: 1
C16: Manage | D16: 1 | E16: 1 | F16: 1 | G16: 1 | H16: 1 | I16: 1 | J16: 1 | K16: 1 | L16: 1 | M16: 1 | N16: 1 | O16: 1 | P16: 1 | Q16: 1 | R16: 1 | S16: 0 | T16: 1 | U16: 1 | V16: 1 | W16: 1 | X16: 1 | Y16: 1 | Z16: 1 | AA16: 1 | AB16: 1 | AC16: 1
C17: Control | D17: 1 | E17: 1 | F17: 1 | G17: 0 | H17: 1 | I17: 0 | J17: 0 | K17: 0 | L17: 0 | M17: 0 | N17: 0 | O17: 0 | P17: 0 | Q17: 0 | R17: 0 | S17: 0 | T17: 0 | U17: 0 | V17: 0 | W17: 1 | X17: 0 | Y17: 0 | Z17: 0 | AA17: 1 | AB17: 1 | AC17: 1
C18: Process | D18: 0 | E18: 0 | F18: 0 | G18: 0 | H18: 0 | I18: 0 | J18: 0 | K18: 0 | L18: 0 | M18: 0 | N18: 0 | O18: 0 | P18: 0 | Q18: 1 | R18: 1 | S18: 0 | T18: 0 | U18: 0 | V18: 0 | W18: 1 | X18: 0 | Y18: 0 | Z18: 0 | AA18: 0 | AB18: 1 | AC18: 1
B19: Eligibility | D19: Internal | E19: Internal | F19: Internal | G19: Internal | H19: Internal | I19: Internal Only | J19: Internal | K19: Internal | L19: Internal | M19: Internal Only | N19: Internal | O19: Internal | P19: Internal | Q19: Internal Only | R19: Internal Only | S19: Internal | T19: Internal | U19: Internal | V19: Internal | W19: Internal | X19: Internal | Y19: Internal | Z19: Internal | AA19: Internal | AB19: Internal | AC19: Internal | AD19: Internal
D20: *External (IBs Only) | E20: External | F20: External | G20: External | H20: External | J20: External | K20: External | L20: External | N20: External | O20: External | P20: External | S20: External | T20: External | U20: External | Z20: External | AA20: External | AD20: External
A21: Product Group | B21: Module
A22: Platform | B22: System Health Events | M22: Manage | W22: Manage
B23: View System Health Events | D23: View | E23: View | F23: View | G23: View | H23: View | J23: View | K23: View | L23: View | M23: View | N23: View | O23: View | P23: View | Q23: View | R23: View | S23: View | T23: View | U23: View | V23: View | W23: View | X23: View | Y23: View | Z23: View | AA23: View | AB23: View | AC23: View
B24: Features | M24: View | W24: View
B25: Manage Feature Configuration | M25: Manage | W25: Manage
B26: Manage Login Support Only | M26: Manage - To be removed (NWPI-14667)
A27: Client Lifecycle Management | B27: Onboarding: Form Applications | D27: View | E27: View | F27: View | G27: View to be added (NWPI-14494) | H27: View | J27: View | K27: View | L27: View | N27: View to be added (NWPI-14494) | O27: View to be added (NWPI-14494) | P27: View | Q27: View | R27: View to be added (NWPI-14494) | S27: View | T27: View | U27: View to be added (NWPI-14494) | V27: View to be Added (NWPI-14790) | W27: View | Z27: View | AA27: View | AB27: View | AC27: View
B28: Onboarding: Paper Upload | D28: View/Control | E28: View/Control | F28: View/Control | G28: View | H28: View | J28: View/Manage | K28: View/Manage | L28: View/Manage | M28: View - To be removed (NWPI-14667) | N28: View | O28: View | P28: View | Q28: View/Process | R28: View | S28: View | T28: View | U28: View | V28: View to Be Added (NWPI-14791) | W28: View/Control | Z28: View/Manage | AA28: View/Control | AB28: View | AC28: View
B29: Onboarding: Questionnaire Applications | D29: To be removed (NWPI-14666) | E29: To be removed (NWPI-14666) | F29: To be removed (NWPI-14666) | G29: To be removed (NWPI-14666) | H29: To be removed (NWPI-14666) | J29: To be removed (NWPI-14666) | K29: To be removed (NWPI-14666) | L29: To be removed (NWPI-14666) | M29: To be removed (NWPI-14666) | N29: To be removed (NWPI-14666) | O29: To be removed (NWPI-14666) | P29: To be removed (NWPI-14666) | Q29: To be removed (NWPI-14666) | R29: To be removed (NWPI-14666) | S29: To be removed (NWPI-14666) | T29: To be removed (NWPI-14666) | U29: To be removed (NWPI-14666) | W29: To be removed (NWPI-14666) | Z29: To be removed (NWPI-14666) | AA29: To be removed (NWPI-14666)
B30: Onboarding: Approve Option Applications | D30: Control | E30: Control | F30: Control | W30: Control | AA30: Control
B31: CRS-FATCA | D31: View/Manage | E31: View/Manage | F31: View/Manage | H31: View | J31: View/Manage | K31: View/Manage | L31: View/Manage | N31: View | O31: View | P31: View | Q31: View/Manage | S31: View | T31: View | U31: View | V31: View | W31: View/Manage | Z31: View/Manage | AA31: View/Manage | AB31: View | AC31: View
A32: Client Inquiry & Insights ("Accounts") | B32: Accounts | D32: View | E32: View | F32: View | G32: View | H32: View | J32: View | K32: View | L32: View | M32: View | N32: View | O32: View | P32: View | Q32: View | R32: View | S32: View | T32: View | U32: View | V32: View | W32: View | X32: View | Y32: View | Z32: View | AA32: View | AB32: View | AC32: View
B33: Statements | D33: View | E33: View | F33: View | G33: View | H33: View | J33: View | K33: View | L33: View | M33: View - To be removed (NWPI-14667) | N33: View | O33: View | P33: View | Q33: View | R33: View | S33: View | T33: View | U33: View | V33: View | W33: View | Z33: View | AA33: View | AB33: View | AC33: View
B34: Tax Documents | D34: View | E34: View | F34: View | G34: View | H34: View | J34: View | K34: View | L34: View | M34: View - To be removed (NWPI-14667) | N34: View | O34: View | P34: View | Q34: View | R34: View | S34: View | T34: View | U34: View | V34: View | W34: View | Z34: View | AA34: View | AB34: View | AC34: View
B35: Trade Confirmations | D35: View | E35: View | F35: View | G35: View | H35: View | J35: View | K35: View | L35: View | M35: View - To be removed (NWPI-14667) | N35: View | O35: View | P35: View | Q35: View | R35: View | S35: View | T35: View | U35: View | V35: View | W35: View | Z35: View | AA35: View | AB35: View | AC35: View
A36: Client Servicing ("Servicing") | B36: Servicing | D36: View | E36: View/Manage | F36: View/Manage | G36: View | H36: View/Manage | J36: View | K36: View/Manage | L36: View/Manage | M36: View - To be removed (NWPI-14667) | N36: View | O36: View (exists) Manage to be added (NWPI-14791) | P36: View/Manage | Q36: View | R36: View | S36: View | T36: View/Manage | U36: View Manage to be added NWPI-14791 | W36: View/Manage | Z36: View/Manage | AA36: View/Manage
B37: Servicing: Approvals | E37: Control | F37: Control | H37: Control | W37: Control | AA37: Control
A38: Order Management ("Orders") | B38: Orders | D38: View | E38: View | F38: View | G38: View | H38: View | J38: View | K38: View | L38: View | M38: View - To be removed (NWPI-14667) | N38: View | O38: View | P38: View | Q38: View | R38: View | S38: View | T38: View | U38: View | V38: View | W38: View | Z38: View | AA38: View | AB38: View | AC38: View
B39: Manage Equity Orders | F39: Manage | G39: Manage | K39: Manage | N39: Manage | T39: Manage | U39: Manage | V39: Manage | W39: Manage | Z39: Manage | AA39: Manage | AB39: Manage
B40: Manage Options Orders | F40: Manage | G40: Manage | K40: Manage | N40: Manage | T40: Manage | U40: Manage | V40: Manage | W40: Manage | Z40: Manage | AA40: Manage | AB40: Manage
B41: Manage Mutual Fund Orders | F41: Manage | G41: Manage | K41: Manage | N41: Manage | T41: Manage | U41: Manage | V41: Manage | W41: Manage | Z41: Manage | AA41: Manage | AB41: Manage
B42: Orders: MF Uploads | F42: View/Manage | G42: View/Manage | K42: View/Manage | N42: View/Manage | T42: View/Manage | U42: View/Manage | V42: Manage | W42: Manage | Z42: Manage | AA42: Manage | AB42: View/Manage
B43: Orders: Uploads | F43: View/Manage | G43: View/Manage | K43: View/Manage | N43: View/Manage | T43: Missing | U43: Missing | V43: Manage | W43: Manage | Z43: Manage | AA43: Manage | AB43: View/Manage
B44: Orders: GIC | F44: Manage | G44: Manage | K44: Manage | N44: Manage | T44: Manage | U44: Manage | V44: Manage | W44: Manage | Z44: Manage | AA44: Manage | AB44: Manage
B45: Allocations (New Issues) | F45: Manage (Optional Entitlement) | K45: Manage (Optional Entitlement) | N45: Manage (Optional Entitlement) | T45: Manage (Optional Entitlement) | U45: Manage (Optional Entitlement) | V45: Manage (Optional Entitlement) | W45: Manage (Optional Entitlement) | Z45: Manage (Optional Entitlement) | AA45: Manage (Optional Entitlement) | AB45: Manage (Optional Entitlement)
A46: Trade Operations ("Trades") | B46: Trade Allocations | D46: View to be added (NWPI-14589) | E46: View to be added (NWPI-14589) | F46: View/Manage | G46: View (exists) Manage to be removed (NWPI-14589) | H46: View to be added (NWPI-14589) | I46: Tech Support | J46: View to be added (NWPI-14589) | K46: View/Manage | L46: View to be added (NWPI-14589) Manage To be added (NWPI-14589) | M46: View - To be removed (NWPI-14589) | N46: View to be added (NWPI-14589) | O46: View to be added (NWPI-14589) Manage To be added (NWPI-14589) | P46: View to be added (NWPI-14589) | Q46: View to be added (NWPI-14589) | R46: View (exists) Manage to be added (NWPI-14589) | S46: View | T46: View to be added (NWPI-14589) | U46: View To be added (NWPI-14589) Manage To be added (NWPI-14589) | V46: View/Manage | W46: View/Manage | Z46: View to be added NWPI-14433 | AA46: View to be added NWPI-14440 | AB46: View/Manage | AC46: View/Manage
B47: Trade Allocations: Approvals | F47: Control | G47: Control to be removed (NWPI-14589) | K47: Control to be removed (NWPI-14589) | W47: Control | AB47: Control | AC47: Control
B48: Trade Allocations: Processing | F48: Process to be removed (NWPI-14589) | G48: Process to be removed (NWPI-14589) | K48: Process to be removed (NWPI-14589) | R48: Process | W48: Process | AB48: Process | AC48: Process
B49: MaxLite | D49: View | E49: View | F49: View | H49: View | J49: View | K49: View | L49: View | N49: View | O49: View | P49: View | Q49: View | S49: View | T49: View | U49: View | V49: View | W49: View | Z49: View | AA49: View | AB49: View | AC49: View
B50: FundFacts | F50: Manage (Optional Entitlement) | K50: Manage (Optional Entitlement) | L50: Manage (Optional Entitlement) | O50: Manage (Optional Entitlement) | U50: Manage (Optional Entitlement) | V50: Manage (Optional Entitlement) | W50: Manage (Optional Entitlement) | AB50: Manage (Optional Entitlement) | AC50: Manage (Optional Entitlement)
B51: FundFacts History
A52: Tools | B52: Data Export | D52: View | E52: View | F52: View | H52: View | J52: View | K52: View | L52: View | M52: View | N52: View | O52: View | P52: View | Q52: View | S52: View | T52: View | U52: View | V52: View | W52: View | Z52: View | AA52: View | AB52: View | AC52: View
B53: Tools | D53: View | E53: View | F53: View | H53: View | J53: View | K53: View | L53: View | M53: View | N53: View | O53: View | P53: View | Q53: View | S53: View | T53: View | U53: View | V53: View | W53: View | Z53: View | AA53: View | AB53: View | AC53: View
A54: Navigation | B54: Compass (Legacy) | D54: View | E54: View | F54: View | H54: View | J54: View | K54: View | L54: View | M54: View | N54: View | O54: View | P54: View | Q54: View | S54: View | T54: View | U54: View | V54: View | W54: View | X54: View | Y54: View | Z54: View | AA54: View | AB54: View | AC54: View
A55: Non-Core: Investor Portal | B55: MyPortfolio+ IA | D55: View (Optional Entitlement) | E55: View (Optional Entitlement) | F55: View (Optional Entitlement) | H55: View (Optional Entitlement) | J55: View (Optional Entitlement) | K55: View (Optional Entitlement) | L55: View (Optional Entitlement) | N55: View (Optional Entitlement) | O55: View (Optional Entitlement) | P55: View (Optional Entitlement) | Q55: View (Optional Entitlement) | S55: View (Optional Entitlement) | T55: View (Optional Entitlement) | U55: View (Optional Entitlement) | V55: View (Optional Entitlement) | W55: View (Optional Entitlement) | Z55: View (Optional Entitlement) | AA55: View (Optional Entitlement) | AB55: View (Optional Entitlement) | AC55: View (Optional Entitlement)
B56: Bulk Document Upload | D56: View (Optional Entitlement) | E56: View (Optional Entitlement) | F56: View (Optional Entitlement) | H56: View (Optional Entitlement) | J56: View (Optional Entitlement) | K56: View (Optional Entitlement) | L56: View (Optional Entitlement) | N56: View (Optional Entitlement) | O56: View (Optional Entitlement) | P56: View (Optional Entitlement) | Q56: View (Optional Entitlement) | S56: View (Optional Entitlement) | T56: View (Optional Entitlement) | U56: View (Optional Entitlement) | V56: View (Optional Entitlement) | W56: View (Optional Entitlement) | Z56: View (Optional Entitlement) | AA56: View (Optional Entitlement) | AB56: View (Optional Entitlement) | AC56: View (Optional Entitlement)
B57: MyPortfolio+ User Admin | D57: View (Optional Entitlement) | E57: View (Optional Entitlement) | F57: View (Optional Entitlement) | H57: View (Optional Entitlement) | J57: View (Optional Entitlement) | K57: View (Optional Entitlement) | L57: View (Optional Entitlement) | N57: View (Optional Entitlement) | O57: View (Optional Entitlement) | P57: View (Optional Entitlement) | Q57: View (Optional Entitlement) | S57: View (Optional Entitlement) | T57: View (Optional Entitlement) | U57: View (Optional Entitlement) | V57: View (Optional Entitlement) | W57: View (Optional Entitlement) | Z57: View (Optional Entitlement) | AA57: View (Optional Entitlement) | AB57: View (Optional Entitlement) | AC57: View (Optional Entitlement) | AD57: View (Optional Entitlement)
A58: Non-Core: Data | B58: CRMA | D58: View (Optional Entitlement) | E58: View (Optional Entitlement) | F58: View (Optional Entitlement) | H58: View (Optional Entitlement) | J58: View (Optional Entitlement) | K58: View (Optional Entitlement) | L58: View (Optional Entitlement) | N58: View (Optional Entitlement) | O58: View (Optional Entitlement) | P58: View (Optional Entitlement) | Q58: View (Optional Entitlement) | S58: View (Optional Entitlement) | T58: View (Optional Entitlement) | U58: View (Optional Entitlement) | V58: View (Optional Entitlement) | W58: View (Optional Entitlement) | Z58: View (Optional Entitlement) | AA58: View (Optional Entitlement) | AB58: View (Optional Entitlement) | AC58: View (Optional Entitlement)
B59: Web Panagon | D59: View (Optional Entitlement) | E59: View (Optional Entitlement) | F59: View (Optional Entitlement) | H59: View (Optional Entitlement) | J59: View (Optional Entitlement) | K59: View (Optional Entitlement) | L59: View (Optional Entitlement) | N59: View (Optional Entitlement) | O59: View (Optional Entitlement) | P59: View (Optional Entitlement) | Q59: View (Optional Entitlement) | S59: View (Optional Entitlement) | T59: View (Optional Entitlement) | U59: View (Optional Entitlement) | V59: View (Optional Entitlement) | W59: View (Optional Entitlement) | Z59: View (Optional Entitlement) | AA59: View (Optional Entitlement) | AB59: View (Optional Entitlement) | AC59: View (Optional Entitlement)

Sheet Full Map Legend
B1: R2 Features that don't need to be included in the reconcilation exercise, as the controls are not driven by CX
B2: CX Features that are part of the packages, but have the same control across all of them
B3: CX Features that are part of the packages, AND have multiple controls and impact the package assignment based on UAR selection
B4: Upcoming CX Features that are part of the packages, AND have multiple controls and impact the package assignment based on UAR selection
B5: CX features which aren't configurable at the user level, they are inherently part of the package

Sheet Full Map - New(50)
P1: Product | Q1: Client Inquiry & Insights | AG1: Investor Portal | AI1: Client Lifecycle Management | AT1: Client Servicing | BI1: Order Management | BR1: Trade Operations | CG1: Trading Tools | CK1: Managed Portfolios | CL1: Data and Reporting | CP1: Fee Management | CR1: Reference Data | CU1: User Access Management | DC1: Application Links | DF1: Application SSO
P2: Feature | Q2: Client & Account Summary | R2: Client Profile | S2: Client Profile | T2: Client Documents | U2: Account Profile | V2: Account Profile | W2: Account Holdings | X2: Account Activity | Y2: Account Profile | Z2: Account Profile | AA2: Account Documents | AB2: Account Documents | AC2: Account Documents | AD2: Account Documents | AE2: Account Documents | AF2: Client & Account Summary | AG2: Investor Portal Advisor View | AH2: Investor Portal Document Upload | AI2: Form-based Onboarding | AJ2: Paper Upload | AK2: CRS-FACTA Submissions | AL2: CRS-FACTA Submissions | AM2: Add Account | AN2: Client Profile Modifications | AO2: Client Profile Modifications | AP2: Estate Settlement | AQ2: Estate Settlement | AR2: Estate Settlement Resource | AS2: NBIN Document Resource Centre | AT2: Transfer Alerts | AU2: Transfer Statuses | AV2: Transfers Management | AW2: Transfers Management | AX2: Servicing | AY2: Servicing | AZ2: Systematic Plans | BA2: Systematic Plans | BC2: DRIP | BD2: Book Value Adjustments | BE2: Internal Transfers (Journals) | BF2: Tax Slip Events | BG2: Tax Slip Maintenance | BH2: Maturing Instruments | BI2: Core Orders Monitoring | BJ2: Core Orders: Mutual Funds | BK2: Core Orders: Equity | BL2: Core Orders: Options | BM2: Basket Orders | BN2: Basket Orders | BO2: GIC | BP2: New Issues | BQ2: Equity Borrowing | BR2: Trade Allocations | BS2: Trade Allocations | BT2: Trade Allocations | BU2: Trade Allocations | BV2: Option Expiry | BW2: Option Expiry | BX2: Options Commissions | BY2: Options Email Delivery | BZ2: Options Positions | CA2: Options Positions | CB2: View Re-Org Events | CC2: Re-Org Events | CD2: View Re-Org Events | CE2: Fund Facts | CF2: Fund Facts | CG2: NBF Research | CH2: NBF Research | CI2: Evercore Research | CJ2: Strucutred Products | CK2: Managed Portfolio Solutions | CL2: Credit Monitoring | CM2: Data Exports | CN2: Firm Reports | CO2: Firm Reports | CP2: Management Fees Upload | CQ2: Custody Fee Management | CR2: Historical FX Rates | CS2: Live Exchange Rates | CT2: Quotes | CU2: Client User Management | CV2: Global User Management | CW2: Global User Management | CX2: Global User Management | CY2: Global User Management | CZ2: Global User Management | DA2: Global User Management | DB2: Global User Management | DC2: Compass (Legacy) | DD2: Tools | DE2: NetRep | DF2: Creosus | DG2: D1G1T | DH2: Harmony
P3: Module | Q3: Accounts | R3: Client Accounts | S3: Client Profile | T3: Profile Documents | U3: Account Profile | V3: Accounts | W3: Positions | X3: Transactions | Y3: Accounts | Z3: Accounts | AA3: Statements | AB3: Tax Documents | AC3: Trade Confirmations | AD3: Securities Lending Reports | AE3: Estate Tax Slips | AF3: Activity Monitoring | AG3: My Portfolio+ IA | AH3: Bulk Document Upload | AI3: Form-Based Onboarding | AJ3: Paper Upload | AK3: CRS-FACTA Submissions | AL3: CRS-FACTA Submissions | AM3: Accounts | AN3: myRequest | AO3: TBC | AP3: Estate Settlement | AQ3: myRequest | AR3: Tools | AS3: Tools | AT3: Transfers Management (R2) | AU3: Transfers Management (R2) | AV3: Transfers Management (R2) | AW3: Transfers Management | AX3: Servicing | AY3: Servicing | AZ3: Systematic Plans (R2) | BA3: Systematic Plans | BC3: Tools | BD3: File Uploads | BE3: File Uploads | BF3: My Tax Slip Info | BG3: Tax Slip Maintenance & Notifications | BH3: Tools | BI3: Orders | BJ3: Orders | BK3: Orders | BL3: Orders | BM3: Basket Orders | BN3: File Uploads | BO3: GIC | BP3: Allocations | BQ3: Tools | BR3: MaxLite | BS3: Trade Allocations | BT3: Trade Allocations | BU3: File Uploads | BV3: Option Expiry Events | BW3: Option Expiry Events (?) | BX3: Options Positions | BY3: Options Positions | BZ3: Options Positions | CA3: Options Management | CB3: Tools | CC3: File Uploads | CD3: Re-org Management | CE3: Fund Facts | CF3: Fund Facts | CG3: NBF Research | CH3: NBF Research | CI3: Evercore Research | CJ3: Trading Tools | CK3: Managed Portfolio Solutions | CL3: CRMA | CM3: Data Export | CN3: Firm Reporting | CO3: WebPanagon | CP3: File Upload: Management Fees - Single/Batch | CQ3: Fees | CR3: Tools | CS3: Tools | CT3: Tools | CU3: MyPortfolio+ User Admin | CV3: Users | CW3: Users | CX3: Users | CY3: Users | CZ3: Users | DA3: Manage Attestations | DB3: Manage Attestations | DC3: Compass (Legacy) | DD3: Application Links - E Trans (FIS) | DE3: Application Links - NetRep | DF3: Creosus | DG3: DIGIT | DH3: Harmony
P4: Module Resource | Q4: View Firm Client Accounts | R4: View Client Accounts | S4: View Client Profile | T4: Client Profile Documents | U4: View Account Profile | V4: Account Memos | W4: Positions | X4: Transactions | Y4: Account Fees | Z4: Fund Account Display | AA4: Statements | AB4: Tax Slips | AC4: Trade Confirmations | AD4: Securities Lending Reports | AE4: Estate Tax Slips | AF4: Activity Monitoring | AG4: Access My Portfolio+ IA | AH4: Access Bulk Document Upload | AI4: Form-based Onboarding | AJ4: Paper Upload | AK4: CRS-FATCA Submissions - View | AL4: CRS-FATCA Submissions - Manage | AM4: Add Account | AN4: MyRequest Banking & Address Updates | AO4: Client Profile Modifications | AP4: Access Estates Management | AQ4: Estate Settlement | AR4: Tools | AS4: NBIN Document Resource Centre | AT4: Transfer Alerts | AU4: Transfers statuses | AV4: Transfers | AW4: Access Transfers Management | AX4: Access Servicing | AY4: Access Servicing > Approvals | AZ4: Systematic Plans | BA4: Systematic Plans | BB4: Servicing Uploads | BC4: Tools (DRIP) | BD4: File Upload: Book Value Updates | BE4: File Upload: Journal Processing | BF4: My Tax Slip Info | BG4: Tax Slip Maintenance & Notifications | BH4: Tools (Maturing Instruments) | BI4: Orders | BJ4: Manage Mutual Fund Orders | BK4: Manage Equity Orders | BL4: Manage Option Orders | BM4: Manage Basket Orders | BN4: Mutual Fund File Upload | BO4: Access GIC | BP4: Access New Issues | BQ4: Tools (Equity Borrowing) | BR4: Access Maxlite | BS4: View Trade Allocations | BT4: Manage Trade Allocations | BU4: Trade Advice File Upload | BV4: Option Expiry Events | BW4: Option Expiry Events > Uploads | BX4: Tools - Options Commissions | BY4: Tools - Options Email Delivery Log | BZ4: Tools - Options Positions | CA4: Options Management TBC | CB4: Tools (View Re-Org Events) | CC4: Re-Org Events >. Uploads | CD4: Re-Org Events TBC | CE4: Access Send Fund Facts | CF4: Access Fund Facts History | CG4: NBF Research | CH4: NBF Research | CI4: Evercore Research | CJ4: Structured Products | CK4: Application Links - Managed Portfolio Solutions (MPS) | CL4: Access CRMA | CM4: Access Data Export | CN4: Access Firm Reporting | CO4: Access WebPanagon | CP4: File Upload: Management Fees - Single/Batch | CQ4: TBC (Custody Fee Management) | CR4: Tools (Historical FX Rates) | CS4: Tools - Live Exchange Rates | CT4: Delayed Quotes | CU4: Access MyPortfolio+ User Admin | CV4: Users | CW4: SSO Users | CX4: Users > Uploads | CY4: Users > Exports | CZ4: Tools - Manage Firm Users | DA4: Firm Attestations | DB4: Attestations | DC4: Compass (Legacy) | DD4: Application Links - E Trans (FIS) | DE4: Application Links - NetRep | DF4: Creosus | DG4: DIGIT | DH4: Harmony
A5: Requirement ID | B5: Application Links | C5: Application SSO | D5: Client Inquiry & Insights | E5: Client Lifecycle Management | F5: Client Servicing | G5: Data and Reporting | H5: Fee Management | I5: Investor Portal | J5: Managed Portfolios | K5: Order Management | L5: Reference Data | M5: Trade Operations | N5: Trading Tools | O5: User Access Management | P5: Role - Absolute Match | DI5: Notes
A6: REQ-001 | B6: View | C6: View | D6: View | E6: View | F6: View | G6: View | H6: View | I6: View | J6: View | K6: View | L6: View | M6: View | N6: View | O6: Not applicable | P6: View Only Confidential Profile | Q6: V | R6: V | S6: V | T6: V | U6: V | V6: V | W6: V | X6: V | Y6: V-O | Z6: V-O | AA6: V-O | AB6: V-O | AC6: V-O | AD6: V-O | AE6: V-O | AG6: V-O | AH6: V-O | AI6: V | AJ6: V | AK6: V-O | AL6: n/a | AM6: n/a | AN6: V | AO6: V | AP6: V | AQ6: V | AR6: V | AS6: V | AV6: V | AX6: V | AY6: n/a | AZ6: n/a | BA6: V | BC6: V | BD6: V-O | BE6: V-O | BF6: V | BG6: V | BH6: V | BI6: V | BJ6: n/a | BK6: n/a | BL6: n/a | BM6: n/a | BN6: n/a | BO6: n/a | BP6: n/a | BQ6: V | BR6: V | BS6: V | BT6: n/a | BV6: V | BY6: V | BZ6: V | CA6: V | CB6: V | CD6: V | CE6: n/a | CF6: n/a | CG6: V-O | CI6: V-O | CJ6: V-O | CK6: V-O | CL6: V-O | CM6: V-O | CN6: V-O | CO6: V-O | CP6: V-O | CR6: V-O | CS6: V-O | CT6: V-O | CU6: n/a | CV6: n/a | CW6: n/a | CX6: n/a | CY6: n/a | CZ6: n/a | DA6: n/a | DB6: n/a | DC6: V-O | DD6: V-O | DE6: V-O | DF6: V-O | DG6: V-O | DH6: V-O
A7: REQ-002 | B7: View | C7: View | D7: View | E7: View | F7: View | G7: View | H7: View | I7: View | J7: View | K7: View | L7: View | M7: Manage | N7: View | O7: Not applicable | P7: **No available package | Q7: V | R7: V | S7: V | T7: V | U7: V | V7: V | W7: V | X7: V | Y7: V-O | Z7: V-O | AA7: V-O | AB7: V-O | AC7: V-O | AD7: V-O | AE7: V-O | AG7: V-O | AH7: V-O | AI7: V | AJ7: V | AK7: V-O | AL7: n/a | AM7: n/a | AN7: V | AO7: V | AP7: V | AQ7: V | AR7: V | AS7: V | AV7: V | AX7: V | AY7: n/a | AZ7: n/a | BA7: V | BC7: V | BD7: V-O | BE7: V-O | BF7: V | BG7: V | BH7: V | BI7: V | BJ7: n/a | BK7: n/a | BL7: n/a | BM7: n/a | BN7: n/a | BO7: n/a | BP7: n/a | BQ7: V | BR7: V | BS7: V | BT7: M | BV7: V | BW7: M | BX7: M | BY7: V | BZ7: V | CA7: M | CB7: V | CC7: M | CD7: V | CE7: M-O | CF7: M-O | CG7: V-O | CI7: V-O | CJ7: V-O | CK7: V-O | CL7: V-O | CM7: V-O | CN7: V-O | CO7: V-O | CP7: V-O | CR7: V-O | CS7: V-O | CT7: V-O | CU7: n/a | CV7: n/a | CW7: n/a | CX7: n/a | CY7: n/a | CZ7: n/a | DA7: n/a | DB7: n/a | DC7: V-O | DD7: V-O | DE7: V-O | DF7: V-O | DG7: V-O | DH7: V-O
A8: REQ-003 | B8: View | C8: View | D8: View | E8: View | F8: View | G8: View | H8: View | I8: View | J8: View | K8: Manage | L8: View | M8: View | N8: View | O8: Not applicable | P8: Manage Orders | Q8: V | R8: V | S8: V | T8: V | U8: V | V8: V | W8: V | X8: V | Y8: V-O | Z8: V-O | AA8: V-O | AB8: V-O | AC8: V-O | AD8: V-O | AE8: V-O | AG8: V-O | AH8: V-O | AI8: V | AJ8: V | AK8: V-O | AL8: n/a | AM8: n/a | AN8: V | AO8: V | AP8: V | AQ8: V | AR8: V | AS8: V | AV8: V | AX8: V | AY8: n/a | AZ8: n/a | BA8: V | BC8: V | BD8: V-O | BE8: V-O | BF8: V | BG8: V | BH8: V | BI8: V | BJ8: M-O | BK8: M-O | BL8: M-O | BM8: M-O | BN8: M-O | BO8: M-O | BP8: M-O | BQ8: V | BR8: V | BS8: V | BT8: n/a | BV8: V | BY8: V | BZ8: V | CA8: V | CB8: V | CD8: V | CE8: n/a | CF8: n/a | CG8: V-O | CI8: V-O | CJ8: V-O | CK8: V-O | CL8: V-O | CM8: V-O | CN8: V-O | CO8: V-O | CP8: V-O | CR8: V-O | CS8: V-O | CT8: V-O | CU8: n/a | CV8: n/a | CW8: n/a | CX8: n/a | CY8: n/a | CZ8: n/a | DA8: n/a | DB8: n/a | DC8: V-O | DD8: V-O | DE8: V-O | DF8: V-O | DG8: V-O | DH8: V-O
A9: REQ-004 | B9: View | C9: View | D9: View | E9: View | F9: View | G9: View | H9: View | I9: View | J9: View | K9: Manage | L9: View | M9: Manage | N9: View | O9: Not applicable | P9: Manage Orders and Trades | Q9: V | R9: V | S9: V | T9: V | U9: V | V9: V | W9: V | X9: V | Y9: V-O | Z9: V-O | AA9: V-O | AB9: V-O | AC9: V-O | AD9: V-O | AE9: V-O | AG9: V-O | AH9: V-O | AI9: V | AJ9: V | AK9: V-O | AL9: n/a | AM9: n/a | AN9: V | AO9: V | AP9: V | AQ9: V | AR9: V | AS9: V | AV9: V | AX9: V | AY9: n/a | AZ9: n/a | BA9: V | BC9: V | BD9: V-O | BE9: V-O | BF9: V | BG9: V | BH9: V | BI9: V | BJ9: M-O | BK9: M-O | BL9: M-O | BM9: M-O | BN9: M-O | BO9: M-O | BP9: M-O | BQ9: V | BR9: V | BS9: V | BT9: M | BV9: V | BW9: M | BX9: M | BY9: V | BZ9: V | CA9: M | CB9: V | CC9: M | CD9: V | CE9: M-O | CF9: M-O | CG9: V-O | CI9: V-O | CJ9: V-O | CK9: V-O | CL9: V-O | CM9: V-O | CN9: V-O | CO9: V-O | CP9: V-O | CR9: V-O | CS9: V-O | CT9: V-O | CU9: n/a | CV9: n/a | CW9: n/a | CX9: n/a | CY9: n/a | CZ9: n/a | DA9: n/a | DB9: n/a | DC9: V-O | DD9: V-O | DE9: V-O | DF9: V-O | DG9: V-O | DH9: V-O
A10: REQ-005 | B10: View | C10: View | D10: View | E10: View | F10: Manage | G10: View | H10: View | I10: View | J10: View | K10: View | L10: View | M10: View | N10: View | O10: Not applicable | P10: Manage Servicing Requests | Q10: V | R10: V | S10: V | T10: V | U10: V | V10: V | W10: V | X10: V | Y10: V-O | Z10: V-O | AA10: V-O | AB10: V-O | AC10: V-O | AD10: V-O | AE10: V-O | AG10: V-O | AH10: V-O | AI10: V | AJ10: V | AK10: V-O | AL10: n/a | AM10: n/a | AN10: V | AO10: V | AP10: V | AQ10: V | AR10: V | AS10: V | AV10: M | AX10: M | AY10: n/a | AZ10: M | BA10: M | BC10: V | BD10: M-O | BE10: M-O | BF10: V | BG10: V | BH10: V | BI10: V | BJ10: n/a | BK10: n/a | BL10: n/a | BM10: n/a | BN10: n/a | BO10: n/a | BP10: n/a | BQ10: V | BR10: V | BS10: V | BT10: n/a | BV10: V | BY10: V | BZ10: V | CA10: V | CB10: V | CD10: V | CE10: n/a | CF10: n/a | CG10: V-O | CI10: V-O | CJ10: V-O | CK10: V-O | CL10: V-O | CM10: V-O | CN10: V-O | CO10: V-O | CP10: V-O | CR10: V-O | CS10: V-O | CT10: V-O | CU10: n/a | CV10: n/a | CW10: n/a | CX10: n/a | CY10: n/a | CZ10: n/a | DA10: n/a | DB10: n/a | DC10: V-O | DD10: V-O | DE10: V-O | DF10: V-O | DG10: V-O | DH10: V-O
A11: REQ-006 | B11: View | C11: View | D11: View | E11: View | F11: Manage | G11: View | H11: View | I11: View | J11: View | K11: View | L11: View | M11: Manage | N11: View | O11: Not applicable | P11: Manage Servicing and Trades | Q11: V | R11: V | S11: V | T11: V | U11: V | V11: V | W11: V | X11: V | Y11: V-O | Z11: V-O | AA11: V-O | AB11: V-O | AC11: V-O | AD11: V-O | AE11: V-O | AG11: V-O | AH11: V-O | AI11: V | AJ11: V | AK11: V-O | AL11: n/a | AM11: n/a | AN11: V | AO11: V | AP11: V | AQ11: V | AR11: V | AS11: V | AV11: M | AX11: M | AY11: n/a | AZ11: M | BA11: M | BC11: V | BD11: M-O | BE11: M-O | BF11: V | BG11: V | BH11: V | BI11: V | BJ11: n/a | BK11: n/a | BL11: n/a | BM11: n/a | BN11: n/a | BO11: n/a | BP11: n/a | BQ11: V | BR11: V | BS11: V | BT11: M | BV11: V | BW11: M | BX11: M | BY11: V | BZ11: V | CA11: M | CB11: V | CC11: M | CD11: V | CE11: M-O | CF11: M-O | CG11: V-O | CI11: V-O | CJ11: V-O | CK11: V-O | CL11: V-O | CM11: V-O | CN11: V-O | CO11: V-O | CP11: V-O | CR11: V-O | CS11: V-O | CT11: V-O | CU11: n/a | CV11: n/a | CW11: n/a | CX11: n/a | CY11: n/a | CZ11: n/a | DA11: n/a | DB11: n/a | DC11: V-O | DD11: V-O | DE11: V-O | DF11: V-O | DG11: V-O | DH11: V-O
A12: REQ-007 | B12: View | C12: View | D12: View | E12: View | F12: Manage | G12: View | H12: View | I12: View | J12: View | K12: Manage | L12: View | M12: View | N12: View | O12: Not applicable | P12: Manage Servicing and Orders | Q12: V | R12: V | S12: V | T12: V | U12: V | V12: V | W12: V | X12: V | Y12: V-O | Z12: V-O | AA12: V-O | AB12: V-O | AC12: V-O | AD12: V-O | AE12: V-O | AG12: V-O | AH12: V-O | AI12: V | AJ12: V | AK12: V-O | AL12: n/a | AM12: n/a | AN12: V | AO12: V | AP12: V | AQ12: V | AR12: V | AS12: V | AV12: M | AX12: M | AY12: n/a | AZ12: M | BA12: M | BC12: V | BD12: M-O | BE12: M-O | BF12: V | BG12: V | BH12: V | BI12: V | BJ12: M-O | BK12: M-O | BL12: M-O | BM12: M-O | BN12: M-O | BO12: M-O | BP12: M-O | BQ12: V | BR12: V | BS12: V | BT12: n/a | BV12: V | BY12: V | BZ12: V | CA12: V | CB12: V | CD12: V | CE12: n/a | CF12: n/a | CG12: V-O | CI12: V-O | CJ12: V-O | CK12: V-O | CL12: V-O | CM12: V-O | CN12: V-O | CO12: V-O | CP12: V-O | CR12: V-O | CS12: V-O | CT12: V-O | CU12: n/a | CV12: n/a | CW12: n/a | CX12: n/a | CY12: n/a | CZ12: n/a | DA12: n/a | DB12: n/a | DC12: V-O | DD12: V-O | DE12: V-O | DF12: V-O | DG12: V-O | DH12: V-O
A13: REQ-008 | B13: View | C13: View | D13: View | E13: View | F13: Manage | G13: View | H13: View | I13: View | J13: View | K13: Manage | L13: View | M13: Manage | N13: View | O13: Not applicable | P13: Manage Transactions | Q13: V | R13: V | S13: V | T13: V | U13: V | V13: V | W13: V | X13: V | Y13: V-O | Z13: V-O | AA13: V-O | AB13: V-O | AC13: V-O | AD13: V-O | AE13: V-O | AG13: V-O | AH13: V-O | AI13: V | AJ13: V | AK13: V-O | AL13: n/a | AM13: n/a | AN13: V | AO13: V | AP13: V | AQ13: V | AR13: V | AS13: V | AV13: M | AX13: M | AY13: n/a | AZ13: M | BA13: M | BC13: V | BD13: M-O | BE13: M-O | BF13: V | BG13: V | BH13: V | BI13: V | BJ13: M-O | BK13: M-O | BL13: M-O | BM13: M-O | BN13: M-O | BO13: M-O | BP13: M-O | BQ13: V | BR13: V | BS13: V | BT13: M | BV13: V | BW13: M | BX13: M | BY13: V | BZ13: V | CA13: M | CB13: V | CC13: M | CD13: V | CE13: M-O | CF13: M-O | CG13: V-O | CI13: V-O | CJ13: V-O | CK13: V-O | CL13: V-O | CM13: V-O | CN13: V-O | CO13: V-O | CP13: V-O | CR13: V-O | CS13: V-O | CT13: V-O | CU13: n/a | CV13: n/a | CW13: n/a | CX13: n/a | CY13: n/a | CZ13: n/a | DA13: n/a | DB13: n/a | DC13: V-O | DD13: V-O | DE13: V-O | DF13: V-O | DG13: V-O | DH13: V-O
A14: REQ-009 | B14: View | C14: View | D14: View | E14: View | F14: Control | G14: View | H14: View | I14: View | J14: View | K14: View | L14: View | M14: View | N14: View | O14: Not applicable | P14: Admin Servicing Requests | Q14: V | R14: V | S14: V | T14: V | U14: V | V14: V | W14: V | X14: V | Y14: V-O | Z14: V-O | AA14: V-O | AB14: V-O | AC14: V-O | AD14: V-O | AE14: V-O | AG14: V-O | AH14: V-O | AI14: V | AJ14: V | AK14: V-O | AL14: n/a | AM14: n/a | AN14: V | AO14: V | AP14: V | AQ14: V | AR14: V | AS14: V | AX14: M | AY14: C | AZ14: M | BA14: M | BC14: V | BF14: V | BG14: V | BH14: V | BI14: V | BJ14: n/a | BK14: n/a | BL14: n/a | BM14: n/a | BN14: n/a | BO14: n/a | BP14: n/a | BQ14: V | BR14: V | BS14: V | BT14: n/a | BV14: V | BY14: V | BZ14: V | CA14: V | CB14: V | CD14: V | CE14: n/a | CF14: n/a | CG14: V-O | CI14: V-O | CJ14: V-O | CK14: V-O | CL14: V-O | CM14: V-O | CN14: V-O | CO14: V-O | CP14: V-O | CR14: V-O | CS14: V-O | CT14: V-O | CU14: n/a | CV14: n/a | CW14: n/a | CX14: n/a | CY14: n/a | CZ14: n/a | DA14: n/a | DB14: n/a | DC14: V-O | DD14: V-O | DE14: V-O | DF14: V-O | DG14: V-O | DH14: V-O
A15: REQ-010 | B15: View | C15: View | D15: View | E15: View | F15: Control | G15: View | H15: View | I15: View | J15: View | K15: View | L15: View | M15: Manage | N15: View | O15: Not applicable | P15: **No available package | Q15: V | R15: V | S15: V | T15: V | U15: V | V15: V | W15: V | X15: V | Y15: V-O | Z15: V-O | AA15: V-O | AB15: V-O | AC15: V-O | AD15: V-O | AE15: V-O | AG15: V-O | AH15: V-O | AI15: V | AJ15: V | AK15: V-O | AL15: n/a | AM15: n/a | AN15: V | AO15: V | AP15: V | AQ15: V | AR15: V | AS15: V | AX15: M | AY15: C | AZ15: M | BA15: M | BC15: V | BF15: V | BG15: V | BH15: V | BI15: V | BJ15: n/a | BK15: n/a | BL15: n/a | BM15: n/a | BN15: n/a | BO15: n/a | BP15: n/a | BQ15: V | BR15: V | BS15: V | BT15: M | BV15: V | BW15: M | BX15: M | BY15: V | BZ15: V | CA15: M | CB15: V | CC15: M | CD15: V | CE15: M-O | CF15: M-O | CG15: V-O | CI15: V-O | CJ15: V-O | CK15: V-O | CL15: V-O | CM15: V-O | CN15: V-O | CO15: V-O | CP15: V-O | CR15: V-O | CS15: V-O | CT15: V-O | CU15: n/a | CV15: n/a | CW15: n/a | CX15: n/a | CY15: n/a | CZ15: n/a | DA15: n/a | DB15: n/a | DC15: V-O | DD15: V-O | DE15: V-O | DF15: V-O | DG15: V-O | DH15: V-O | DI15: Admin Servicing Requests is a close match, but Trade Allocations is View and we need Manage in this combination
A16: REQ-011 | B16: View | C16: View | D16: View | E16: View | F16: Control | G16: View | H16: View | I16: View | J16: View | K16: Manage | L16: View | M16: View | N16: View | O16: Not applicable | P16: **No available package | Q16: V | R16: V | S16: V | T16: V | U16: V | V16: V | W16: V | X16: V | Y16: V-O | Z16: V-O | AA16: V-O | AB16: V-O | AC16: V-O | AD16: V-O | AE16: V-O | AG16: V-O | AH16: V-O | AI16: V | AJ16: V | AK16: V-O | AL16: n/a | AM16: n/a | AN16: V | AO16: V | AP16: V | AQ16: V | AR16: V | AS16: V | AX16: M | AY16: C | AZ16: M | BA16: M | BC16: V | BF16: V | BG16: V | BH16: V | BI16: V | BJ16: M-O | BK16: M-O | BL16: M-O | BM16: M-O | BN16: M-O | BO16: M-O | BP16: M-O | BQ16: V | BR16: V | BS16: V | BT16: n/a | BV16: V | BY16: V | BZ16: V | CA16: V | CB16: V | CD16: V | CE16: n/a | CF16: n/a | CG16: V-O | CI16: V-O | CJ16: V-O | CK16: V-O | CL16: V-O | CM16: V-O | CN16: V-O | CO16: V-O | CP16: V-O | CR16: V-O | CS16: V-O | CT16: V-O | CU16: n/a | CV16: n/a | CW16: n/a | CX16: n/a | CY16: n/a | CZ16: n/a | DA16: n/a | DB16: n/a | DC16: V-O | DD16: V-O | DE16: V-O | DF16: V-O | DG16: V-O | DH16: V-O | DI16: All packages with Control for Servicing Approvals and Manage for Order Management have Control for Paper Upload
A17: REQ-012 | B17: View | C17: View | D17: View | E17: View | F17: Control | G17: View | H17: View | I17: View | J17: View | K17: Manage | L17: View | M17: Manage | N17: View | O17: Not applicable | P17: **No available package | Q17: V | R17: V | S17: V | T17: V | U17: V | V17: V | W17: V | X17: V | Y17: V-O | Z17: V-O | AA17: V-O | AB17: V-O | AC17: V-O | AD17: V-O | AE17: V-O | AG17: V-O | AH17: V-O | AI17: V | AJ17: V | AK17: V-O | AL17: n/a | AM17: n/a | AN17: V | AO17: V | AP17: V | AQ17: V | AR17: V | AS17: V | AX17: M | AY17: C | AZ17: M | BA17: M | BC17: V | BF17: V | BG17: V | BH17: V | BI17: V | BJ17: M-O | BK17: M-O | BL17: M-O | BM17: M-O | BN17: M-O | BO17: M-O | BP17: M-O | BQ17: V | BR17: V | BS17: V | BT17: M | BV17: V | BW17: M | BX17: M | BY17: V | BZ17: V | CA17: M | CB17: V | CC17: M | CD17: V | CE17: M-O | CF17: M-O | CG17: V-O | CI17: V-O | CJ17: V-O | CK17: V-O | CL17: V-O | CM17: V-O | CN17: V-O | CO17: V-O | CP17: V-O | CR17: V-O | CS17: V-O | CT17: V-O | CU17: n/a | CV17: n/a | CW17: n/a | CX17: n/a | CY17: n/a | CZ17: n/a | DA17: n/a | DB17: n/a | DC17: V-O | DD17: V-O | DE17: V-O | DF17: V-O | DG17: V-O | DH17: V-O | DI17: All packages with Control for Servicing Approvals and Manage for Order Management have Control for Paper Upload
A18: REQ-013 | B18: View | C18: View | D18: View | E18: Manage | F18: View | G18: View | H18: View | I18: View | J18: View | K18: View | L18: View | M18: View | N18: View | O18: Not applicable | P18: Manage Accounts And Profiles | Q18: V | R18: V | S18: V | T18: V | U18: V | V18: V | W18: V | X18: V | Y18: V-O | Z18: V-O | AA18: V-O | AB18: V-O | AC18: V-O | AD18: V-O | AE18: V-O | AG18: V-O | AH18: V-O | AI18: M | AJ18: M | AK18: V-O | AL18: M-O | AM18: M | AN18: M | AO18: M | AP18: M | AQ18: M | AR18: V | AS18: V | AV18: V | AX18: V | AY18: n/a | AZ18: n/a | BA18: V | BC18: V | BD18: V-O | BE18: V-O | BF18: V | BG18: V | BH18: V | BI18: V | BJ18: n/a | BK18: n/a | BL18: n/a | BM18: n/a | BN18: n/a | BO18: n/a | BP18: n/a | BQ18: V | BR18: V | BS18: V | BT18: n/a | BV18: V | BY18: V | BZ18: V | CA18: V | CB18: V | CD18: V | CE18: n/a | CF18: n/a | CG18: V-O | CI18: V-O | CJ18: V-O | CK18: V-O | CL18: V-O | CM18: V-O | CN18: V-O | CO18: V-O | CP18: V-O | CR18: V-O | CS18: V-O | CT18: V-O | CU18: n/a | CV18: n/a | CW18: n/a | CX18: n/a | CY18: n/a | CZ18: n/a | DA18: n/a | DB18: n/a | DC18: V-O | DD18: V-O | DE18: V-O | DF18: V-O | DG18: V-O | DH18: V-O
A19: REQ-014 | B19: View | C19: View | D19: View | E19: Manage | F19: View | G19: View | H19: View | I19: View | J19: View | K19: View | L19: View | M19: Manage | N19: View | O19: Not applicable | P19: **No available package | Q19: V | R19: V | S19: V | T19: V | U19: V | V19: V | W19: V | X19: V | Y19: V-O | Z19: V-O | AA19: V-O | AB19: V-O | AC19: V-O | AD19: V-O | AE19: V-O | AG19: V-O | AH19: V-O | AI19: M | AJ19: M | AK19: V-O | AL19: M-O | AM19: M | AN19: M | AO19: M | AP19: M | AQ19: M | AR19: V | AS19: V | AV19: V | AX19: V | AY19: n/a | AZ19: n/a | BA19: V | BC19: V | BD19: V-O | BE19: V-O | BF19: V | BG19: V | BH19: V | BI19: V | BJ19: n/a | BK19: n/a | BL19: n/a | BM19: n/a | BN19: n/a | BO19: n/a | BP19: n/a | BQ19: V | BR19: V | BS19: V | BT19: M | BV19: V | BW19: M | BX19: M | BY19: V | BZ19: V | CA19: M | CB19: V | CC19: M | CD19: V | CE19: M-O | CF19: M-O | CG19: V-O | CI19: V-O | CJ19: V-O | CK19: V-O | CL19: V-O | CM19: V-O | CN19: V-O | CO19: V-O | CP19: V-O | CR19: V-O | CS19: V-O | CT19: V-O | CU19: n/a | CV19: n/a | CW19: n/a | CX19: n/a | CY19: n/a | CZ19: n/a | DA19: n/a | DB19: n/a | DC19: V-O | DD19: V-O | DE19: V-O | DF19: V-O | DG19: V-O | DH19: V-O | DI19: Manage Accounts, Profiles, and Servicing is a close match but Servicing is Manage and we need View in this combination
A20: REQ-015 | B20: View | C20: View | D20: View | E20: Manage | F20: View | G20: View | H20: View | I20: View | J20: View | K20: Manage | L20: View | M20: View | N20: View | O20: Not applicable | P20: **No available package | Q20: V | R20: V | S20: V | T20: V | U20: V | V20: V | W20: V | X20: V | Y20: V-O | Z20: V-O | AA20: V-O | AB20: V-O | AC20: V-O | AD20: V-O | AE20: V-O | AG20: V-O | AH20: V-O | AI20: M | AJ20: M | AK20: V-O | AL20: M-O | AM20: M | AN20: M | AO20: M | AP20: M | AQ20: M | AR20: V | AS20: V | AV20: V | AX20: V | AY20: n/a | AZ20: n/a | BA20: V | BC20: V | BD20: V-O | BE20: V-O | BF20: V | BG20: V | BH20: V | BI20: V | BJ20: M-O | BK20: M-O | BL20: M-O | BM20: M-O | BN20: M-O | BO20: M-O | BP20: M-O | BQ20: V | BR20: V | BS20: V | BT20: n/a | BV20: V | BY20: V | BZ20: V | CA20: V | CB20: V | CD20: V | CE20: n/a | CF20: n/a | CG20: V-O | CI20: V-O | CJ20: V-O | CK20: V-O | CL20: V-O | CM20: V-O | CN20: V-O | CO20: V-O | CP20: V-O | CR20: V-O | CS20: V-O | CT20: V-O | CU20: n/a | CV20: n/a | CW20: n/a | CX20: n/a | CY20: n/a | CZ20: n/a | DA20: n/a | DB20: n/a | DC20: V-O | DD20: V-O | DE20: V-O | DF20: V-O | DG20: V-O | DH20: V-O | DI20: Manage All but not Trades is a close match but Servicing is Manage and we need View in this combination
A21: REQ-016 | B21: View | C21: View | D21: View | E21: Manage | F21: View | G21: View | H21: View | I21: View | J21: View | K21: Manage | L21: View | M21: Manage | N21: View | O21: Not applicable | P21: **No available package | Q21: V | R21: V | S21: V | T21: V | U21: V | V21: V | W21: V | X21: V | Y21: V-O | Z21: V-O | AA21: V-O | AB21: V-O | AC21: V-O | AD21: V-O | AE21: V-O | AG21: V-O | AH21: V-O | AI21: M | AJ21: M | AK21: V-O | AL21: M-O | AM21: M | AN21: M | AO21: M | AP21: M | AQ21: M | AR21: V | AS21: V | AV21: V | AX21: V | AY21: n/a | AZ21: n/a | BA21: V | BC21: V | BD21: V-O | BE21: V-O | BF21: V | BG21: V | BH21: V | BI21: V | BJ21: M-O | BK21: M-O | BL21: M-O | BM21: M-O | BN21: M-O | BO21: M-O | BP21: M-O | BQ21: V | BR21: V | BS21: V | BT21: M | BV21: V | BW21: M | BX21: M | BY21: V | BZ21: V | CA21: M | CB21: V | CC21: M | CD21: V | CE21: M-O | CF21: M-O | CG21: V-O | CI21: V-O | CJ21: V-O | CK21: V-O | CL21: V-O | CM21: V-O | CN21: V-O | CO21: V-O | CP21: V-O | CR21: V-O | CS21: V-O | CT21: V-O | CU21: n/a | CV21: n/a | CW21: n/a | CX21: n/a | CY21: n/a | CZ21: n/a | DA21: n/a | DB21: n/a | DC21: V-O | DD21: V-O | DE21: V-O | DF21: V-O | DG21: V-O | DH21: V-O | DI21: Manage All is a close match but Servicing is Manage and we need View in this combination
A22: REQ-017 | B22: View | C22: View | D22: View | E22: Manage | F22: Manage | G22: View | H22: View | I22: View | J22: View | K22: View | L22: View | M22: View | N22: View | O22: Not applicable | P22: **No available package | Q22: V | R22: V | S22: V | T22: V | U22: V | V22: V | W22: V | X22: V | Y22: V-O | Z22: V-O | AA22: V-O | AB22: V-O | AC22: V-O | AD22: V-O | AE22: V-O | AG22: V-O | AH22: V-O | AI22: M | AJ22: M | AK22: V-O | AL22: M-O | AM22: M | AN22: M | AO22: M | AP22: M | AQ22: M | AR22: V | AS22: V | AV22: M | AX22: M | AY22: n/a | AZ22: M | BA22: M | BC22: V | BD22: M-O | BE22: M-O | BF22: V | BG22: V | BH22: V | BI22: V | BJ22: n/a | BK22: n/a | BL22: n/a | BM22: n/a | BN22: n/a | BO22: n/a | BP22: n/a | BQ22: V | BR22: V | BS22: V | BT22: n/a | BV22: V | BY22: V | BZ22: V | CA22: V | CB22: V | CD22: V | CE22: n/a | CF22: n/a | CG22: V-O | CI22: V-O | CJ22: V-O | CK22: V-O | CL22: V-O | CM22: V-O | CN22: V-O | CO22: V-O | CP22: V-O | CR22: V-O | CS22: V-O | CT22: V-O | CU22: n/a | CV22: n/a | CW22: n/a | CX22: n/a | CY22: n/a | CZ22: n/a | DA22: n/a | DB22: n/a | DC22: V-O | DD22: V-O | DE22: V-O | DF22: V-O | DG22: V-O | DH22: V-O | DI22: Manage Accounts, Profiles, and Servicing is a close match but Trade Allocations is Manage and we need View in this combination
A23: REQ-018 | B23: View | C23: View | D23: View | E23: Manage | F23: Manage | G23: View | H23: View | I23: View | J23: View | K23: View | L23: View | M23: Manage | N23: View | O23: Not applicable | P23: Manage Accounts, Profiles, Servicing and Trade | Q23: V | R23: V | S23: V | T23: V | U23: V | V23: V | W23: V | X23: V | Y23: V-O | Z23: V-O | AA23: V-O | AB23: V-O | AC23: V-O | AD23: V-O | AE23: V-O | AG23: V-O | AH23: V-O | AI23: M | AJ23: M | AK23: V-O | AL23: M-O | AM23: M | AN23: M | AO23: M | AP23: M | AQ23: M | AR23: V | AS23: V | AV23: M | AX23: M | AY23: n/a | AZ23: M | BA23: M | BC23: V | BD23: M-O | BE23: M-O | BF23: V | BG23: V | BH23: V | BI23: V | BJ23: n/a | BK23: n/a | BL23: n/a | BM23: n/a | BN23: n/a | BO23: n/a | BP23: n/a | BQ23: V | BR23: V | BS23: V | BT23: M | BV23: V | BW23: M | BX23: M | BY23: V | BZ23: V | CA23: M | CB23: V | CC23: M | CD23: V | CE23: M-O | CF23: M-O | CG23: V-O | CI23: V-O | CJ23: V-O | CK23: V-O | CL23: V-O | CM23: V-O | CN23: V-O | CO23: V-O | CP23: V-O | CR23: V-O | CS23: V-O | CT23: V-O | CU23: n/a | CV23: n/a | CW23: n/a | CX23: n/a | CY23: n/a | CZ23: n/a | DA23: n/a | DB23: n/a | DC23: V-O | DD23: V-O | DE23: V-O | DF23: V-O | DG23: V-O | DH23: V-O
A24: REQ-019 | B24: View | C24: View | D24: View | E24: Manage | F24: Manage | G24: View | H24: View | I24: View | J24: View | K24: Manage | L24: View | M24: View | N24: View | O24: Not applicable | P24: Manage All but not Trades | Q24: V | R24: V | S24: V | T24: V | U24: V | V24: V | W24: V | X24: V | Y24: V-O | Z24: V-O | AA24: V-O | AB24: V-O | AC24: V-O | AD24: V-O | AE24: V-O | AG24: V-O | AH24: V-O | AI24: M | AJ24: M | AK24: V-O | AL24: M-O | AM24: M | AN24: M | AO24: M | AP24: M | AQ24: M | AR24: V | AS24: V | AV24: M | AX24: M | AY24: n/a | AZ24: M | BA24: M | BC24: V | BD24: M-O | BE24: M-O | BF24: V | BG24: V | BH24: V | BI24: V | BJ24: M-O | BK24: M-O | BL24: M-O | BM24: M-O | BN24: M-O | BO24: M-O | BP24: M-O | BQ24: V | BR24: V | BS24: V | BT24: n/a | BV24: V | BY24: V | BZ24: V | CA24: V | CB24: V | CD24: V | CE24: n/a | CF24: n/a | CG24: V-O | CI24: V-O | CJ24: V-O | CK24: V-O | CL24: V-O | CM24: V-O | CN24: V-O | CO24: V-O | CP24: V-O | CR24: V-O | CS24: V-O | CT24: V-O | CU24: n/a | CV24: n/a | CW24: n/a | CX24: n/a | CY24: n/a | CZ24: n/a | DA24: n/a | DB24: n/a | DC24: V-O | DD24: V-O | DE24: V-O | DF24: V-O | DG24: V-O | DH24: V-O
A25: REQ-020 | B25: View | C25: View | D25: View | E25: Manage | F25: Manage | G25: View | H25: View | I25: View | J25: View | K25: Manage | L25: View | M25: Manage | N25: View | O25: Not applicable | P25: Manage All | Q25: V | R25: V | S25: V | T25: V | U25: V | V25: V | W25: V | X25: V | Y25: V-O | Z25: V-O | AA25: V-O | AB25: V-O | AC25: V-O | AD25: V-O | AE25: V-O | AG25: V-O | AH25: V-O | AI25: M | AJ25: M | AK25: V-O | AL25: M-O | AM25: M | AN25: M | AO25: M | AP25: M | AQ25: M | AR25: V | AS25: V | AV25: M | AX25: M | AY25: n/a | AZ25: M | BA25: M | BC25: V | BD25: M-O | BE25: M-O | BF25: V | BG25: V | BH25: V | BI25: V | BJ25: M-O | BK25: M-O | BL25: M-O | BM25: M-O | BN25: M-O | BO25: M-O | BP25: M-O | BQ25: V | BR25: V | BS25: V | BT25: M | BV25: V | BW25: M | BX25: M | BY25: V | BZ25: V | CA25: M | CB25: V | CC25: M | CD25: V | CE25: M-O | CF25: M-O | CG25: V-O | CI25: V-O | CJ25: V-O | CK25: V-O | CL25: V-O | CM25: V-O | CN25: V-O | CO25: V-O | CP25: V-O | CR25: V-O | CS25: V-O | CT25: V-O | CU25: n/a | CV25: n/a | CW25: n/a | CX25: n/a | CY25: n/a | CZ25: n/a | DA25: n/a | DB25: n/a | DC25: V-O | DD25: V-O | DE25: V-O | DF25: V-O | DG25: V-O | DH25: V-O
A26: REQ-021 | B26: View | C26: View | D26: View | E26: Manage | F26: Control | G26: View | H26: View | I26: View | J26: View | K26: View | L26: View | M26: View | N26: View | O26: Not applicable | P26: **No available package | Q26: V | R26: V | S26: V | T26: V | U26: V | V26: V | W26: V | X26: V | Y26: V-O | Z26: V-O | AA26: V-O | AB26: V-O | AC26: V-O | AD26: V-O | AE26: V-O | AG26: V-O | AH26: V-O | AI26: M | AJ26: M | AK26: V-O | AL26: M-O | AM26: M | AN26: M | AO26: M | AP26: M | AQ26: M | AR26: V | AS26: V | AX26: M | AY26: C | AZ26: M | BA26: M | BC26: V | BF26: V | BG26: V | BH26: V | BI26: V | BJ26: n/a | BK26: n/a | BL26: n/a | BM26: n/a | BN26: n/a | BO26: n/a | BP26: n/a | BQ26: V | BR26: V | BS26: V | BT26: n/a | BV26: V | BY26: V | BZ26: V | CA26: V | CB26: V | CD26: V | CE26: n/a | CF26: n/a | CG26: V-O | CI26: V-O | CJ26: V-O | CK26: V-O | CL26: V-O | CM26: V-O | CN26: V-O | CO26: V-O | CP26: V-O | CR26: V-O | CS26: V-O | CT26: V-O | CU26: n/a | CV26: n/a | CW26: n/a | CX26: n/a | CY26: n/a | CZ26: n/a | DA26: n/a | DB26: n/a | DC26: V-O | DD26: V-O | DE26: V-O | DF26: V-O | DG26: V-O | DH26: V-O | DI26: Admin Accounts, Profiles And Servicing is a close match but Paper Upload is Control and we need Manage
A27: REQ-022 | B27: View | C27: View | D27: View | E27: Manage | F27: Control | G27: View | H27: View | I27: View | J27: View | K27: View | L27: View | M27: Manage | N27: View | O27: Not applicable | P27: **No available package | Q27: V | R27: V | S27: V | T27: V | U27: V | V27: V | W27: V | X27: V | Y27: V-O | Z27: V-O | AA27: V-O | AB27: V-O | AC27: V-O | AD27: V-O | AE27: V-O | AG27: V-O | AH27: V-O | AI27: M | AJ27: M | AK27: V-O | AL27: M-O | AM27: M | AN27: M | AO27: M | AP27: M | AQ27: M | AR27: V | AS27: V | AX27: M | AY27: C | AZ27: M | BA27: M | BC27: V | BF27: V | BG27: V | BH27: V | BI27: V | BJ27: n/a | BK27: n/a | BL27: n/a | BM27: n/a | BN27: n/a | BO27: n/a | BP27: n/a | BQ27: V | BR27: V | BS27: V | BT27: M | BV27: V | BW27: M | BX27: M | BY27: V | BZ27: V | CA27: M | CB27: V | CC27: M | CD27: V | CE27: M-O | CF27: M-O | CG27: V-O | CI27: V-O | CJ27: V-O | CK27: V-O | CL27: V-O | CM27: V-O | CN27: V-O | CO27: V-O | CP27: V-O | CR27: V-O | CS27: V-O | CT27: V-O | CU27: n/a | CV27: n/a | CW27: n/a | CX27: n/a | CY27: n/a | CZ27: n/a | DA27: n/a | DB27: n/a | DC27: V-O | DD27: V-O | DE27: V-O | DF27: V-O | DG27: V-O | DH27: V-O | DI27: All packages with Control for Servicing Approvals and N/A for Order Management don't satisfy controls for Paper Upload and Trade Allocations
A28: REQ-023 | B28: View | C28: View | D28: View | E28: Manage | F28: Control | G28: View | H28: View | I28: View | J28: View | K28: Manage | L28: View | M28: View | N28: View | O28: Not applicable | P28: Admin All but not Trades | Q28: V | R28: V | S28: V | T28: V | U28: V | V28: V | W28: V | X28: V | Y28: V-O | Z28: V-O | AA28: V-O | AB28: V-O | AC28: V-O | AD28: V-O | AE28: V-O | AG28: V-O | AH28: V-O | AI28: M | AJ28: M | AK28: V-O | AL28: M-O | AM28: M | AN28: M | AO28: M | AP28: M | AQ28: M | AR28: V | AS28: V | AX28: M | AY28: C | AZ28: M | BA28: M | BC28: V | BF28: V | BG28: V | BH28: V | BI28: V | BJ28: M-O | BK28: M-O | BL28: M-O | BM28: M-O | BN28: M-O | BO28: M-O | BP28: M-O | BQ28: V | BR28: V | BS28: V | BT28: n/a | BV28: V | BY28: V | BZ28: V | CA28: V | CB28: V | CD28: V | CE28: n/a | CF28: n/a | CG28: V-O | CI28: V-O | CJ28: V-O | CK28: V-O | CL28: V-O | CM28: V-O | CN28: V-O | CO28: V-O | CP28: V-O | CR28: V-O | CS28: V-O | CT28: V-O | CU28: n/a | CV28: n/a | CW28: n/a | CX28: n/a | CY28: n/a | CZ28: n/a | DA28: n/a | DB28: n/a | DC28: V-O | DD28: V-O | DE28: V-O | DF28: V-O | DG28: V-O | DH28: V-O | DI28: validate - paper upload is Manage, not an absolute match
A29: REQ-024 | B29: View | C29: View | D29: View | E29: Manage | F29: Control | G29: View | H29: View | I29: View | J29: View | K29: Manage | L29: View | M29: Manage | N29: View | O29: Not applicable | P29: **No available package | Q29: V | R29: V | S29: V | T29: V | U29: V | V29: V | W29: V | X29: V | Y29: V-O | Z29: V-O | AA29: V-O | AB29: V-O | AC29: V-O | AD29: V-O | AE29: V-O | AG29: V-O | AH29: V-O | AI29: M | AJ29: M | AK29: V-O | AL29: M-O | AM29: M | AN29: M | AO29: M | AP29: M | AQ29: M | AR29: V | AS29: V | AX29: M | AY29: C | AZ29: M | BA29: M | BC29: V | BF29: V | BG29: V | BH29: V | BI29: V | BJ29: M-O | BK29: M-O | BL29: M-O | BM29: M-O | BN29: M-O | BO29: M-O | BP29: M-O | BQ29: V | BR29: V | BS29: V | BT29: M | BV29: V | BW29: M | BX29: M | BY29: V | BZ29: V | CA29: M | CB29: V | CC29: M | CD29: V | CE29: M-O | CF29: M-O | CG29: V-O | CI29: V-O | CJ29: V-O | CK29: V-O | CL29: V-O | CM29: V-O | CN29: V-O | CO29: V-O | CP29: V-O | CR29: V-O | CS29: V-O | CT29: V-O | CU29: n/a | CV29: n/a | CW29: n/a | CX29: n/a | CY29: n/a | CZ29: n/a | DA29: n/a | DB29: n/a | DC29: V-O | DD29: V-O | DE29: V-O | DF29: V-O | DG29: V-O | DH29: V-O | DI29: All packages with Control for Servicing Approvals and Manage for Order Management have Control for Paper Upload
A30: REQ-025 | B30: View | C30: View | D30: View | E30: Control | F30: View | G30: View | H30: View | I30: View | J30: View | K30: View | L30: View | M30: View | N30: View | O30: Not applicable | P30: Admin Accounts And Profiles | Q30: V | R30: V | S30: V | T30: V | U30: V | V30: V | W30: V | X30: V | Y30: V-O | Z30: V-O | AA30: V-O | AB30: V-O | AC30: V-O | AD30: V-O | AE30: V-O | AG30: V-O | AH30: V-O | AI30: C-O | AJ30: C-O | AK30: V-O | AL30: M-O | AP30: C | AR30: V | AS30: V | AV30: V | AX30: V | AY30: n/a | AZ30: n/a | BA30: V | BC30: V | BD30: V-O | BE30: V-O | BF30: V | BG30: V | BH30: V | BI30: V | BJ30: n/a | BK30: n/a | BL30: n/a | BM30: n/a | BN30: n/a | BO30: n/a | BP30: n/a | BQ30: V | BR30: V | BS30: V | BT30: n/a | BV30: V | BY30: V | BZ30: V | CA30: V | CB30: V | CD30: V | CE30: n/a | CF30: n/a | CG30: V-O | CI30: V-O | CJ30: V-O | CK30: V-O | CL30: V-O | CM30: V-O | CN30: V-O | CO30: V-O | CP30: V-O | CR30: V-O | CS30: V-O | CT30: V-O | CU30: n/a | CV30: n/a | CW30: n/a | CX30: n/a | CY30: n/a | CZ30: n/a | DA30: n/a | DB30: n/a | DC30: V-O | DD30: V-O | DE30: V-O | DF30: V-O | DG30: V-O | DH30: V-O
A31: REQ-026 | B31: View | C31: View | D31: View | E31: Control | F31: View | G31: View | H31: View | I31: View | J31: View | K31: View | L31: View | M31: Manage | N31: View | O31: Not applicable | P31: **No available package | Q31: V | R31: V | S31: V | T31: V | U31: V | V31: V | W31: V | X31: V | Y31: V-O | Z31: V-O | AA31: V-O | AB31: V-O | AC31: V-O | AD31: V-O | AE31: V-O | AG31: V-O | AH31: V-O | AI31: C-O | AJ31: C-O | AK31: V-O | AL31: M-O | AP31: C | AR31: V | AS31: V | AV31: V | AX31: V | AY31: n/a | AZ31: n/a | BA31: V | BC31: V | BD31: V-O | BE31: V-O | BF31: V | BG31: V | BH31: V | BI31: V | BJ31: n/a | BK31: n/a | BL31: n/a | BM31: n/a | BN31: n/a | BO31: n/a | BP31: n/a | BQ31: V | BR31: V | BS31: V | BT31: M | BV31: V | BW31: M | BX31: M | BY31: V | BZ31: V | CA31: M | CB31: V | CC31: M | CD31: V | CE31: M-O | CF31: M-O | CG31: V-O | CI31: V-O | CJ31: V-O | CK31: V-O | CL31: V-O | CM31: V-O | CN31: V-O | CO31: V-O | CP31: V-O | CR31: V-O | CS31: V-O | CT31: V-O | CU31: n/a | CV31: n/a | CW31: n/a | CX31: n/a | CY31: n/a | CZ31: n/a | DA31: n/a | DB31: n/a | DC31: V-O | DD31: V-O | DE31: V-O | DF31: V-O | DG31: V-O | DH31: V-O | DI31: Admin Accounts And Profiles is a close match but Trade Allocations is View and we need Manage in this combination
A32: REQ-027 | B32: View | C32: View | D32: View | E32: Control | F32: View | G32: View | H32: View | I32: View | J32: View | K32: Manage | L32: View | M32: View | N32: View | O32: Not applicable | P32: **No available package | Q32: V | R32: V | S32: V | T32: V | U32: V | V32: V | W32: V | X32: V | Y32: V-O | Z32: V-O | AA32: V-O | AB32: V-O | AC32: V-O | AD32: V-O | AE32: V-O | AG32: V-O | AH32: V-O | AI32: C-O | AJ32: C-O | AK32: V-O | AL32: M-O | AP32: C | AR32: V | AS32: V | AV32: V | AX32: V | AY32: n/a | AZ32: n/a | BA32: V | BC32: V | BD32: V-O | BE32: V-O | BF32: V | BG32: V | BH32: V | BI32: V | BJ32: M-O | BK32: M-O | BL32: M-O | BM32: M-O | BN32: M-O | BO32: M-O | BP32: M-O | BQ32: V | BR32: V | BS32: V | BT32: n/a | BV32: V | BY32: V | BZ32: V | CA32: V | CB32: V | CD32: V | CE32: n/a | CF32: n/a | CG32: V-O | CI32: V-O | CJ32: V-O | CK32: V-O | CL32: V-O | CM32: V-O | CN32: V-O | CO32: V-O | CP32: V-O | CR32: V-O | CS32: V-O | CT32: V-O | CU32: n/a | CV32: n/a | CW32: n/a | CX32: n/a | CY32: n/a | CZ32: n/a | DA32: n/a | DB32: n/a | DC32: V-O | DD32: V-O | DE32: V-O | DF32: V-O | DG32: V-O | DH32: V-O | DI32: All packages with Control for Paper Upload and Manage for Order Management have Control for Servicing Approvals but its not available in this combination
A33: REQ-028 | B33: View | C33: View | D33: View | E33: Control | F33: View | G33: View | H33: View | I33: View | J33: View | K33: Manage | L33: View | M33: Manage | N33: View | O33: Not applicable | P33: **No available package | Q33: V | R33: V | S33: V | T33: V | U33: V | V33: V | W33: V | X33: V | Y33: V-O | Z33: V-O | AA33: V-O | AB33: V-O | AC33: V-O | AD33: V-O | AE33: V-O | AG33: V-O | AH33: V-O | AI33: C-O | AJ33: C-O | AK33: V-O | AL33: M-O | AP33: C | AR33: V | AS33: V | AV33: V | AX33: V | AY33: n/a | AZ33: n/a | BA33: V | BC33: V | BD33: V-O | BE33: V-O | BF33: V | BG33: V | BH33: V | BI33: V | BJ33: M-O | BK33: M-O | BL33: M-O | BM33: M-O | BN33: M-O | BO33: M-O | BP33: M-O | BQ33: V | BR33: V | BS33: V | BT33: M | BV33: V | BW33: M | BX33: M | BY33: V | BZ33: V | CA33: M | CB33: V | CC33: M | CD33: V | CE33: M-O | CF33: M-O | CG33: V-O | CI33: V-O | CJ33: V-O | CK33: V-O | CL33: V-O | CM33: V-O | CN33: V-O | CO33: V-O | CP33: V-O | CR33: V-O | CS33: V-O | CT33: V-O | CU33: n/a | CV33: n/a | CW33: n/a | CX33: n/a | CY33: n/a | CZ33: n/a | DA33: n/a | DB33: n/a | DC33: V-O | DD33: V-O | DE33: V-O | DF33: V-O | DG33: V-O | DH33: V-O | DI33: All packages with Control for Paper Upload and Manage for Order Management have Control for Servicing Approvals but its not available in this combination
A34: REQ-029 | B34: View | C34: View | D34: View | E34: Control | F34: Manage | G34: View | H34: View | I34: View | J34: View | K34: View | L34: View | M34: View | N34: View | O34: Not applicable | P34: **No available package | Q34: V | R34: V | S34: V | T34: V | U34: V | V34: V | W34: V | X34: V | Y34: V-O | Z34: V-O | AA34: V-O | AB34: V-O | AC34: V-O | AD34: V-O | AE34: V-O | AG34: V-O | AH34: V-O | AI34: C-O | AJ34: C-O | AK34: V-O | AL34: M-O | AP34: C | AR34: V | AS34: V | AV34: M | AX34: M | AY34: n/a | AZ34: M | BA34: M | BC34: V | BD34: M-O | BE34: M-O | BF34: V | BG34: V | BH34: V | BI34: V | BJ34: n/a | BK34: n/a | BL34: n/a | BM34: n/a | BN34: n/a | BO34: n/a | BP34: n/a | BQ34: V | BR34: V | BS34: V | BT34: n/a | BV34: V | BY34: V | BZ34: V | CA34: V | CB34: V | CD34: V | CE34: n/a | CF34: n/a | CG34: V-O | CI34: V-O | CJ34: V-O | CK34: V-O | CL34: V-O | CM34: V-O | CN34: V-O | CO34: V-O | CP34: V-O | CR34: V-O | CS34: V-O | CT34: V-O | CU34: n/a | CV34: n/a | CW34: n/a | CX34: n/a | CY34: n/a | CZ34: n/a | DA34: n/a | DB34: n/a | DC34: V-O | DD34: V-O | DE34: V-O | DF34: V-O | DG34: V-O | DH34: V-O | DI34: Admin Accounts, Profiles And Servicing is a close match but Servicing Approvals is Control and its not available in this combination
A35: REQ-030 | B35: View | C35: View | D35: View | E35: Control | F35: Manage | G35: View | H35: View | I35: View | J35: View | K35: View | L35: View | M35: Manage | N35: View | O35: Not applicable | P35: **No available package | Q35: V | R35: V | S35: V | T35: V | U35: V | V35: V | W35: V | X35: V | Y35: V-O | Z35: V-O | AA35: V-O | AB35: V-O | AC35: V-O | AD35: V-O | AE35: V-O | AG35: V-O | AH35: V-O | AI35: C-O | AJ35: C-O | AK35: V-O | AL35: M-O | AP35: C | AR35: V | AS35: V | AV35: M | AX35: M | AY35: n/a | AZ35: M | BA35: M | BC35: V | BD35: M-O | BE35: M-O | BF35: V | BG35: V | BH35: V | BI35: V | BJ35: n/a | BK35: n/a | BL35: n/a | BM35: n/a | BN35: n/a | BO35: n/a | BP35: n/a | BQ35: V | BR35: V | BS35: V | BT35: M | BV35: V | BW35: M | BX35: M | BY35: V | BZ35: V | CA35: M | CB35: V | CC35: M | CD35: V | CE35: M-O | CF35: M-O | CG35: V-O | CI35: V-O | CJ35: V-O | CK35: V-O | CL35: V-O | CM35: V-O | CN35: V-O | CO35: V-O | CP35: V-O | CR35: V-O | CS35: V-O | CT35: V-O | CU35: n/a | CV35: n/a | CW35: n/a | CX35: n/a | CY35: n/a | CZ35: n/a | DA35: n/a | DB35: n/a | DC35: V-O | DD35: V-O | DE35: V-O | DF35: V-O | DG35: V-O | DH35: V-O | DI35: Admin Accounts, Profiles And Servicing is a close match but Servicing Approvals and Trade Allocation controls don't satisfy the combination
A36: REQ-031 | B36: View | C36: View | D36: View | E36: Control | F36: Manage | G36: View | H36: View | I36: View | J36: View | K36: Manage | L36: View | M36: View | N36: View | O36: Not applicable | P36: **No available package | Q36: V | R36: V | S36: V | T36: V | U36: V | V36: V | W36: V | X36: V | Y36: V-O | Z36: V-O | AA36: V-O | AB36: V-O | AC36: V-O | AD36: V-O | AE36: V-O | AG36: V-O | AH36: V-O | AI36: C-O | AJ36: C-O | AK36: V-O | AL36: M-O | AP36: C | AR36: V | AS36: V | AV36: M | AX36: M | AY36: n/a | AZ36: M | BA36: M | BC36: V | BD36: M-O | BE36: M-O | BF36: V | BG36: V | BH36: V | BI36: V | BJ36: M-O | BK36: M-O | BL36: M-O | BM36: M-O | BN36: M-O | BO36: M-O | BP36: M-O | BQ36: V | BR36: V | BS36: V | BT36: n/a | BV36: V | BY36: V | BZ36: V | CA36: V | CB36: V | CD36: V | CE36: n/a | CF36: n/a | CG36: V-O | CI36: V-O | CJ36: V-O | CK36: V-O | CL36: V-O | CM36: V-O | CN36: V-O | CO36: V-O | CP36: V-O | CR36: V-O | CS36: V-O | CT36: V-O | CU36: n/a | CV36: n/a | CW36: n/a | CX36: n/a | CY36: n/a | CZ36: n/a | DA36: n/a | DB36: n/a | DC36: V-O | DD36: V-O | DE36: V-O | DF36: V-O | DG36: V-O | DH36: V-O | DI36: All packages with Control for Paper Upload and Manage for Order Management have Control for Servicing Approvals but its not available in this combination
A37: REQ-032 | B37: View | C37: View | D37: View | E37: Control | F37: Manage | G37: View | H37: View | I37: View | J37: View | K37: Manage | L37: View | M37: Manage | N37: View | O37: Not applicable | P37: **No available package | Q37: V | R37: V | S37: V | T37: V | U37: V | V37: V | W37: V | X37: V | Y37: V-O | Z37: V-O | AA37: V-O | AB37: V-O | AC37: V-O | AD37: V-O | AE37: V-O | AG37: V-O | AH37: V-O | AI37: C-O | AJ37: C-O | AK37: V-O | AL37: M-O | AP37: C | AR37: V | AS37: V | AV37: M | AX37: M | AY37: n/a | AZ37: M | BA37: M | BC37: V | BD37: M-O | BE37: M-O | BF37: V | BG37: V | BH37: V | BI37: V | BJ37: M-O | BK37: M-O | BL37: M-O | BM37: M-O | BN37: M-O | BO37: M-O | BP37: M-O | BQ37: V | BR37: V | BS37: V | BT37: M | BV37: V | BW37: M | BX37: M | BY37: V | BZ37: V | CA37: M | CB37: V | CC37: M | CD37: V | CE37: M-O | CF37: M-O | CG37: V-O | CI37: V-O | CJ37: V-O | CK37: V-O | CL37: V-O | CM37: V-O | CN37: V-O | CO37: V-O | CP37: V-O | CR37: V-O | CS37: V-O | CT37: V-O | CU37: n/a | CV37: n/a | CW37: n/a | CX37: n/a | CY37: n/a | CZ37: n/a | DA37: n/a | DB37: n/a | DC37: V-O | DD37: V-O | DE37: V-O | DF37: V-O | DG37: V-O | DH37: V-O | DI37: All packages with Control for Paper Upload and Manage for Order Management have Control for Servicing Approvals but its not available in this combination
A38: REQ-033 | B38: View | C38: View | D38: View | E38: Control | F38: Control | G38: View | H38: View | I38: View | J38: View | K38: View | L38: View | M38: View | N38: View | O38: Not applicable | P38: Admin Accounts, Profiles And Servicing | Q38: V | R38: V | S38: V | T38: V | U38: V | V38: V | W38: V | X38: V | Y38: V-O | Z38: V-O | AA38: V-O | AB38: V-O | AC38: V-O | AD38: V-O | AE38: V-O | AG38: V-O | AH38: V-O | AI38: C-O | AJ38: C-O | AK38: V-O | AL38: M-O | AP38: C | AR38: V | AS38: V | AX38: M | AY38: C | AZ38: M | BA38: M | BC38: V | BF38: V | BG38: V | BH38: V | BI38: V | BJ38: n/a | BK38: n/a | BL38: n/a | BM38: n/a | BN38: n/a | BO38: n/a | BP38: n/a | BQ38: V | BR38: V | BS38: V | BT38: n/a | BV38: V | BY38: V | BZ38: V | CA38: V | CB38: V | CD38: V | CE38: n/a | CF38: n/a | CG38: V-O | CI38: V-O | CJ38: V-O | CK38: V-O | CL38: V-O | CM38: V-O | CN38: V-O | CO38: V-O | CP38: V-O | CR38: V-O | CS38: V-O | CT38: V-O | CU38: n/a | CV38: n/a | CW38: n/a | CX38: n/a | CY38: n/a | CZ38: n/a | DA38: n/a | DB38: n/a | DC38: V-O | DD38: V-O | DE38: V-O | DF38: V-O | DG38: V-O | DH38: V-O
A39: REQ-034 | B39: View | C39: View | D39: View | E39: Control | F39: Control | G39: View | H39: View | I39: View | J39: View | K39: View | L39: View | M39: Manage | N39: View | O39: Not applicable | P39: **No available package | Q39: V | R39: V | S39: V | T39: V | U39: V | V39: V | W39: V | X39: V | Y39: V-O | Z39: V-O | AA39: V-O | AB39: V-O | AC39: V-O | AD39: V-O | AE39: V-O | AG39: V-O | AH39: V-O | AI39: C-O | AJ39: C-O | AK39: V-O | AL39: M-O | AP39: C | AR39: V | AS39: V | AX39: M | AY39: C | AZ39: M | BA39: M | BC39: V | BF39: V | BG39: V | BH39: V | BI39: V | BJ39: n/a | BK39: n/a | BL39: n/a | BM39: n/a | BN39: n/a | BO39: n/a | BP39: n/a | BQ39: V | BR39: V | BS39: V | BT39: M | BV39: V | BW39: M | BX39: M | BY39: V | BZ39: V | CA39: M | CB39: V | CC39: M | CD39: V | CE39: M-O | CF39: M-O | CG39: V-O | CI39: V-O | CJ39: V-O | CK39: V-O | CL39: V-O | CM39: V-O | CN39: V-O | CO39: V-O | CP39: V-O | CR39: V-O | CS39: V-O | CT39: V-O | CU39: n/a | CV39: n/a | CW39: n/a | CX39: n/a | CY39: n/a | CZ39: n/a | DA39: n/a | DB39: n/a | DC39: V-O | DD39: V-O | DE39: V-O | DF39: V-O | DG39: V-O | DH39: V-O | DI39: Admin Accounts, Profiles And Servicing is a close match but Trade Allocations is View and we need Manage in this combination
A40: REQ-035 | B40: View | C40: View | D40: View | E40: Control | F40: Control | G40: View | H40: View | I40: View | J40: View | K40: Manage | L40: View | M40: View | N40: View | O40: Not applicable | P40: Admin All but not Trades | Q40: V | R40: V | S40: V | T40: V | U40: V | V40: V | W40: V | X40: V | Y40: V-O | Z40: V-O | AA40: V-O | AB40: V-O | AC40: V-O | AD40: V-O | AE40: V-O | AG40: V-O | AH40: V-O | AI40: C-O | AJ40: C-O | AK40: V-O | AL40: M-O | AP40: C | AR40: V | AS40: V | AX40: M | AY40: C | AZ40: M | BA40: M | BC40: V | BF40: V | BG40: V | BH40: V | BI40: V | BJ40: M-O | BK40: M-O | BL40: M-O | BM40: M-O | BN40: M-O | BO40: M-O | BP40: M-O | BQ40: V | BR40: V | BS40: V | BT40: n/a | BV40: V | BY40: V | BZ40: V | CA40: V | CB40: V | CD40: V | CE40: n/a | CF40: n/a | CG40: V-O | CI40: V-O | CJ40: V-O | CK40: V-O | CL40: V-O | CM40: V-O | CN40: V-O | CO40: V-O | CP40: V-O | CR40: V-O | CS40: V-O | CT40: V-O | CU40: n/a | CV40: n/a | CW40: n/a | CX40: n/a | CY40: n/a | CZ40: n/a | DA40: n/a | DB40: n/a | DC40: V-O | DD40: V-O | DE40: V-O | DF40: V-O | DG40: V-O | DH40: V-O | DI40: review
A41: REQ-036 | B41: View | C41: View | D41: View | E41: Control | F41: Control | G41: View | H41: View | I41: View | J41: View | K41: Manage | L41: View | M41: Manage | N41: View | O41: Not applicable | P41: **No available package | Q41: V | R41: V | S41: V | T41: V | U41: V | V41: V | W41: V | X41: V | Y41: V-O | Z41: V-O | AA41: V-O | AB41: V-O | AC41: V-O | AD41: V-O | AE41: V-O | AG41: V-O | AH41: V-O | AI41: C-O | AJ41: C-O | AK41: V-O | AL41: M-O | AP41: C | AR41: V | AS41: V | AX41: M | AY41: C | AZ41: M | BA41: M | BC41: V | BF41: V | BG41: V | BH41: V | BI41: V | BJ41: M-O | BK41: M-O | BL41: M-O | BM41: M-O | BN41: M-O | BO41: M-O | BP41: M-O | BQ41: V | BR41: V | BS41: V | BT41: M | BV41: V | BW41: M | BX41: M | BY41: V | BZ41: V | CA41: M | CB41: V | CC41: M | CD41: V | CE41: M-O | CF41: M-O | CG41: V-O | CI41: V-O | CJ41: V-O | CK41: V-O | CL41: V-O | CM41: V-O | CN41: V-O | CO41: V-O | CP41: V-O | CR41: V-O | CS41: V-O | CT41: V-O | CU41: n/a | CV41: n/a | CW41: n/a | CX41: n/a | CY41: n/a | CZ41: n/a | DA41: n/a | DB41: n/a | DC41: V-O | DD41: V-O | DE41: V-O | DF41: V-O | DG41: V-O | DH41: V-O | DI41: Admin All is a close match but it has Control for Trade Allocations: Approvals which is not available in this combination
A42: REQ-037 | B42: View | C42: View | D42: View | E42: Process | F42: View | G42: View | H42: View | I42: View | J42: View | K42: View | L42: View | M42: View | N42: View | O42: Not applicable | P42: Process Accounts And Profiles | Q42: V | R42: V | S42: V | T42: V | U42: V | V42: V | W42: V | X42: V | Y42: V-O | Z42: V-O | AA42: V-O | AB42: V-O | AC42: V-O | AD42: V-O | AE42: V-O | AG42: V-O | AH42: V-O | AI42: P | AJ42: P | AK42: V-O | AL42: n/a | AP42: n/a | AR42: V | AS42: V | AV42: V | AX42: V | AY42: n/a | AZ42: n/a | BA42: V | BC42: V | BD42: V-O | BE42: V-O | BF42: V | BG42: V | BH42: V | BI42: V | BJ42: n/a | BK42: n/a | BL42: n/a | BM42: n/a | BN42: n/a | BO42: n/a | BP42: n/a | BQ42: V | BR42: V | BS42: V | BT42: n/a | BV42: V | BY42: V | BZ42: V | CA42: V | CB42: V | CD42: V | CE42: n/a | CF42: n/a | CG42: V-O | CI42: V-O | CJ42: V-O | CK42: V-O | CL42: V-O | CM42: V-O | CN42: V-O | CO42: V-O | CP42: V-O | CR42: V-O | CS42: V-O | CT42: V-O | CU42: n/a | CV42: n/a | CW42: n/a | CX42: n/a | CY42: n/a | CZ42: n/a | DA42: n/a | DB42: n/a | DC42: V-O | DD42: V-O | DE42: V-O | DF42: V-O | DG42: V-O | DH42: V-O
A43: REQ-038 | B43: View | C43: View | D43: View | E43: Process | F43: View | G43: View | H43: View | I43: View | J43: View | K43: View | L43: View | M43: Manage | N43: View | O43: Not applicable | P43: **No available package | Q43: V | R43: V | S43: V | T43: V | U43: V | V43: V | W43: V | X43: V | Y43: V-O | Z43: V-O | AA43: V-O | AB43: V-O | AC43: V-O | AD43: V-O | AE43: V-O | AG43: V-O | AH43: V-O | AI43: P | AJ43: P | AK43: V-O | AL43: n/a | AP43: n/a | AR43: V | AS43: V | AV43: V | AX43: V | AY43: n/a | AZ43: n/a | BA43: V | BC43: V | BD43: V-O | BE43: V-O | BF43: V | BG43: V | BH43: V | BI43: V | BJ43: n/a | BK43: n/a | BL43: n/a | BM43: n/a | BN43: n/a | BO43: n/a | BP43: n/a | BQ43: V | BR43: V | BS43: V | BT43: M | BV43: V | BW43: M | BX43: M | BY43: V | BZ43: V | CA43: M | CB43: V | CC43: M | CD43: V | CE43: M-O | CF43: M-O | CG43: V-O | CI43: V-O | CJ43: V-O | CK43: V-O | CL43: V-O | CM43: V-O | CN43: V-O | CO43: V-O | CP43: V-O | CR43: V-O | CS43: V-O | CT43: V-O | CU43: n/a | CV43: n/a | CW43: n/a | CX43: n/a | CY43: n/a | CZ43: n/a | DA43: n/a | DB43: n/a | DC43: V-O | DD43: V-O | DE43: V-O | DF43: V-O | DG43: V-O | DH43: V-O | DI43: Process Accounts And Profiles is the only package with Process for Paper Upload and it does not satisfy this combination for CRS-FATCA and Trade Allocations
A44: REQ-039 | B44: View | C44: View | D44: View | E44: Process | F44: View | G44: View | H44: View | I44: View | J44: View | K44: Manage | L44: View | M44: View | N44: View | O44: Not applicable | P44: **No available package | Q44: V | R44: V | S44: V | T44: V | U44: V | V44: V | W44: V | X44: V | Y44: V-O | Z44: V-O | AA44: V-O | AB44: V-O | AC44: V-O | AD44: V-O | AE44: V-O | AG44: V-O | AH44: V-O | AI44: P | AJ44: P | AK44: V-O | AL44: n/a | AP44: n/a | AR44: V | AS44: V | AV44: V | AX44: V | AY44: n/a | AZ44: n/a | BA44: V | BC44: V | BD44: V-O | BE44: V-O | BF44: V | BG44: V | BH44: V | BI44: V | BJ44: M-O | BK44: M-O | BL44: M-O | BM44: M-O | BN44: M-O | BO44: M-O | BP44: M-O | BQ44: V | BR44: V | BS44: V | BT44: n/a | BV44: V | BY44: V | BZ44: V | CA44: V | CB44: V | CD44: V | CE44: n/a | CF44: n/a | CG44: V-O | CI44: V-O | CJ44: V-O | CK44: V-O | CL44: V-O | CM44: V-O | CN44: V-O | CO44: V-O | CP44: V-O | CR44: V-O | CS44: V-O | CT44: V-O | CU44: n/a | CV44: n/a | CW44: n/a | CX44: n/a | CY44: n/a | CZ44: n/a | DA44: n/a | DB44: n/a | DC44: V-O | DD44: V-O | DE44: V-O | DF44: V-O | DG44: V-O | DH44: V-O | DI44: Process Accounts And Profiles is the only package with Process for Paper Upload and it does not satisfy this combination for CRS-FATCA and Order Management
A45: REQ-040 | B45: View | C45: View | D45: View | E45: Process | F45: View | G45: View | H45: View | I45: View | J45: View | K45: Manage | L45: View | M45: Manage | N45: View | O45: Not applicable | P45: **No available package | Q45: V | R45: V | S45: V | T45: V | U45: V | V45: V | W45: V | X45: V | Y45: V-O | Z45: V-O | AA45: V-O | AB45: V-O | AC45: V-O | AD45: V-O | AE45: V-O | AG45: V-O | AH45: V-O | AI45: P | AJ45: P | AK45: V-O | AL45: n/a | AP45: n/a | AR45: V | AS45: V | AV45: V | AX45: V | AY45: n/a | AZ45: n/a | BA45: V | BC45: V | BD45: V-O | BE45: V-O | BF45: V | BG45: V | BH45: V | BI45: V | BJ45: M-O | BK45: M-O | BL45: M-O | BM45: M-O | BN45: M-O | BO45: M-O | BP45: M-O | BQ45: V | BR45: V | BS45: V | BT45: M | BV45: V | BW45: M | BX45: M | BY45: V | BZ45: V | CA45: M | CB45: V | CC45: M | CD45: V | CE45: M-O | CF45: M-O | CG45: V-O | CI45: V-O | CJ45: V-O | CK45: V-O | CL45: V-O | CM45: V-O | CN45: V-O | CO45: V-O | CP45: V-O | CR45: V-O | CS45: V-O | CT45: V-O | CU45: n/a | CV45: n/a | CW45: n/a | CX45: n/a | CY45: n/a | CZ45: n/a | DA45: n/a | DB45: n/a | DC45: V-O | DD45: V-O | DE45: V-O | DF45: V-O | DG45: V-O | DH45: V-O | DI45: Process Accounts And Profiles is the only package with Process for Paper Upload and it does not satisfy this combination for CRS-FATCA, Order Management and Trade Allocations
A46: REQ-041 | B46: View | C46: View | D46: View | E46: Process | F46: Manage | G46: View | H46: View | I46: View | J46: View | K46: View | L46: View | M46: View | N46: View | O46: Not applicable | P46: **No available package | Q46: V | R46: V | S46: V | T46: V | U46: V | V46: V | W46: V | X46: V | Y46: V-O | Z46: V-O | AA46: V-O | AB46: V-O | AC46: V-O | AD46: V-O | AE46: V-O | AG46: V-O | AH46: V-O | AI46: P | AJ46: P | AK46: V-O | AL46: n/a | AP46: n/a | AR46: V | AS46: V | AV46: M | AX46: M | AY46: n/a | AZ46: M | BA46: M | BC46: V | BD46: M-O | BE46: M-O | BF46: V | BG46: V | BH46: V | BI46: V | BJ46: n/a | BK46: n/a | BL46: n/a | BM46: n/a | BN46: n/a | BO46: n/a | BP46: n/a | BQ46: V | BR46: V | BS46: V | BT46: n/a | BV46: V | BY46: V | BZ46: V | CA46: V | CB46: V | CD46: V | CE46: n/a | CF46: n/a | CG46: V-O | CI46: V-O | CJ46: V-O | CK46: V-O | CL46: V-O | CM46: V-O | CN46: V-O | CO46: V-O | CP46: V-O | CR46: V-O | CS46: V-O | CT46: V-O | CU46: n/a | CV46: n/a | CW46: n/a | CX46: n/a | CY46: n/a | CZ46: n/a | DA46: n/a | DB46: n/a | DC46: V-O | DD46: V-O | DE46: V-O | DF46: V-O | DG46: V-O | DH46: V-O | DI46: Process Accounts And Profiles is the only package with Process for Paper Upload and it does not satisfy this combination for CRS-FATCA and Servicing
A47: REQ-042 | B47: View | C47: View | D47: View | E47: Process | F47: Manage | G47: View | H47: View | I47: View | J47: View | K47: View | L47: View | M47: Manage | N47: View | O47: Not applicable | P47: **No available package | Q47: V | R47: V | S47: V | T47: V | U47: V | V47: V | W47: V | X47: V | Y47: V-O | Z47: V-O | AA47: V-O | AB47: V-O | AC47: V-O | AD47: V-O | AE47: V-O | AG47: V-O | AH47: V-O | AI47: P | AJ47: P | AK47: V-O | AL47: n/a | AP47: n/a | AR47: V | AS47: V | AV47: M | AX47: M | AY47: n/a | AZ47: M | BA47: M | BC47: V | BD47: M-O | BE47: M-O | BF47: V | BG47: V | BH47: V | BI47: V | BJ47: n/a | BK47: n/a | BL47: n/a | BM47: n/a | BN47: n/a | BO47: n/a | BP47: n/a | BQ47: V | BR47: V | BS47: V | BT47: M | BV47: V | BW47: M | BX47: M | BY47: V | BZ47: V | CA47: M | CB47: V | CC47: M | CD47: V | CE47: M-O | CF47: M-O | CG47: V-O | CI47: V-O | CJ47: V-O | CK47: V-O | CL47: V-O | CM47: V-O | CN47: V-O | CO47: V-O | CP47: V-O | CR47: V-O | CS47: V-O | CT47: V-O | CU47: n/a | CV47: n/a | CW47: n/a | CX47: n/a | CY47: n/a | CZ47: n/a | DA47: n/a | DB47: n/a | DC47: V-O | DD47: V-O | DE47: V-O | DF47: V-O | DG47: V-O | DH47: V-O | DI47: Process Accounts And Profiles is the only package with Process for Paper Upload and it does not satisfy this combination for CRS-FATCA, Servicing and Trade Allocations
A48: REQ-043 | B48: View | C48: View | D48: View | E48: Process | F48: Manage | G48: View | H48: View | I48: View | J48: View | K48: Manage | L48: View | M48: View | N48: View | O48: Not applicable | P48: **No available package | Q48: V | R48: V | S48: V | T48: V | U48: V | V48: V | W48: V | X48: V | Y48: V-O | Z48: V-O | AA48: V-O | AB48: V-O | AC48: V-O | AD48: V-O | AE48: V-O | AG48: V-O | AH48: V-O | AI48: P | AJ48: P | AK48: V-O | AL48: n/a | AP48: n/a | AR48: V | AS48: V | AV48: M | AX48: M | AY48: n/a | AZ48: M | BA48: M | BC48: V | BD48: M-O | BE48: M-O | BF48: V | BG48: V | BH48: V | BI48: V | BJ48: M-O | BK48: M-O | BL48: M-O | BM48: M-O | BN48: M-O | BO48: M-O | BP48: M-O | BQ48: V | BR48: V | BS48: V | BT48: n/a | BV48: V | BY48: V | BZ48: V | CA48: V | CB48: V | CD48: V | CE48: n/a | CF48: n/a | CG48: V-O | CI48: V-O | CJ48: V-O | CK48: V-O | CL48: V-O | CM48: V-O | CN48: V-O | CO48: V-O | CP48: V-O | CR48: V-O | CS48: V-O | CT48: V-O | CU48: n/a | CV48: n/a | CW48: n/a | CX48: n/a | CY48: n/a | CZ48: n/a | DA48: n/a | DB48: n/a | DC48: V-O | DD48: V-O | DE48: V-O | DF48: V-O | DG48: V-O | DH48: V-O | DI48: Process Accounts And Profiles is the only package with Process for Paper Upload and it does not satisfy this combination for CRS-FATCA, Servicing and Order Management
A49: REQ-044 | B49: View | C49: View | D49: View | E49: Process | F49: Manage | G49: View | H49: View | I49: View | J49: View | K49: Manage | L49: View | M49: Manage | N49: View | O49: Not applicable | P49: **No available package | Q49: V | R49: V | S49: V | T49: V | U49: V | V49: V | W49: V | X49: V | Y49: V-O | Z49: V-O | AA49: V-O | AB49: V-O | AC49: V-O | AD49: V-O | AE49: V-O | AG49: V-O | AH49: V-O | AI49: P | AJ49: P | AK49: V-O | AL49: n/a | AP49: n/a | AR49: V | AS49: V | AV49: M | AX49: M | AY49: n/a | AZ49: M | BA49: M | BC49: V | BD49: M-O | BE49: M-O | BF49: V | BG49: V | BH49: V | BI49: V | BJ49: M-O | BK49: M-O | BL49: M-O | BM49: M-O | BN49: M-O | BO49: M-O | BP49: M-O | BQ49: V | BR49: V | BS49: V | BT49: M | BV49: V | BW49: M | BX49: M | BY49: V | BZ49: V | CA49: M | CB49: V | CC49: M | CD49: V | CE49: M-O | CF49: M-O | CG49: V-O | CI49: V-O | CJ49: V-O | CK49: V-O | CL49: V-O | CM49: V-O | CN49: V-O | CO49: V-O | CP49: V-O | CR49: V-O | CS49: V-O | CT49: V-O | CU49: n/a | CV49: n/a | CW49: n/a | CX49: n/a | CY49: n/a | CZ49: n/a | DA49: n/a | DB49: n/a | DC49: V-O | DD49: V-O | DE49: V-O | DF49: V-O | DG49: V-O | DH49: V-O | DI49: Process Accounts And Profiles is the only package with Process for Paper Upload and it does not satisfy this combination for CRS-FATCA, Servicing, Order Management and Trade Allocations
A50: REQ-045 | B50: View | C50: View | D50: View | E50: Process | F50: Control | G50: View | H50: View | I50: View | J50: View | K50: View | L50: View | M50: View | N50: View | O50: Not applicable | P50: **No available package | Q50: V | R50: V | S50: V | T50: V | U50: V | V50: V | W50: V | X50: V | Y50: V-O | Z50: V-O | AA50: V-O | AB50: V-O | AC50: V-O | AD50: V-O | AE50: V-O | AG50: V-O | AH50: V-O | AI50: P | AJ50: P | AK50: V-O | AL50: n/a | AP50: n/a | AR50: V | AS50: V | AX50: M | AY50: C | AZ50: M | BA50: M | BC50: V | BF50: V | BG50: V | BH50: V | BI50: V | BJ50: n/a | BK50: n/a | BL50: n/a | BM50: n/a | BN50: n/a | BO50: n/a | BP50: n/a | BQ50: V | BR50: V | BS50: V | BT50: n/a | BV50: V | BY50: V | BZ50: V | CA50: V | CB50: V | CD50: V | CE50: n/a | CF50: n/a | CG50: V-O | CI50: V-O | CJ50: V-O | CK50: V-O | CL50: V-O | CM50: V-O | CN50: V-O | CO50: V-O | CP50: V-O | CR50: V-O | CS50: V-O | CT50: V-O | CU50: n/a | CV50: n/a | CW50: n/a | CX50: n/a | CY50: n/a | CZ50: n/a | DA50: n/a | DB50: n/a | DC50: V-O | DD50: V-O | DE50: V-O | DF50: V-O | DG50: V-O | DH50: V-O | DI50: Process Accounts And Profiles is the only package with Process for Paper Upload and it does not satisfy this combination for CRS-FATCA, Servicing and Servicing Approvals
A51: REQ-046 | B51: View | C51: View | D51: View | E51: Process | F51: Control | G51: View | H51: View | I51: View | J51: View | K51: View | L51: View | M51: Manage | N51: View | O51: Not applicable | P51: **No available package | Q51: V | R51: V | S51: V | T51: V | U51: V | V51: V | W51: V | X51: V | Y51: V-O | Z51: V-O | AA51: V-O | AB51: V-O | AC51: V-O | AD51: V-O | AE51: V-O | AG51: V-O | AH51: V-O | AI51: P | AJ51: P | AK51: V-O | AL51: n/a | AP51: n/a | AR51: V | AS51: V | AX51: M | AY51: C | AZ51: M | BA51: M | BC51: V | BF51: V | BG51: V | BH51: V | BI51: V | BJ51: n/a | BK51: n/a | BL51: n/a | BM51: n/a | BN51: n/a | BO51: n/a | BP51: n/a | BQ51: V | BR51: V | BS51: V | BT51: M | BV51: V | BW51: M | BX51: M | BY51: V | BZ51: V | CA51: M | CB51: V | CC51: M | CD51: V | CE51: M-O | CF51: M-O | CG51: V-O | CI51: V-O | CJ51: V-O | CK51: V-O | CL51: V-O | CM51: V-O | CN51: V-O | CO51: V-O | CP51: V-O | CR51: V-O | CS51: V-O | CT51: V-O | CU51: n/a | CV51: n/a | CW51: n/a | CX51: n/a | CY51: n/a | CZ51: n/a | DA51: n/a | DB51: n/a | DC51: V-O | DD51: V-O | DE51: V-O | DF51: V-O | DG51: V-O | DH51: V-O | DI51: Process Accounts And Profiles is the only package with Process for Paper Upload and it does not satisfy this combination for CRS-FATCA, Servicing, Servicing Approvals and Trade Allocations
A52: REQ-047 | B52: View | C52: View | D52: View | E52: Process | F52: Control | G52: View | H52: View | I52: View | J52: View | K52: Manage | L52: View | M52: View | N52: View | O52: Not applicable | P52: **No available package | Q52: V | R52: V | S52: V | T52: V | U52: V | V52: V | W52: V | X52: V | Y52: V-O | Z52: V-O | AA52: V-O | AB52: V-O | AC52: V-O | AD52: V-O | AE52: V-O | AG52: V-O | AH52: V-O | AI52: P | AJ52: P | AK52: V-O | AL52: n/a | AP52: n/a | AR52: V | AS52: V | AX52: M | AY52: C | AZ52: M | BA52: M | BC52: V | BF52: V | BG52: V | BH52: V | BI52: V | BJ52: M-O | BK52: M-O | BL52: M-O | BM52: M-O | BN52: M-O | BO52: M-O | BP52: M-O | BQ52: V | BR52: V | BS52: V | BT52: n/a | BV52: V | BY52: V | BZ52: V | CA52: V | CB52: V | CD52: V | CE52: n/a | CF52: n/a | CG52: V-O | CI52: V-O | CJ52: V-O | CK52: V-O | CL52: V-O | CM52: V-O | CN52: V-O | CO52: V-O | CP52: V-O | CR52: V-O | CS52: V-O | CT52: V-O | CU52: n/a | CV52: n/a | CW52: n/a | CX52: n/a | CY52: n/a | CZ52: n/a | DA52: n/a | DB52: n/a | DC52: V-O | DD52: V-O | DE52: V-O | DF52: V-O | DG52: V-O | DH52: V-O | DI52: Process Accounts And Profiles is the only package with Process for Paper Upload and it does not satisfy this combination for CRS-FATCA, Servicing, Servicing Approvals and Order Management
A53: REQ-048 | B53: View | C53: View | D53: View | E53: Process | F53: Control | G53: View | H53: View | I53: View | J53: View | K53: Manage | L53: View | M53: Manage | N53: View | O53: Not applicable | P53: **No available package | Q53: V | R53: V | S53: V | T53: V | U53: V | V53: V | W53: V | X53: V | Y53: V-O | Z53: V-O | AA53: V-O | AB53: V-O | AC53: V-O | AD53: V-O | AE53: V-O | AG53: V-O | AH53: V-O | AI53: P | AJ53: P | AK53: V-O | AL53: n/a | AP53: n/a | AR53: V | AS53: V | AX53: M | AY53: C | AZ53: M | BA53: M | BC53: V | BF53: V | BG53: V | BH53: V | BI53: V | BJ53: M-O | BK53: M-O | BL53: M-O | BM53: M-O | BN53: M-O | BO53: M-O | BP53: M-O | BQ53: V | BR53: V | BS53: V | BT53: M | BV53: V | BW53: M | BX53: M | BY53: V | BZ53: V | CA53: M | CB53: V | CC53: M | CD53: V | CE53: M-O | CF53: M-O | CG53: V-O | CI53: V-O | CJ53: V-O | CK53: V-O | CL53: V-O | CM53: V-O | CN53: V-O | CO53: V-O | CP53: V-O | CR53: V-O | CS53: V-O | CT53: V-O | CU53: n/a | CV53: n/a | CW53: n/a | CX53: n/a | CY53: n/a | CZ53: n/a | DA53: n/a | DB53: n/a | DC53: V-O | DD53: V-O | DE53: V-O | DF53: V-O | DG53: V-O | DH53: V-O | DI53: Process Accounts And Profiles is the only package with Process for Paper Upload and it does not satisfy this combination for CRS-FATCA, Servicing, Servicing Approvals, Order Management and Trade Allocations
A54: REQ-049 | B54: Not applicable | C54: Not applicable | D54: Not applicable | E54: Not applicable | F54: Not applicable | G54: Not applicable | H54: Not applicable | I54: Not applicable | J54: Not applicable | K54: Not applicable | L54: Not applicable | M54: Not applicable | N54: Not applicable | O54: Manage | P54: Client User Management (new Package; name TBD) | Q54: n/a | R54: n/a | S54: n/a | T54: n/a | U54: n/a | V54: n/a | W54: n/a | X54: n/a | Y54: n/a | Z54: n/a | AA54: n/a | AB54: n/a | AC54: n/a | AD54: n/a | AE54: n/a | AF54: n/a | AG54: n/a | AH54: n/a | AI54: n/a | AJ54: n/a | AK54: n/a | AL54: n/a | AM54: n/a | AN54: n/a | AO54: n/a | AP54: n/a | AQ54: n/a | AR54: n/a | AS54: n/a | AT54: n/a | AU54: n/a | AV54: n/a | AW54: n/a | AX54: n/a | AY54: n/a | AZ54: n/a | BA54: n/a | BC54: n/a | BD54: n/a | BE54: n/a | BF54: n/a | BG54: n/a | BH54: n/a | BI54: n/a | BJ54: n/a | BK54: n/a | BL54: n/a | BM54: n/a | BN54: n/a | BO54: n/a | BP54: n/a | BQ54: n/a | BR54: n/a | BS54: n/a | BT54: n/a | BU54: n/a | BV54: n/a | BW54: n/a | BX54: n/a | BY54: n/a | BZ54: n/a | CA54: n/a | CB54: n/a | CC54: n/a | CD54: n/a | CE54: n/a | CF54: n/a | CG54: n/a | CH54: n/a | CI54: n/a | CJ54: n/a | CK54: n/a | CL54: n/a | CM54: n/a | CN54: n/a | CO54: n/a | CP54: n/a | CQ54: n/a | CR54: n/a | CS54: n/a | CT54: n/a | CU54: M-O | CV54: M | CW54: M | CX54: M | CY54: M | CZ54: M | DA54: M | DB54: M | DC54: n/a | DD54: n/a | DE54: n/a | DF54: n/a | DG54: n/a | DH54: n/a

Sheet work-1
B1: Packages
A2: Display Name | B2: Admin Accounts And Profiles | C2: Admin Accounts, Profiles And Servicing | D2: Admin All | E2: Admin Orders | F2: Admin Servicing Requests | G2: Config Platform | H2: Manage Accounts And Profiles | I2: Manage All | J2: Manage Accounts, Profiles, Servicing and Trades | K2: Manage Firms And Users | L2: Manage Orders | M2: Manage Servicing and Trades | N2: Manage Servicing Requests | O2: Process Accounts And Profiles | P2: Process Trades | Q2: View Only Confidential Profile | R2: Manage Servicing and Orders | S2: Manage Transactions | T2: Manage Orders and Trades | U2: Global Admin | V2: Manage Users | W2: Manage Users Passwords | X2: Manage All but not Trades | Y2: Admin All but not Trades | Z2: Admin Orders and Trades | AA2: Full Admin Trades | AB2: Client User Management (new Package; name TBD)
A3: System Name | B3: AdminAccountsAndProfiles_V1.17 | C3: AdminAllButNotTrade_V1.17 | D3: AdminAll_V1.17 | E3: AdminOrders_V1.17 | F3: AdminServiceRequests_V1.17 | G3: ConfigurePlatformV1.17 | H3: ManageAccountsAndProfiles_V1.17 | I3: ManageAll_V1.17 | J3: ManageAllButNotTrade_v1.16 | K3: ManageFirmAndUser_V1.17 | L3: ManageOrders_V1.17 | M3: ManageServicingandTrades | N3: ManageServiceRequests_V1.17 | O3: ProcessAccounts_V1.17 | P3: ManagePostTrade_V1.17 | Q3: ViewOnlyConfidentialProfile_V1.17 | R3: ManageServicingAndOrders | S3: ManageTransactions_V1.17 | T3: ManageOrdersAndTrades | U3: GlobalAdmin | V3: TBD | W3: TBD | X3: TBD | Y3: TBD | Z3: TBD | AA3: TBD | AB3: TBD
A4: Modules
A5: Onboarding: Form Applications | B5: View | C5: View | D5: View | E5: View to be added (NWPI-14494) | F5: View | H5: View | I5: View | J5: View | L5: View to be added (NWPI-14494) | M5: View to be added (NWPI-14494) | N5: View | O5: View | P5: View to be added (NWPI-14494) | Q5: View | R5: View | S5: View to be added (NWPI-14494) | T5: View to be Added (NWPI-14790) | U5: View | X5: View | Y5: View | Z5: View | AA5: View
A6: Onboarding: Paper Upload | B6: View/Control | C6: View/Control | D6: View/Control | E6: View | F6: View | H6: View/Manage | I6: View/Manage | J6: View/Manage | K6: View - To be removed (NWPI-14667) | L6: View | M6: View | N6: View | O6: View/Process | P6: View | Q6: View | R6: View | S6: View | T6: View to Be Added (NWPI-14791) | U6: View/Control | X6: View/Manage | Y6: View/Control | Z6: View | AA6: View
A7: CRS-FATCA | B7: View/Manage | C7: View/Manage | D7: View/Manage | F7: View | H7: View/Manage | I7: View/Manage | J7: View/Manage | L7: View | M7: View | N7: View | O7: View/Manage | Q7: View | R7: View | S7: View | T7: View | U7: View/Manage | X7: View/Manage | Y7: View/Manage | Z7: View | AA7: View
A8: Servicing | B8: View | C8: View/Manage | D8: View/Manage | E8: View | F8: View/Manage | H8: View | I8: View/Manage | J8: View/Manage | K8: View - To be removed (NWPI-14667) | L8: View | M8: View (exists) Manage to be added (NWPI-14791) | N8: View/Manage | O8: View | P8: View | Q8: View | R8: View/Manage | S8: View Manage to be added NWPI-14791 | U8: View/Manage | X8: View/Manage | Y8: View/Manage
A9: Servicing: Approvals | C9: Control | D9: Control | F9: Control | U9: Control | Y9: Control
A10: Tools | B10: View | C10: View | D10: View | F10: View | H10: View | I10: View | J10: View | K10: View | L10: View | M10: View | N10: View | O10: View | Q10: View | R10: View | S10: View | T10: View | U10: View | X10: View | Y10: View | Z10: View | AA10: View
A11: Orders | B11: View | C11: View | D11: View | E11: View | F11: View | H11: View | I11: View | J11: View | K11: View - To be removed (NWPI-14667) | L11: View | M11: View | N11: View | O11: View | P11: View | Q11: View | R11: View | S11: View | T11: View | U11: View | X11: View | Y11: View | Z11: View | AA11: View
A12: Manage Mutual Fund Orders | D12: Manage | E12: Manage | I12: Manage | L12: Manage | R12: Manage | S12: Manage | T12: Manage | U12: Manage | X12: Manage | Y12: Manage | Z12: Manage
